Workbook

Sheet Guide
A1: 608 Smith Avenue Pro Forma — Guide
A2: Decision model for Oct 2026–May 2030. Base is the default scenario; all yellow cells on Inputs are editable.
A4: Purpose | B4: Use the model to assess Smith occupancy, founder compensation, the optional storefront, and the conditional second venue.
A6: How to use | B6: Action
A7: 1 | B7: Choose Downside, Base, or Upside in Inputs!B4. Dashboard and Annual Summary follow that selection.
A8: 2 | B8: Edit only yellow scenario cells. Formula cells carry cached values and recalculate when opened in Excel.
A9: 3 | B9: Review Smith occupancy and total labor after the six-month storefront ramp, then inspect cash and sensitivities.
A10: 4 | B10: Refresh available cash and resolve founder cash timing and pre-model founder deferred compensation before financing decisions.
A12: Editable input legend | B12: Yellow = editable input; blue/white = formula or explanatory output.
A13: Editable input | B13: Change these assumptions on Inputs; do not overwrite model formulas.
A15: Classification | B15: Meaning
A16: Observed | B16: Historical or snapshot value reported from source records.
A17: Owner-defined | B17: Fact or direction provided by the owner on or before 2026-09-24.
A18: Modeled | B18: Editable planning assumption, conversion, rate, or scenario choice.
A19: Unresolved | B19: Required fact not yet established; the shown value is an explicit modeled default.
A22: Core mechanics
A23: Smith storefront sales solve to the occupancy target after meal prep and frozen pizza, then ramp 35% / 50% / 65% / 80% / 90% / 100% over six months.
A24: Airbnb is nonfood revenue. Events include $1,350 food revenue per event. Personal-chef, Smith meal prep, storefront, and frozen pizza are food revenue.
A25: Food COGS applies only to food revenue; Airbnb variable cost applies only to Airbnb; payment fees are 3% of non-Airbnb revenue.
A26: Founder economic compensation is $7,500/month in total labor. Current cash salary timing, opening deferred balance, and backpay are separate editable inputs.
A27: Founder cash timing and any pre-model deferred balance/back-pay remain unresolved. Oct 2026 cash start and zero backpay are modeled defaults—not owner facts; opening cash is observed.
A28: Happy Monday sandwiches are excluded. Frozen pizza only is modeled, and all pizza is produced at Hopkins. Smith houses meal prep.
A30: Important disclosure
A31: This is a planning financial model, not tax, legal, or accounting advice. It excludes debt service and financing, income and sales taxes, inventory working capital, security deposits, and capital raises. Opening cash is a one-account snapshot, not complete liquidity. Validate assumptions with qualified advisers.

Sheet Inputs
A1: Inputs — Scenario Assumptions
A2: Select a scenario, then edit yellow cells. Classifications distinguish sourced facts from modeled or unresolved values.
A4: Selected Scenario | B4: Base | C4: Base is the default. Dashboard and Annual Summary formulas follow Inputs!B4.
A5: Classification vocabulary: Observed | Owner-defined | Modeled | Unresolved. Yellow cells are editable inputs.
A7: Assumption | B7: Classification | C7: Unit | D7: Downside | E7: Base | F7: Upside | G7: Rationale / provenance
A8: Smith Utilities | B8: Modeled | C8: $/month | D8: 1400 | E8: 1000 | F8: 700 | G8: Transfers to Local Effort in Mar 2027.
A9: Second Venue Activation | B9: Modeled | C9: 0/1 | D9: 0 | E9: 1 | F9: 1 | G9: 1 activates Jan 2027 revenue and $5,000 monthly rent; 0 declines the post-trial venue.
A10: Second Venue Trial Scale | B10: Modeled | C10: % of run-rate | D10: 0.5 | E10: 0.75 | F10: 1 | G10: Scales Oct–Dec 2026 trial revenue; no trial rent was supplied.
A11: Airbnb Weekends / Month | B11: Modeled | C11: weekends | D11: 1.5 | E11: 3 | F11: 4 | G11: Booked weekends at $2,400 each; Airbnb is nonfood revenue.
A12: Airbnb Variable Cost | B12: Modeled | C12: % Airbnb | D12: 0.25 | E12: 0.18 | F12: 0.12 | G12: Variable cost applies only to Airbnb revenue.
A13: Small Events / Month | B13: Modeled | C13: events | D13: 1 | E13: 2 | F13: 3 | G13: Second-venue event count at activated run-rate.
A14: Small Event Revenue / Event | B14: Owner-defined | C14: $/event | D14: 2100 | E14: 2100 | F14: 2100 | G14: $2,100 gross event revenue; $1,350 is food revenue.
A15: Event Food Revenue / Event | B15: Owner-defined | C15: $/event | D15: 1350 | E15: 1350 | F15: 1350 | G15: Food component used for food COGS; remainder is nonfood venue revenue.
A16: Personal Chef Packages / Month | B16: Modeled | C16: packages | D16: 1 | E16: 2 | F16: 4 | G16: Activated second-venue run-rate.
A17: Personal Chef Price | B17: Modeled | C17: $/package | D17: 800 | E17: 1200 | F17: 1800 | G17: Modeled package price; personal-chef revenue is food revenue.
A18: Meal Prep Starting Monthly Revenue | B18: Modeled | C18: $/month | D18: 4334.42 | E18: 4334.42 | F18: 4334.42 | G18: $4,334.42 monthly starting point derived from the owner-provided 4001 dollars per 28-day anchor.
A19: Meal Prep Monthly Growth | B19: Modeled | C19: %/month | D19: 0 | E19: 0.01 | F19: 0.02 | G19: Compounds monthly from Oct 2026.
... A59: Second Venue Activation Date | B59: Owner-defined | C59: date | D59: 46388 | E59: 46388 | F59: 46388 | G59: Jan 2027 activation decision.

Sheet Historical
A1: Historical — Jan to Sep 2026
A2: Observed Local Budget data through 2026-09-30. Food purchases are inventory purchasing, not consumed COGS; founder cash proxy is not economic salary.
A3: May–Sep baseline anchors the starting forecast. Revenue excludes $5,922.27 of Square advances; cash flow replaces $1,459.17 of Debt-category placeholders with settlement remittances.
A5: Observed Metric | B5: 46023 | C5: 46054 | D5: 46082 | E5: 46113 | F5: 46143 | G5: 46174 | H5: 46204 | I5: 46235 | J5: 46266 | K5: Jan–Sep 2026 Total
A6: Net Revenue | B6: 10914.69 | C6: 7379.86 | D6: 6946.7 | E6: 11396.43 | F6: 15096.45 | G6: 10443.78 | H6: 17334.09 | I6: 11466.46 | J6: 10812.43 | K6: =SUM(B6:J6) -> 101790.89
A7: Food Purchases | B7: 1815.23 | C7: 3486.39 | D7: 2630.47 | E7: 3784.26 | F7: 3526.97 | G7: 3325.58 | H7: 4312.22 | I7: 4126.8 | J7: 3326.67 | K7: =SUM(B7:J7) -> 30334.59
A8: Paid Labor | B8: 0 | C8: 40 | D8: 0 | E8: 0 | F8: 560 | G8: 2566 | H8: 1279 | I8: 1642 | J8: 190 | K8: =SUM(B8:J8) -> 6277
A9: Facility Costs | B9: 6350 | C9: 1538 | D9: 1889 | E9: 2180 | F9: 1463.33 | G9: 1525 | H9: 3849.5 | I9: 1133.83 | J9: 1179.02 | K9: =SUM(B9:J9) -> 21107.68
A10: Core Other OpEx | B10: 1137.27 | C10: 977.2 | D10: 1913.49 | E10: 1723.46 | F10: 1579.02 | G10: 2756.47 | H10: 1740.49 | I10: 1571.59 | J10: 787.2 | K10: =SUM(B10:J10) -> 14186.19
A11: Founder Cash Proxy | B11: 1089.73 | C11: 1201.3 | D11: 3677.76 | E11: 3862.46 | F11: 6572.45 | G11: 3297.57 | H11: 1432.52 | I11: 1837.94 | J11: 2020.71 | K11: =SUM(B11:J11) -> 24992.44
A12: Unclassified Transactions | B12: 30.46 | C12: 30.46 | D12: 144.02 | E12: 226.98 | F12: 568.26 | G12: 126.03 | H12: 293.93 | I12: 553.98 | J12: 393.55 | K12: =SUM(B12:J12) -> 2367.67
A13: Adjusted Cash Flow After Debt | B13: 431.43 | C13: 876.96 | D13: 2335.04 | E13: 3291.77 | F13: 1063.48 | G13: -974.88 | H13: 3225.39 | I13: 2428.11 | J13: 2103.5 | K13: =SUM(B13:J13) -> 14780.8
A16: Observed May–Sep baseline | B16: Five-month simple averages; fixed/core other OpEx anchors the editable scenario range.
A17: May–Sep Revenue Baseline | B17: 13030.64
A18: May–Sep Direct Paid Labor Baseline | B18: 1247.4
A19: May–Sep Fixed/Core Other OpEx Baseline | B19: 1686.95

Sheet Model - Downside
A1: 608 Smith Avenue — Downside Scenario
A2: Formula-driven 44-month downside case. Yellow assumptions live on Inputs; outputs below include cached values for non-calculating readers.
A3: Storefront sales are target-driven illustrations, not observed demand. Founder current cash salary and deferred repayment are separate from economic labor cost.
A5: Metric | B5: Unit | C5: Driver / interpretation | D5: 46296 | E5: 46327 | F5: 46357 | G5: 46388 | H5: 46419 | I5: 46447 | J5: 46478 | K5: 46508 | L5: 46539 | M5: 46569 | N5: 46600 | O5: 46631 | P5: 46661 | Q5: 46692 | R5: 46722 | S5: 46753 | T5: 46784 | U5: 46813 | V5: 46844 | W5: 46874 | X5: 46905 | Y5: 46935 | Z5: 46966 | AA5: 46997 | AB5: 47027 | AC5: 47058 | AD5: 47088 | AE5: 47119 | AF5: 47150 | AG5: 47178 | AH5: 47209 | AI5: 47239 | AJ5: 47270 | AK5: 47300 | AL5: 47331 | AM5: 47362 | AN5: 47392 | AO5: 47423 | AP5: 47453 | AQ5: 47484 | AR5: 47515 | AS5: 47543 | AT5: 47574 | AU5: 47604
A6: REVENUE
A7: Meal Prep Revenue | B7: $/month | C7: Smith food revenue; monthly compound growth | D7: ='Inputs'!$D$18*POWER(1+'Inputs'!$D$19,0) -> 4334.42 | E7: ='Inputs'!$D$18*POWER(1+'Inputs'!$D$19,1) -> 4334.42 | F7: ='Inputs'!$D$18*POWER(1+'Inputs'!$D$19,2) -> 4334.42 | G7: ='Inputs'!$D$18*POWER(1+'Inputs'!$D$19,3) -> 4334.42 | H7: ='Inputs'!$D$18*POWER(1+'Inputs'!$D$19,4) -> 4334.42 | I7: ='Inputs'!$D$18*POWER(1+'Inputs'!$D$19,5) -> 4334.42 | J7: ='Inputs'!$D$18*POWER(1+'Inputs'!$D$19,6) -> 4334.42 | K7: ='Inputs'!$D$18*POWER(1+'Inputs'!$D$19,7) -> 4334.42 | L7: ='Inputs'!$D$18*POWER(1+'Inputs'!$D$19,8) -> 4334.42 | M7: ='Inputs'!$D$18*POWER(1+'Inputs'!$D$19,9) -> 4334.42 | N7: ='Inputs'!$D$18*POWER(1+'Inputs'!$D$19,10) -> 4334.42 | O7: ='Inputs'!$D$18*POWER(1+'Inputs'!$D$19,11) -> 4334.42 | P7: ='Inputs'!$D$18*POWER(1+'Inputs'!$D$19,12) -> 4334.42 | Q7: ='Inputs'!$D$18*POWER(1+'Inputs'!$D$19,13) -> 4334.42 | R7: ='Inputs'!$D$18*POWER(1+'Inputs'!$D$19,14) -> 4334.42 | S7: ='Inputs'!$D$18*POWER(1+'Inputs'!$D$19,15) -> 4334.42 | T7: ='Inputs'!$D$18*POWER(1+'Inputs'!$D$19,16) -> 4334.42 | U7: ='Inputs'!$D$18*POWER(1+'Inputs'!$D$19,17) -> 4334.42 | V7: ='Inputs'!$D$18*POWER(1+'Inputs'!$D$19,18) -> 4334.42 | W7: ='Inputs'!$D$18*POWER(1+'Inputs'!$D$19,19) -> 4334.42 | X7: ='Inputs'!$D$18*POWER(1+'Inputs'!$D$19,20) -> 4334.42 | Y7: ='Inputs'!$D$18*POWER(1+'Inputs'!$D$19,21) -> 4334.42 | Z7: ='Inputs'!$D$18*POWER(1+'Inputs'!$D$19,22) -> 4334.42 | AA7: ='Inputs'!$D$18*POWER(1+'Inputs'!$D$19,23) -> 4334.42 | AB7: ='Inputs'!$D$18*POWER(1+'Inputs'!$D$19,24) -> 4334.42 | AC7: ='Inputs'!$D$18*POWER(1+'Inputs'!$D$19,25) -> 4334.42 | AD7: ='Inputs'!$D$18*POWER(1+'Inputs'!$D$19,26) -> 4334.42 | AE7: ='Inputs'!$D$18*POWER(1+'Inputs'!$D$19,27) -> 4334.42 | AF7: ='Inputs'!$D$18*POWER(1+'Inputs'!$D$19,28) -> 4334.42 | AG7: ='Inputs'!$D$18*POWER(1+'Inputs'!$D$19,29) -> 4334.42 | AH7: ='Inputs'!$D$18*POWER(1+'Inputs'!$D$19,30) -> 4334.42 | AI7: ='Inputs'!$D$18*POWER(1+'Inputs'!$D$19,31) -> 4334.42 | AJ7: ='Inputs'!$D$18*POWER(1+'Inputs'!$D$19,32) -> 4334.42 | AK7: ='Inputs'!$D$18*POWER(1+'Inputs'!$D$19,33) -> 4334.42 | AL7: ='Inputs'!$D$18*POWER(1+'Inputs'!$D$19,34) -> 4334.42 | AM7: ='Inputs'!$D$18*POWER(1+'Inputs'!$D$19,35) -> 4334.42 | AN7: ='Inputs'!$D$18*POWER(1+'Inputs'!$D$19,36) -> 4334.42 | AO7: ='Inputs'!$D$18*POWER(1+'Inputs'!$D$19,37) -> 4334.42 | AP7: ='Inputs'!$D$18*POWER(1+'Inputs'!$D$19,38) -> 4334.42 | AQ7: ='Inputs'!$D$18*POWER(1+'Inputs'!$D$19,39) -> 4334.42 | AR7: ='Inputs'!$D$18*POWER(1+'Inputs'!$D$19,40) -> 4334.42 | AS7: ='Inputs'!$D$18*POWER(1+'Inputs'!$D$19,41) -> 4334.42 | AT7: ='Inputs'!$D$18*POWER(1+'Inputs'!$D$19,42) -> 4334.42 | AU7: ='Inputs'!$D$18*POWER(1+'Inputs'!$D$19,43) -> 4334.42
A8: Frozen Pizza Revenue | B8: $/month | C8: Starting units × realized price × unit growth; produced at Hopkins | D8: ='Inputs'!$D$20*POWER(1+'Inputs'!$D$22,0)*'Inputs'!$D$21 -> 810 | E8: ='Inputs'!$D$20*POWER(1+'Inputs'!$D$22,1)*'Inputs'!$D$21 -> 810 | F8: ='Inputs'!$D$20*POWER(1+'Inputs'!$D$22,2)*'Inputs'!$D$21 -> 810 | G8: ='Inputs'!$D$20*POWER(1+'Inputs'!$D$22,3)*'Inputs'!$D$21 -> 810 | H8: ='Inputs'!$D$20*POWER(1+'Inputs'!$D$22,4)*'Inputs'!$D$21 -> 810 | I8: ='Inputs'!$D$20*POWER(1+'Inputs'!$D$22,5)*'Inputs'!$D$21 -> 810 | J8: ='Inputs'!$D$20*POWER(1+'Inputs'!$D$22,6)*'Inputs'!$D$21 -> 810 | K8: ='Inputs'!$D$20*POWER(1+'Inputs'!$D$22,7)*'Inputs'!$D$21 -> 810 | L8: ='Inputs'!$D$20*POWER(1+'Inputs'!$D$22,8)*'Inputs'!$D$21 -> 810 | M8: ='Inputs'!$D$20*POWER(1+'Inputs'!$D$22,9)*'Inputs'!$D$21 -> 810 | N8: ='Inputs'!$D$20*POWER(1+'Inputs'!$D$22,10)*'Inputs'!$D$21 -> 810 | O8: ='Inputs'!$D$20*POWER(1+'Inputs'!$D$22,11)*'Inputs'!$D$21 -> 810 | P8: ='Inputs'!$D$20*POWER(1+'Inputs'!$D$22,12)*'Inputs'!$D$21 -> 810 | Q8: ='Inputs'!$D$20*POWER(1+'Inputs'!$D$22,13)*'Inputs'!$D$21 -> 810 | R8: ='Inputs'!$D$20*POWER(1+'Inputs'!$D$22,14)*'Inputs'!$D$21 -> 810 | S8: ='Inputs'!$D$20*POWER(1+'Inputs'!$D$22,15)*'Inputs'!$D$21 -> 810 | T8: ='Inputs'!$D$20*POWER(1+'Inputs'!$D$22,16)*'Inputs'!$D$21 -> 810 | U8: ='Inputs'!$D$20*POWER(1+'Inputs'!$D$22,17)*'Inputs'!$D$21 -> 810 | V8: ='Inputs'!$D$20*POWER(1+'Inputs'!$D$22,18)*'Inputs'!$D$21 -> 810 | W8: ='Inputs'!$D$20*POWER(1+'Inputs'!$D$22,19)*'Inputs'!$D$21 -> 810 | X8: ='Inputs'!$D$20*POWER(1+'Inputs'!$D$22,20)*'Inputs'!$D$21 -> 810 | Y8: ='Inputs'!$D$20*POWER(1+'Inputs'!$D$22,21)*'Inputs'!$D$21 -> 810 | Z8: ='Inputs'!$D$20*POWER(1+'Inputs'!$D$22,22)*'Inputs'!$D$21 -> 810 | AA8: ='Inputs'!$D$20*POWER(1+'Inputs'!$D$22,23)*'Inputs'!$D$21 -> 810 | AB8: ='Inputs'!$D$20*POWER(1+'Inputs'!$D$22,24)*'Inputs'!$D$21 -> 810 | AC8: ='Inputs'!$D$20*POWER(1+'Inputs'!$D$22,25)*'Inputs'!$D$21 -> 810 | AD8: ='Inputs'!$D$20*POWER(1+'Inputs'!$D$22,26)*'Inputs'!$D$21 -> 810 | AE8: ='Inputs'!$D$20*POWER(1+'Inputs'!$D$22,27)*'Inputs'!$D$21 -> 810 | AF8: ='Inputs'!$D$20*POWER(1+'Inputs'!$D$22,28)*'Inputs'!$D$21 -> 810 | AG8: ='Inputs'!$D$20*POWER(1+'Inputs'!$D$22,29)*'Inputs'!$D$21 -> 810 | AH8: ='Inputs'!$D$20*POWER(1+'Inputs'!$D$22,30)*'Inputs'!$D$21 -> 810 | AI8: ='Inputs'!$D$20*POWER(1+'Inputs'!$D$22,31)*'Inputs'!$D$21 -> 810 | AJ8: ='Inputs'!$D$20*POWER(1+'Inputs'!$D$22,32)*'Inputs'!$D$21 -> 810 | AK8: ='Inputs'!$D$20*POWER(1+'Inputs'!$D$22,33)*'Inputs'!$D$21 -> 810 | AL8: ='Inputs'!$D$20*POWER(1+'Inputs'!$D$22,34)*'Inputs'!$D$21 -> 810 | AM8: ='Inputs'!$D$20*POWER(1+'Inputs'!$D$22,35)*'Inputs'!$D$21 -> 810 | AN8: ='Inputs'!$D$20*POWER(1+'Inputs'!$D$22,36)*'Inputs'!$D$21 -> 810 | AO8: ='Inputs'!$D$20*POWER(1+'Inputs'!$D$22,37)*'Inputs'!$D$21 -> 810 | AP8: ='Inputs'!$D$20*POWER(1+'Inputs'!$D$22,38)*'Inputs'!$D$21 -> 810 | AQ8: ='Inputs'!$D$20*POWER(1+'Inputs'!$D$22,39)*'Inputs'!$D$21 -> 810 | AR8: ='Inputs'!$D$20*POWER(1+'Inputs'!$D$22,40)*'Inputs'!$D$21 -> 810 | AS8: ='Inputs'!$D$20*POWER(1+'Inputs'!$D$22,41)*'Inputs'!$D$21 -> 810 | AT8: ='Inputs'!$D$20*POWER(1+'Inputs'!$D$22,42)*'Inputs'!$D$21 -> 810 | AU8: ='Inputs'!$D$20*POWER(1+'Inputs'!$D$22,43)*'Inputs'!$D$21 -> 810
A9: Storefront Revenue | B9: $/month | C9: Required Smith sales after meal prep and frozen pizza × six-month ramp | D9: =MAX(0,D36-D7-D8)*(IF(D$5<'Inputs'!$D$23,0,CHOOSE(MIN(7,MAX(1,(YEAR(D$5)-YEAR('Inputs'!$D$23))*12+MONTH(D$5)-MONTH('Inputs'!$D$23)+1)),'Inputs'!$D$50,'Inputs'!$D$51,'Inputs'!$D$52,'Inputs'!$D$53,'Inputs'!$D$54,'Inputs'!$D$55,'Inputs'!$D$55))) -> 0 | E9: =MAX(0,E36-E7-E8)*(IF(E$5<'Inputs'!$D$23,0,CHOOSE(MIN(7,MAX(1,(YEAR(E$5)-YEAR('Inputs'!$D$23))*12+MONTH(E$5)-MONTH('Inputs'!$D$23)+1)),'Inputs'!$D$50,'Inputs'!$D$51,'Inputs'!$D$52,'Inputs'!$D$53,'Inputs'!$D$54,'Inputs'!$D$55,'Inputs'!$D$55))) -> 0 | F9: =MAX(0,F36-F7-F8)*(IF(F$5<'Inputs'!$D$23,0,CHOOSE(MIN(7,MAX(1,(YEAR(F$5)-YEAR('Inputs'!$D$23))*12+MONTH(F$5)-MONTH('Inputs'!$D$23)+1)),'Inputs'!$D$50,'Inputs'!$D$51,'Inputs'!$D$52,'Inputs'!$D$53,'Inputs'!$D$54,'Inputs'!$D$55,'Inputs'!$D$55))) -> 0 | G9: =MAX(0,G36-G7-G8)*(IF(G$5<'Inputs'!$D$23,0,CHOOSE(MIN(7,MAX(1,(YEAR(G$5)-YEAR('Inputs'!$D$23))*12+MONTH(G$5)-MONTH('Inputs'!$D$23)+1)),'Inputs'!$D$50,'Inputs'!$D$51,'Inputs'!$D$52,'Inputs'!$D$53,'Inputs'!$D$54,'Inputs'!$D$55,'Inputs'!$D$55))) -> 0 | H9: =MAX(0,H36-H7-H8)*(IF(H$5<'Inputs'!$D$23,0,CHOOSE(MIN(7,MAX(1,(YEAR(H$5)-YEAR('Inputs'!$D$23))*12+MONTH(H$5)-MONTH('Inputs'!$D$23)+1)),'Inputs'!$D$50,'Inputs'!$D$51,'Inputs'!$D$52,'Inputs'!$D$53,'Inputs'!$D$54,'Inputs'!$D$55,'Inputs'!$D$55))) -> 0 | I9: =MAX(0,I36-I7-I8)*(IF(I$5<'Inputs'!$D$23,0,CHOOSE(MIN(7,MAX(1,(YEAR(I$5)-YEAR('Inputs'!$D$23))*12+MONTH(I$5)-MONTH('Inputs'!$D$23)+1)),'Inputs'!$D$50,'Inputs'!$D$51,'Inputs'!$D$52,'Inputs'!$D$53,'Inputs'!$D$54,'Inputs'!$D$55,'Inputs'!$D$55))) -> 0 | J9: =MAX(0,J36-J7-J8)*(IF(J$5<'Inputs'!$D$23,0,CHOOSE(MIN(7,MAX(1,(YEAR(J$5)-YEAR('Inputs'!$D$23))*12+MONTH(J$5)-MONTH('Inputs'!$D$23)+1)),'Inputs'!$D$50,'Inputs'!$D$51,'Inputs'!$D$52,'Inputs'!$D$53,'Inputs'!$D$54,'Inputs'!$D$55,'Inputs'!$D$55))) -> 0 | K9: =MAX(0,K36-K7-K8)*(IF(K$5<'Inputs'!$D$23,0,CHOOSE(MIN(7,MAX(1,(YEAR(K$5)-YEAR('Inputs'!$D$23))*12+MONTH(K$5)-MONTH('Inputs'!$D$23)+1)),'Inputs'!$D$50,'Inputs'!$D$51,'Inputs'!$D$52,'Inputs'!$D$53,'Inputs'!$D$54,'Inputs'!$D$55,'Inputs'!$D$55))) -> 0 | ... AU9: =MAX(0,AU36-AU7-AU8)*(IF(AU$5<'Inputs'!$D$23,0,CHOOSE(MIN(7,MAX(1,(YEAR(AU$5)-YEAR('Inputs'!$D$23))*12+MONTH(AU$5)-MONTH('Inputs'!$D$23)+1)),'Inputs'!$D$50,'Inputs'!$D$51,'Inputs'!$D$52,'Inputs'!$D$53,'Inputs'!$D$54,'Inputs'!$D$55,'Inputs'!$D$55))) -> 48485.58
A10: Smith Revenue | B10: $/month | C10: Meal prep + frozen pizza + storefront | D10: =SUM(D7:D9) -> 5144.42 | E10: =SUM(E7:E9) -> 5144.42 | F10: =SUM(F7:F9) -> 5144.42 | G10: =SUM(G7:G9) -> 5144.42 | H10: =SUM(H7:H9) -> 5144.42 | I10: =SUM(I7:I9) -> 5144.42 | J10: =SUM(J7:J9) -> 5144.42 | K10: =SUM(K7:K9) -> 5144.42 | ... AU10: =SUM(AU7:AU9) -> 53630
A11: Airbnb Revenue | B11: $/month | C11: Nonfood revenue at the second venue | D11: ='Inputs'!$D$11*'Inputs'!$D$48*(IF(D$5<'Inputs'!$D$57,0,IF(D$5<='Inputs'!$D$58,'Inputs'!$D$10,IF(D$5>='Inputs'!$D$59,'Inputs'!$D$9,0)))) -> 1800 | E11: ='Inputs'!$D$11*'Inputs'!$D$48*(IF(E$5<'Inputs'!$D$57,0,IF(E$5<='Inputs'!$D$58,'Inputs'!$D$10,IF(E$5>='Inputs'!$D$59,'Inputs'!$D$9,0)))) -> 1800 | F11: ='Inputs'!$D$11*'Inputs'!$D$48*(IF(F$5<'Inputs'!$D$57,0,IF(F$5<='Inputs'!$D$58,'Inputs'!$D$10,IF(F$5>='Inputs'!$D$59,'Inputs'!$D$9,0)))) -> 1800 | G11: ='Inputs'!$D$11*'Inputs'!$D$48*(IF(G$5<'Inputs'!$D$57,0,IF(G$5<='Inputs'!$D$58,'Inputs'!$D$10,IF(G$5>='Inputs'!$D$59,'Inputs'!$D$9,0)))) -> 0 | H11: ='Inputs'!$D$11*'Inputs'!$D$48*(IF(H$5<'Inputs'!$D$57,0,IF(H$5<='Inputs'!$D$58,'Inputs'!$D$10,IF(H$5>='Inputs'!$D$59,'Inputs'!$D$9,0)))) -> 0 | I11: ='Inputs'!$D$11*'Inputs'!$D$48*(IF(I$5<'Inputs'!$D$57,0,IF(I$5<='Inputs'!$D$58,'Inputs'!$D$10,IF(I$5>='Inputs'!$D$59,'Inputs'!$D$9,0)))) -> 0 | J11: ='Inputs'!$D$11*'Inputs'!$D$48*(IF(J$5<'Inputs'!$D$57,0,IF(J$5<='Inputs'!$D$58,'Inputs'!$D$10,IF(J$5>='Inputs'!$D$59,'Inputs'!$D$9,0)))) -> 0 | K11: ='Inputs'!$D$11*'Inputs'!$D$48*(IF(K$5<'Inputs'!$D$57,0,IF(K$5<='Inputs'!$D$58,'Inputs'!$D$10,IF(K$5>='Inputs'!$D$59,'Inputs'!$D$9,0)))) -> 0 | ... AU11: ='Inputs'!$D$11*'Inputs'!$D$48*(IF(AU$5<'Inputs'!$D$57,0,IF(AU$5<='Inputs'!$D$58,'Inputs'!$D$10,IF(AU$5>='Inputs'!$D$59,'Inputs'!$D$9,0)))) -> 0
A12: Small Events Revenue | B12: $/month | C12: Gross small-event revenue | D12: ='Inputs'!$D$13*'Inputs'!$D$14*(IF(D$5<'Inputs'!$D$57,0,IF(D$5<='Inputs'!$D$58,'Inputs'!$D$10,IF(D$5>='Inputs'!$D$59,'Inputs'!$D$9,0)))) -> 1050 | E12: ='Inputs'!$D$13*'Inputs'!$D$14*(IF(E$5<'Inputs'!$D$57,0,IF(E$5<='Inputs'!$D$58,'Inputs'!$D$10,IF(E$5>='Inputs'!$D$59,'Inputs'!$D$9,0)))) -> 1050 | F12: ='Inputs'!$D$13*'Inputs'!$D$14*(IF(F$5<'Inputs'!$D$57,0,IF(F$5<='Inputs'!$D$58,'Inputs'!$D$10,IF(F$5>='Inputs'!$D$59,'Inputs'!$D$9,0)))) -> 1050 | G12: ='Inputs'!$D$13*'Inputs'!$D$14*(IF(G$5<'Inputs'!$D$57,0,IF(G$5<='Inputs'!$D$58,'Inputs'!$D$10,IF(G$5>='Inputs'!$D$59,'Inputs'!$D$9,0)))) -> 0 | H12: ='Inputs'!$D$13*'Inputs'!$D$14*(IF(H$5<'Inputs'!$D$57,0,IF(H$5<='Inputs'!$D$58,'Inputs'!$D$10,IF(H$5>='Inputs'!$D$59,'Inputs'!$D$9,0)))) -> 0 | I12: ='Inputs'!$D$13*'Inputs'!$D$14*(IF(I$5<'Inputs'!$D$57,0,IF(I$5<='Inputs'!$D$58,'Inputs'!$D$10,IF(I$5>='Inputs'!$D$59,'Inputs'!$D$9,0)))) -> 0 | J12: ='Inputs'!$D$13*'Inputs'!$D$14*(IF(J$5<'Inputs'!$D$57,0,IF(J$5<='Inputs'!$D$58,'Inputs'!$D$10,IF(J$5>='Inputs'!$D$59,'Inputs'!$D$9,0)))) -> 0 | K12: ='Inputs'!$D$13*'Inputs'!$D$14*(IF(K$5<'Inputs'!$D$57,0,IF(K$5<='Inputs'!$D$58,'Inputs'!$D$10,IF(K$5>='Inputs'!$D$59,'Inputs'!$D$9,0)))) -> 0 | ... AU12: ='Inputs'!$D$13*'Inputs'!$D$14*(IF(AU$5<'Inputs'!$D$57,0,IF(AU$5<='Inputs'!$D$58,'Inputs'!$D$10,IF(AU$5>='Inputs'!$D$59,'Inputs'!$D$9,0)))) -> 0
A13: Personal Chef Revenue | B13: $/month | C13: Food revenue from packages at the second venue | D13: ='Inputs'!$D$16*'Inputs'!$D$17*(IF(D$5<'Inputs'!$D$57,0,IF(D$5<='Inputs'!$D$58,'Inputs'!$D$10,IF(D$5>='Inputs'!$D$59,'Inputs'!$D$9,0)))) -> 400 | E13: ='Inputs'!$D$16*'Inputs'!$D$17*(IF(E$5<'Inputs'!$D$57,0,IF(E$5<='Inputs'!$D$58,'Inputs'!$D$10,IF(E$5>='Inputs'!$D$59,'Inputs'!$D$9,0)))) -> 400 | F13: ='Inputs'!$D$16*'Inputs'!$D$17*(IF(F$5<'Inputs'!$D$57,0,IF(F$5<='Inputs'!$D$58,'Inputs'!$D$10,IF(F$5>='Inputs'!$D$59,'Inputs'!$D$9,0)))) -> 400 | G13: ='Inputs'!$D$16*'Inputs'!$D$17*(IF(G$5<'Inputs'!$D$57,0,IF(G$5<='Inputs'!$D$58,'Inputs'!$D$10,IF(G$5>='Inputs'!$D$59,'Inputs'!$D$9,0)))) -> 0 | H13: ='Inputs'!$D$16*'Inputs'!$D$17*(IF(H$5<'Inputs'!$D$57,0,IF(H$5<='Inputs'!$D$58,'Inputs'!$D$10,IF(H$5>='Inputs'!$D$59,'Inputs'!$D$9,0)))) -> 0 | I13: ='Inputs'!$D$16*'Inputs'!$D$17*(IF(I$5<'Inputs'!$D$57,0,IF(I$5<='Inputs'!$D$58,'Inputs'!$D$10,IF(I$5>='Inputs'!$D$59,'Inputs'!$D$9,0)))) -> 0 | J13: ='Inputs'!$D$16*'Inputs'!$D$17*(IF(J$5<'Inputs'!$D$57,0,IF(J$5<='Inputs'!$D$58,'Inputs'!$D$10,IF(J$5>='Inputs'!$D$59,'Inputs'!$D$9,0)))) -> 0 | K13: ='Inputs'!$D$16*'Inputs'!$D$17*(IF(K$5<'Inputs'!$D$57,0,IF(K$5<='Inputs'!$D$58,'Inputs'!$D$10,IF(K$5>='Inputs'!$D$59,'Inputs'!$D$9,0)))) -> 0 | ... AU13: ='Inputs'!$D$16*'Inputs'!$D$17*(IF(AU$5<'Inputs'!$D$57,0,IF(AU$5<='Inputs'!$D$58,'Inputs'!$D$10,IF(AU$5>='Inputs'!$D$59,'Inputs'!$D$9,0)))) -> 0
A14: Second Venue Revenue | B14: $/month | C14: Airbnb + small events + personal chef | D14: =SUM(D11:D13) -> 3250 | E14: =SUM(E11:E13) -> 3250 | F14: =SUM(F11:F13) -> 3250 | G14: =SUM(G11:G13) -> 0 | H14: =SUM(H11:H13) -> 0 | I14: =SUM(I11:I13) -> 0 | J14: =SUM(J11:J13) -> 0 | K14: =SUM(K11:K13) -> 0 | ... AU14: =SUM(AU11:AU13) -> 0
A15: Total Revenue | B15: $/month | C15: Smith + second venue | D15: =D10+D14 -> 8394.42 | E15: =E10+E14 -> 8394.42 | F15: =F10+F14 -> 8394.42 | G15: =G10+G14 -> 5144.42 | H15: =H10+H14 -> 5144.42 | I15: =I10+I14 -> 5144.42 | J15: =J10+J14 -> 5144.42 | K15: =K10+K14 -> 5144.42 | ... AU15: =AU10+AU14 -> 53630
A16: Food Revenue | B16: $/month | C16: Smith + event food component + personal chef | D16: =D10+'Inputs'!$D$13*'Inputs'!$D$15*(IF(D$5<'Inputs'!$D$57,0,IF(D$5<='Inputs'!$D$58,'Inputs'!$D$10,IF(D$5>='Inputs'!$D$59,'Inputs'!$D$9,0))))+D13 -> 6219.42 | E16: =E10+'Inputs'!$D$13*'Inputs'!$D$15*(IF(E$5<'Inputs'!$D$57,0,IF(E$5<='Inputs'!$D$58,'Inputs'!$D$10,IF(E$5>='Inputs'!$D$59,'Inputs'!$D$9,0))))+E13 -> 6219.42 | F16: =F10+'Inputs'!$D$13*'Inputs'!$D$15*(IF(F$5<'Inputs'!$D$57,0,IF(F$5<='Inputs'!$D$58,'Inputs'!$D$10,IF(F$5>='Inputs'!$D$59,'Inputs'!$D$9,0))))+F13 -> 6219.42 | G16: =G10+'Inputs'!$D$13*'Inputs'!$D$15*(IF(G$5<'Inputs'!$D$57,0,IF(G$5<='Inputs'!$D$58,'Inputs'!$D$10,IF(G$5>='Inputs'!$D$59,'Inputs'!$D$9,0))))+G13 -> 5144.42 | H16: =H10+'Inputs'!$D$13*'Inputs'!$D$15*(IF(H$5<'Inputs'!$D$57,0,IF(H$5<='Inputs'!$D$58,'Inputs'!$D$10,IF(H$5>='Inputs'!$D$59,'Inputs'!$D$9,0))))+H13 -> 5144.42 | I16: =I10+'Inputs'!$D$13*'Inputs'!$D$15*(IF(I$5<'Inputs'!$D$57,0,IF(I$5<='Inputs'!$D$58,'Inputs'!$D$10,IF(I$5>='Inputs'!$D$59,'Inputs'!$D$9,0))))+I13 -> 5144.42 | J16: =J10+'Inputs'!$D$13*'Inputs'!$D$15*(IF(J$5<'Inputs'!$D$57,0,IF(J$5<='Inputs'!$D$58,'Inputs'!$D$10,IF(J$5>='Inputs'!$D$59,'Inputs'!$D$9,0))))+J13 -> 5144.42 | K16: =K10+'Inputs'!$D$13*'Inputs'!$D$15*(IF(K$5<'Inputs'!$D$57,0,IF(K$5<='Inputs'!$D$58,'Inputs'!$D$10,IF(K$5>='Inputs'!$D$59,'Inputs'!$D$9,0))))+K13 -> 5144.42 | ... AU16: =AU10+'Inputs'!$D$13*'Inputs'!$D$15*(IF(AU$5<'Inputs'!$D$57,0,IF(AU$5<='Inputs'!$D$58,'Inputs'!$D$10,IF(AU$5>='Inputs'!$D$59,'Inputs'!$D$9,0))))+AU13 -> 53630
A17: COST OF SALES & LABOR
A18: Food COGS | B18: $/month | C18: Applied only to food revenue | D18: =D16*'Inputs'!$D$27 -> 1368.2724 | E18: =E16*'Inputs'!$D$27 -> 1368.2724 | F18: =F16*'Inputs'!$D$27 -> 1368.2724 | G18: =G16*'Inputs'!$D$27 -> 1131.7724 | H18: =H16*'Inputs'!$D$27 -> 1131.7724 | I18: =I16*'Inputs'!$D$27 -> 1131.7724 | J18: =J16*'Inputs'!$D$27 -> 1131.7724 | K18: =K16*'Inputs'!$D$27 -> 1131.7724 | ... AU18: =AU16*'Inputs'!$D$27 -> 11798.6
A19: Food Cost % | B19: % revenue | C19: Food COGS ÷ food revenue | D19: =IFERROR(D18/D16,0) -> 0.22 | E19: =IFERROR(E18/E16,0) -> 0.22 | F19: =IFERROR(F18/F16,0) -> 0.22 | G19: =IFERROR(G18/G16,0) -> 0.22 | H19: =IFERROR(H18/H16,0) -> 0.22 | I19: =IFERROR(I18/I16,0) -> 0.22 | J19: =IFERROR(J18/J16,0) -> 0.22 | K19: =IFERROR(K18/K16,0) -> 0.22 | ... AU19: =IFERROR(AU18/AU16,0) -> 0.22
A20: Venue Variable Cost | B20: $/month | C20: Applied only to Airbnb revenue | D20: =D11*'Inputs'!$D$12 -> 450 | E20: =E11*'Inputs'!$D$12 -> 450 | F20: =F11*'Inputs'!$D$12 -> 450 | G20: =G11*'Inputs'!$D$12 -> 0 | H20: =H11*'Inputs'!$D$12 -> 0 | I20: =I11*'Inputs'!$D$12 -> 0 | J20: =J11*'Inputs'!$D$12 -> 0 | K20: =K11*'Inputs'!$D$12 -> 0 | ... AU20: =AU11*'Inputs'!$D$12 -> 0
A21: Packaging & Delivery | B21: $/month | C21: Applied to food revenue | D21: =D16*'Inputs'!$D$37 -> 248.7768 | E21: =E16*'Inputs'!$D$37 -> 248.7768 | F21: =F16*'Inputs'!$D$37 -> 248.7768 | G21: =G16*'Inputs'!$D$37 -> 205.7768 | H21: =H16*'Inputs'!$D$37 -> 205.7768 | I21: =I16*'Inputs'!$D$37 -> 205.7768 | J21: =J16*'Inputs'!$D$37 -> 205.7768 | K21: =K16*'Inputs'!$D$37 -> 205.7768 | ... AU21: =AU16*'Inputs'!$D$37 -> 2145.2
A22: Direct Paid Labor | B22: $/month | C22: Phase rate × total revenue | D22: =D15*(IF(D$5<'Inputs'!$D$23,'Inputs'!$D$28,IF(D$5<EDATE('Inputs'!$D$23,6),'Inputs'!$D$29,'Inputs'!$D$30))) -> 1259.163 | E22: =E15*(IF(E$5<'Inputs'!$D$23,'Inputs'!$D$28,IF(E$5<EDATE('Inputs'!$D$23,6),'Inputs'!$D$29,'Inputs'!$D$30))) -> 1259.163 | F22: =F15*(IF(F$5<'Inputs'!$D$23,'Inputs'!$D$28,IF(F$5<EDATE('Inputs'!$D$23,6),'Inputs'!$D$29,'Inputs'!$D$30))) -> 1259.163 | G22: =G15*(IF(G$5<'Inputs'!$D$23,'Inputs'!$D$28,IF(G$5<EDATE('Inputs'!$D$23,6),'Inputs'!$D$29,'Inputs'!$D$30))) -> 771.663 | H22: =H15*(IF(H$5<'Inputs'!$D$23,'Inputs'!$D$28,IF(H$5<EDATE('Inputs'!$D$23,6),'Inputs'!$D$29,'Inputs'!$D$30))) -> 771.663 | I22: =I15*(IF(I$5<'Inputs'!$D$23,'Inputs'!$D$28,IF(I$5<EDATE('Inputs'!$D$23,6),'Inputs'!$D$29,'Inputs'!$D$30))) -> 771.663 | J22: =J15*(IF(J$5<'Inputs'!$D$23,'Inputs'!$D$28,IF(J$5<EDATE('Inputs'!$D$23,6),'Inputs'!$D$29,'Inputs'!$D$30))) -> 771.663 | K22: =K15*(IF(K$5<'Inputs'!$D$23,'Inputs'!$D$28,IF(K$5<EDATE('Inputs'!$D$23,6),'Inputs'!$D$29,'Inputs'!$D$30))) -> 771.663 | ... AU22: =AU15*(IF(AU$5<'Inputs'!$D$23,'Inputs'!$D$28,IF(AU$5<EDATE('Inputs'!$D$23,6),'Inputs'!$D$29,'Inputs'!$D$30))) -> 10726
A23: Founder Economic Salary | B23: $/month | C23: Catherine + Weston combined economic compensation | D23: ='Inputs'!$D$32 -> 7500 | E23: ='Inputs'!$D$32 -> 7500 | F23: ='Inputs'!$D$32 -> 7500 | G23: ='Inputs'!$D$32 -> 7500 | H23: ='Inputs'!$D$32 -> 7500 | I23: ='Inputs'!$D$32 -> 7500 | J23: ='Inputs'!$D$32 -> 7500 | K23: ='Inputs'!$D$32 -> 7500 | ... AU23: ='Inputs'!$D$32 -> 7500
A24: Direct Payroll Burden | B24: $/month | C24: Burden on direct paid labor | D24: =D22*'Inputs'!$D$31 -> 151.09956 | E24: =E22*'Inputs'!$D$31 -> 151.09956 | F24: =F22*'Inputs'!$D$31 -> 151.09956 | G24: =G22*'Inputs'!$D$31 -> 92.59956 | H24: =H22*'Inputs'!$D$31 -> 92.59956 | I24: =I22*'Inputs'!$D$31 -> 92.59956 | J24: =J22*'Inputs'!$D$31 -> 92.59956 | K24: =K22*'Inputs'!$D$31 -> 92.59956 | ... AU24: =AU22*'Inputs'!$D$31 -> 1287.12
A25: Total Labor | B25: $/month | C25: Direct labor + founder economic compensation + burden | D25: =SUM(D22,D23,D24) -> 8910.2626 | E25: =SUM(E22,E23,E24) -> 8910.2626 | F25: =SUM(F22,F23,F24) -> 8910.2626 | G25: =SUM(G22,G23,G24) -> 8364.2626 | H25: =SUM(H22,H23,H24) -> 8364.2626 | I25: =SUM(I22,I23,I24) -> 8364.2626 | J25: =SUM(J22,J23,J24) -> 8364.2626 | K25: =SUM(K22,K23,K24) -> 8364.2626 | ... AU25: =SUM(AU22,AU23,AU24) -> 19513.12
A26: Total Labor % | B26: % revenue | C26: Total labor ÷ total revenue | D26: =IFERROR(D25/D15,0) -> 1.0614506 | E26: =IFERROR(E25/E15,0) -> 1.0614506 | F26: =IFERROR(F25/F15,0) -> 1.0614506 | G26: =IFERROR(G25/G15,0) -> 1.6258903 | H26: =IFERROR(H25/H15,0) -> 1.6258903 | I26: =IFERROR(I25/I15,0) -> 1.6258903 | J26: =IFERROR(J25/J15,0) -> 1.6258903 | K26: =IFERROR(K25/K15,0) -> 1.6258903 | ... AU26: =IFERROR(AU25/AU15,0) -> 0.3638471
A27: OCCUPANCY & REQUIRED SALES
A28: Smith Rent & NNN | B28: $/month | C28: Owner-provided stepped rent schedule | D28: =IF(D$5<DATE(2026,10,1),'Inputs'!$D$41,IF(D$5<DATE(2027,1,1),'Inputs'!$D$42,IF(D$5<DATE(2027,6,1),'Inputs'!$D$43,IF(D$5<DATE(2028,1,1),'Inputs'!$D$44,'Inputs'!$D$45)))) -> 1800 | E28: =IF(E$5<DATE(2026,10,1),'Inputs'!$D$41,IF(E$5<DATE(2027,1,1),'Inputs'!$D$42,IF(E$5<DATE(2027,6,1),'Inputs'!$D$43,IF(E$5<DATE(2028,1,1),'Inputs'!$D$44,'Inputs'!$D$45)))) -> 1800 | F28: =IF(F$5<DATE(2026,10,1),'Inputs'!$D$41,IF(F$5<DATE(2027,1,1),'Inputs'!$D$42,IF(F$5<DATE(2027,6,1),'Inputs'!$D$43,IF(F$5<DATE(2028,1,1),'Inputs'!$D$44,'Inputs'!$D$45)))) -> 1800 | G28: =IF(G$5<DATE(2026,10,1),'Inputs'!$D$41,IF(G$5<DATE(2027,1,1),'Inputs'!$D$42,IF(G$5<DATE(2027,6,1),'Inputs'!$D$43,IF(G$5<DATE(2028,1,1),'Inputs'!$D$44,'Inputs'!$D$45)))) -> 2600 | H28: =IF(H$5<DATE(2026,10,1),'Inputs'!$D$41,IF(H$5<DATE(2027,1,1),'Inputs'!$D$42,IF(H$5<DATE(2027,6,1),'Inputs'!$D$43,IF(H$5<DATE(2028,1,1),'Inputs'!$D$44,'Inputs'!$D$45)))) -> 2600 | I28: =IF(I$5<DATE(2026,10,1),'Inputs'!$D$41,IF(I$5<DATE(2027,1,1),'Inputs'!$D$42,IF(I$5<DATE(2027,6,1),'Inputs'!$D$43,IF(I$5<DATE(2028,1,1),'Inputs'!$D$44,'Inputs'!$D$45)))) -> 2600 | J28: =IF(J$5<DATE(2026,10,1),'Inputs'!$D$41,IF(J$5<DATE(2027,1,1),'Inputs'!$D$42,IF(J$5<DATE(2027,6,1),'Inputs'!$D$43,IF(J$5<DATE(2028,1,1),'Inputs'!$D$44,'Inputs'!$D$45)))) -> 2600 | K28: =IF(K$5<DATE(2026,10,1),'Inputs'!$D$41,IF(K$5<DATE(2027,1,1),'Inputs'!$D$42,IF(K$5<DATE(2027,6,1),'Inputs'!$D$43,IF(K$5<DATE(2028,1,1),'Inputs'!$D$44,'Inputs'!$D$45)))) -> 2600 | ... AU28: =IF(AU$5<DATE(2026,10,1),'Inputs'!$D$41,IF(AU$5<DATE(2027,1,1),'Inputs'!$D$42,IF(AU$5<DATE(2027,6,1),'Inputs'!$D$43,IF(AU$5<DATE(2028,1,1),'Inputs'!$D$44,'Inputs'!$D$45)))) -> 3963
A29: Smith Utilities | B29: $/month | C29: Begins on the editable transfer date | D29: =IF(D$5>='Inputs'!$D$46,'Inputs'!$D$8,0) -> 0 | E29: =IF(E$5>='Inputs'!$D$46,'Inputs'!$D$8,0) -> 0 | F29: =IF(F$5>='Inputs'!$D$46,'Inputs'!$D$8,0) -> 0 | G29: =IF(G$5>='Inputs'!$D$46,'Inputs'!$D$8,0) -> 0 | H29: =IF(H$5>='Inputs'!$D$46,'Inputs'!$D$8,0) -> 0 | I29: =IF(I$5>='Inputs'!$D$46,'Inputs'!$D$8,0) -> 1400 | J29: =IF(J$5>='Inputs'!$D$46,'Inputs'!$D$8,0) -> 1400 | K29: =IF(K$5>='Inputs'!$D$46,'Inputs'!$D$8,0) -> 1400 | ... AU29: =IF(AU$5>='Inputs'!$D$46,'Inputs'!$D$8,0) -> 1400
A30: Smith Occupancy Cost | B30: $/month | C30: Smith rent + utilities | D30: =SUM(D28:D29) -> 1800 | E30: =SUM(E28:E29) -> 1800 | F30: =SUM(F28:F29) -> 1800 | G30: =SUM(G28:G29) -> 2600 | H30: =SUM(H28:H29) -> 2600 | I30: =SUM(I28:I29) -> 4000 | J30: =SUM(J28:J29) -> 4000 | K30: =SUM(K28:K29) -> 4000 | ... AU30: =SUM(AU28:AU29) -> 5363
A31: Second Venue Rent | B31: $/month | C31: Conditional on post-trial activation | D31: =IF(D$5>='Inputs'!$D$59,'Inputs'!$D$9*'Inputs'!$D$47,0) -> 0 | E31: =IF(E$5>='Inputs'!$D$59,'Inputs'!$D$9*'Inputs'!$D$47,0) -> 0 | F31: =IF(F$5>='Inputs'!$D$59,'Inputs'!$D$9*'Inputs'!$D$47,0) -> 0 | G31: =IF(G$5>='Inputs'!$D$59,'Inputs'!$D$9*'Inputs'!$D$47,0) -> 0 | H31: =IF(H$5>='Inputs'!$D$59,'Inputs'!$D$9*'Inputs'!$D$47,0) -> 0 | I31: =IF(I$5>='Inputs'!$D$59,'Inputs'!$D$9*'Inputs'!$D$47,0) -> 0 | J31: =IF(J$5>='Inputs'!$D$59,'Inputs'!$D$9*'Inputs'!$D$47,0) -> 0 | K31: =IF(K$5>='Inputs'!$D$59,'Inputs'!$D$9*'Inputs'!$D$47,0) -> 0 | ... AU31: =IF(AU$5>='Inputs'!$D$59,'Inputs'!$D$9*'Inputs'!$D$47,0) -> 0
A32: Hopkins Admin | B32: $/month | C32: Ongoing Hopkins facility/admin charge | D32: ='Inputs'!$D$49 -> 150 | E32: ='Inputs'!$D$49 -> 150 | F32: ='Inputs'!$D$49 -> 150 | G32: ='Inputs'!$D$49 -> 150 | H32: ='Inputs'!$D$49 -> 150 | I32: ='Inputs'!$D$49 -> 150 | J32: ='Inputs'!$D$49 -> 150 | K32: ='Inputs'!$D$49 -> 150 | ... AU32: ='Inputs'!$D$49 -> 150
A33: Total Occupancy Cost | B33: $/month | C33: Smith + second venue + Hopkins | D33: =SUM(D30,D31,D32) -> 1950 | E33: =SUM(E30,E31,E32) -> 1950 | F33: =SUM(F30,F31,F32) -> 1950 | G33: =SUM(G30,G31,G32) -> 2750 | H33: =SUM(H30,H31,H32) -> 2750 | I33: =SUM(I30,I31,I32) -> 4150 | J33: =SUM(J30,J31,J32) -> 4150 | K33: =SUM(K30,K31,K32) -> 4150 | ... AU33: =SUM(AU30,AU31,AU32) -> 5513
A34: Consolidated Occupancy % | B34: % revenue | C34: Total occupancy ÷ total revenue | D34: =IFERROR(D33/D15,0) -> 0.23229717 | E34: =IFERROR(E33/E15,0) -> 0.23229717 | F34: =IFERROR(F33/F15,0) -> 0.23229717 | G34: =IFERROR(G33/G15,0) -> 0.53455978 | H34: =IFERROR(H33/H15,0) -> 0.53455978 | I34: =IFERROR(I33/I15,0) -> 0.8066993 | J34: =IFERROR(J33/J15,0) -> 0.8066993 | K34: =IFERROR(K33/K15,0) -> 0.8066993 | ... AU34: =IFERROR(AU33/AU15,0) -> 0.10279694
A35: Smith Occupancy % | B35: % revenue | C35: Smith occupancy ÷ Smith revenue | D35: =IFERROR(D30/D10,0) -> 0.34989367 | E35: =IFERROR(E30/E10,0) -> 0.34989367 | F35: =IFERROR(F30/F10,0) -> 0.34989367 | G35: =IFERROR(G30/G10,0) -> 0.50540197 | H35: =IFERROR(H30/H10,0) -> 0.50540197 | I35: =IFERROR(I30/I10,0) -> 0.77754149 | J35: =IFERROR(J30/J10,0) -> 0.77754149 | K35: =IFERROR(K30/K10,0) -> 0.77754149 | ... AU35: =IFERROR(AU30/AU10,0) -> 0.1
A36: Required Smith Revenue | B36: $/month | C36: Smith occupancy ÷ target ratio | D36: =D30/'Inputs'!$D$24 -> 18000 | E36: =E30/'Inputs'!$D$24 -> 18000 | F36: =F30/'Inputs'!$D$24 -> 18000 | G36: =G30/'Inputs'!$D$24 -> 26000 | H36: =H30/'Inputs'!$D$24 -> 26000 | I36: =I30/'Inputs'!$D$24 -> 40000 | J36: =J30/'Inputs'!$D$24 -> 40000 | K36: =K30/'Inputs'!$D$24 -> 40000 | ... AU36: =AU30/'Inputs'!$D$24 -> 53630
A37: Smith Revenue Gap / (Surplus) | B37: $/month | C37: Required less modeled Smith revenue | D37: =D36-D10 -> 12855.58 | E37: =E36-E10 -> 12855.58 | F37: =F36-F10 -> 12855.58 | G37: =G36-G10 -> 20855.58 | H37: =H36-H10 -> 20855.58 | I37: =I36-I10 -> 34855.58 | J37: =J36-J10 -> 34855.58 | K37: =K36-K10 -> 34855.58 | ... AU37: =AU36-AU10 -> 0
A38: Required Storefront Transactions / Day | B38: transactions | C38: Required storefront sales ÷ ticket ÷ open days | D38: =MAX(0,D36-D7-D8)/('Inputs'!$D$25*'Inputs'!$D$26) -> 35.709944 | E38: =MAX(0,E36-E7-E8)/('Inputs'!$D$25*'Inputs'!$D$26) -> 35.709944 | F38: =MAX(0,F36-F7-F8)/('Inputs'!$D$25*'Inputs'!$D$26) -> 35.709944 | G38: =MAX(0,G36-G7-G8)/('Inputs'!$D$25*'Inputs'!$D$26) -> 57.932167 | H38: =MAX(0,H36-H7-H8)/('Inputs'!$D$25*'Inputs'!$D$26) -> 57.932167 | I38: =MAX(0,I36-I7-I8)/('Inputs'!$D$25*'Inputs'!$D$26) -> 96.821056 | J38: =MAX(0,J36-J7-J8)/('Inputs'!$D$25*'Inputs'!$D$26) -> 96.821056 | K38: =MAX(0,K36-K7-K8)/('Inputs'!$D$25*'Inputs'!$D$26) -> 96.821056 | ... AU38: =MAX(0,AU36-AU7-AU8)/('Inputs'!$D$25*'Inputs'!$D$26) -> 134.68217
A39: OPERATING RESULT & CASH
A40: Payment Processing | B40: $/month | C40: 3% of revenue other than Airbnb | D40: ='Inputs'!$D$38*(D15-D11) -> 197.8326 | E40: ='Inputs'!$D$38*(E15-E11) -> 197.8326 | F40: ='Inputs'!$D$38*(F15-F11) -> 197.8326 | G40: ='Inputs'!$D$38*(G15-G11) -> 154.3326 | H40: ='Inputs'!$D$38*(H15-H11) -> 154.3326 | I40: ='Inputs'!$D$38*(I15-I11) -> 154.3326 | J40: ='Inputs'!$D$38*(J15-J11) -> 154.3326 | K40: ='Inputs'!$D$38*(K15-K11) -> 154.3326 | ... AU40: ='Inputs'!$D$38*(AU15-AU11) -> 1608.9
A41: Fixed Other OpEx | B41: $/month | C41: 3% inflation on each model-year anniversary | D41: ='Inputs'!$D$39*POWER(1+'Inputs'!$D$56,INT(((YEAR(D$5)-YEAR($D$5))*12+MONTH(D$5)-MONTH($D$5))/12)) -> 1855.65 | E41: ='Inputs'!$D$39*POWER(1+'Inputs'!$D$56,INT(((YEAR(E$5)-YEAR($D$5))*12+MONTH(E$5)-MONTH($D$5))/12)) -> 1855.65 | F41: ='Inputs'!$D$39*POWER(1+'Inputs'!$D$56,INT(((YEAR(F$5)-YEAR($D$5))*12+MONTH(F$5)-MONTH($D$5))/12)) -> 1855.65 | G41: ='Inputs'!$D$39*POWER(1+'Inputs'!$D$56,INT(((YEAR(G$5)-YEAR($D$5))*12+MONTH(G$5)-MONTH($D$5))/12)) -> 1855.65 | H41: ='Inputs'!$D$39*POWER(1+'Inputs'!$D$56,INT(((YEAR(H$5)-YEAR($D$5))*12+MONTH(H$5)-MONTH($D$5))/12)) -> 1855.65 | I41: ='Inputs'!$D$39*POWER(1+'Inputs'!$D$56,INT(((YEAR(I$5)-YEAR($D$5))*12+MONTH(I$5)-MONTH($D$5))/12)) -> 1855.65 | J41: ='Inputs'!$D$39*POWER(1+'Inputs'!$D$56,INT(((YEAR(J$5)-YEAR($D$5))*12+MONTH(J$5)-MONTH($D$5))/12)) -> 1855.65 | K41: ='Inputs'!$D$39*POWER(1+'Inputs'!$D$56,INT(((YEAR(K$5)-YEAR($D$5))*12+MONTH(K$5)-MONTH($D$5))/12)) -> 1855.65 | ... AU41: ='Inputs'!$D$39*POWER(1+'Inputs'!$D$56,INT(((YEAR(AU$5)-YEAR($D$5))*12+MONTH(AU$5)-MONTH($D$5))/12)) -> 2027.7189
A42: Operating Profit | B42: $/month | C42: Accrual operating profit after founder economic compensation | D42: =D15-D18-D20-D21-D25-D33-D40-D41 -> -6586.3744 | E42: =E15-E18-E20-E21-E25-E33-E40-E41 -> -6586.3744 | F42: =F15-F18-F20-F21-F25-F33-F40-F41 -> -6586.3744 | G42: =G15-G18-G20-G21-G25-G33-G40-G41 -> -9317.3744 | H42: =H15-H18-H20-H21-H25-H33-H40-H41 -> -9317.3744 | I42: =I15-I18-I20-I21-I25-I33-I40-I41 -> -10717.374 | J42: =J15-J18-J20-J21-J25-J33-J40-J41 -> -10717.374 | K42: =K15-K18-K20-K21-K25-K33-K40-K41 -> -10717.374 | ... AU42: =AU15-AU18-AU20-AU21-AU25-AU33-AU40-AU41 -> 11023.461
A43: Operating Margin | B43: % revenue | C43: Operating profit ÷ total revenue | D43: =IFERROR(D42/D15,0) -> -0.78461339 | E43: =IFERROR(E42/E15,0) -> -0.78461339 | F43: =IFERROR(F42/F15,0) -> -0.78461339 | G43: =IFERROR(G42/G15,0) -> -1.8111613 | H43: =IFERROR(H42/H15,0) -> -1.8111613 | I43: =IFERROR(I42/I15,0) -> -2.0833008 | J43: =IFERROR(J42/J15,0) -> -2.0833008 | K43: =IFERROR(K42/K15,0) -> -2.0833008 | ... AU43: =IFERROR(AU42/AU15,0) -> 0.20554654
A44: Founder Cash Salary | B44: $/month | C44: Current salary follows the editable cash-pay start | D44: =IF(D$5>='Inputs'!$D$33,'Inputs'!$D$32,0) -> 7500 | E44: =IF(E$5>='Inputs'!$D$33,'Inputs'!$D$32,0) -> 7500 | F44: =IF(F$5>='Inputs'!$D$33,'Inputs'!$D$32,0) -> 7500 | G44: =IF(G$5>='Inputs'!$D$33,'Inputs'!$D$32,0) -> 7500 | H44: =IF(H$5>='Inputs'!$D$33,'Inputs'!$D$32,0) -> 7500 | I44: =IF(I$5>='Inputs'!$D$33,'Inputs'!$D$32,0) -> 7500 | J44: =IF(J$5>='Inputs'!$D$33,'Inputs'!$D$32,0) -> 7500 | K44: =IF(K$5>='Inputs'!$D$33,'Inputs'!$D$32,0) -> 7500 | ... AU44: =IF(AU$5>='Inputs'!$D$33,'Inputs'!$D$32,0) -> 7500
A45: Founder Deferred Repayment | B45: $/month | C45: Editable backpay request capped at available deferred balance | D45: =MIN(MAX(0,IF(D$5>='Inputs'!$D$35,'Inputs'!$D$36,0)),MAX(0,'Inputs'!$D$34+D23-D44)) -> 0 | E45: =MIN(MAX(0,IF(E$5>='Inputs'!$D$35,'Inputs'!$D$36,0)),MAX(0,D47+E23-E44)) -> 0 | F45: =MIN(MAX(0,IF(F$5>='Inputs'!$D$35,'Inputs'!$D$36,0)),MAX(0,E47+F23-F44)) -> 0 | G45: =MIN(MAX(0,IF(G$5>='Inputs'!$D$35,'Inputs'!$D$36,0)),MAX(0,F47+G23-G44)) -> 0 | H45: =MIN(MAX(0,IF(H$5>='Inputs'!$D$35,'Inputs'!$D$36,0)),MAX(0,G47+H23-H44)) -> 0 | I45: =MIN(MAX(0,IF(I$5>='Inputs'!$D$35,'Inputs'!$D$36,0)),MAX(0,H47+I23-I44)) -> 0 | J45: =MIN(MAX(0,IF(J$5>='Inputs'!$D$35,'Inputs'!$D$36,0)),MAX(0,I47+J23-J44)) -> 0 | K45: =MIN(MAX(0,IF(K$5>='Inputs'!$D$35,'Inputs'!$D$36,0)),MAX(0,J47+K23-K44)) -> 0 | L45: =MIN(MAX(0,IF(L$5>='Inputs'!$D$35,'Inputs'!$D$36,0)),MAX(0,K47+L23-L44)) -> 0 | ... AU45: =MIN(MAX(0,IF(AU$5>='Inputs'!$D$35,'Inputs'!$D$36,0)),MAX(0,AT47+AU23-AU44)) -> 0
A46: Deferred Salary Movement | B46: $/month | C46: Economic compensation less current cash salary and repayment | D46: =D23-D44-D45 -> 0 | E46: =E23-E44-E45 -> 0 | F46: =F23-F44-F45 -> 0 | G46: =G23-G44-G45 -> 0 | H46: =H23-H44-H45 -> 0 | I46: =I23-I44-I45 -> 0 | J46: =J23-J44-J45 -> 0 | K46: =K23-K44-K45 -> 0 | ... AU46: =AU23-AU44-AU45 -> 0
A47: Founder Deferred Balance | B47: $ balance | C47: Prior balance + current movement | D47: ='Inputs'!$D$34+D46 -> 0 | E47: =D47+E46 -> 0 | F47: =E47+F46 -> 0 | G47: =F47+G46 -> 0 | H47: =G47+H46 -> 0 | I47: =H47+I46 -> 0 | J47: =I47+J46 -> 0 | K47: =J47+K46 -> 0 | L47: =K47+L46 -> 0 | ... AU47: =AT47+AU46 -> 0
A48: Monthly Operating Cash | B48: $/month | C48: Operating profit + economic compensation − current cash − repayment | D48: =D42+D23-D44-D45 -> -6586.3744 | E48: =E42+E23-E44-E45 -> -6586.3744 | F48: =F42+F23-F44-F45 -> -6586.3744 | G48: =G42+G23-G44-G45 -> -9317.3744 | H48: =H42+H23-H44-H45 -> -9317.3744 | I48: =I42+I23-I44-I45 -> -10717.374 | J48: =J42+J23-J44-J45 -> -10717.374 | K48: =K42+K23-K44-K45 -> -10717.374 | ... AU48: =AU42+AU23-AU44-AU45 -> 11023.461
A49: Cumulative Operating Cash | B49: $ balance | C49: Opening cash + cumulative monthly operating cash | D49: ='Inputs'!$D$40+D48 -> -6484.1444 | E49: =D49+E48 -> -13070.519 | F49: =E49+F48 -> -19656.893 | G49: =F49+G48 -> -28974.267 | H49: =G49+H48 -> -38291.642 | I49: =H49+I48 -> -49009.016 | J49: =I49+J48 -> -59726.391 | K49: =J49+K48 -> -70443.765 | L49: =K49+L48 -> -75410.715 | ... AU49: =AT49+AU48 -> 271769.04

Sheet Model - Base
A1: 608 Smith Avenue — Base Scenario
A2: Formula-driven 44-month base case. Yellow assumptions live on Inputs; outputs below include cached values for non-calculating readers.
A3: Storefront sales are target-driven illustrations, not observed demand. Founder current cash salary and deferred repayment are separate from economic labor cost.
A5: Metric | B5: Unit | C5: Driver / interpretation | D5: 46296 | E5: 46327 | F5: 46357 | G5: 46388 | H5: 46419 | I5: 46447 | J5: 46478 | K5: 46508 | L5: 46539 | M5: 46569 | N5: 46600 | O5: 46631 | P5: 46661 | Q5: 46692 | R5: 46722 | S5: 46753 | T5: 46784 | U5: 46813 | V5: 46844 | W5: 46874 | X5: 46905 | Y5: 46935 | Z5: 46966 | AA5: 46997 | AB5: 47027 | AC5: 47058 | AD5: 47088 | AE5: 47119 | AF5: 47150 | AG5: 47178 | AH5: 47209 | AI5: 47239 | AJ5: 47270 | AK5: 47300 | AL5: 47331 | AM5: 47362 | AN5: 47392 | AO5: 47423 | AP5: 47453 | AQ5: 47484 | AR5: 47515 | AS5: 47543 | AT5: 47574 | AU5: 47604
A6: REVENUE
A7: Meal Prep Revenue | B7: $/month | C7: Smith food revenue; monthly compound growth | D7: ='Inputs'!$E$18*POWER(1+'Inputs'!$E$19,0) -> 4334.42 | E7: ='Inputs'!$E$18*POWER(1+'Inputs'!$E$19,1) -> 4377.7642 | F7: ='Inputs'!$E$18*POWER(1+'Inputs'!$E$19,2) -> 4421.5418 | G7: ='Inputs'!$E$18*POWER(1+'Inputs'!$E$19,3) -> 4465.7573 | H7: ='Inputs'!$E$18*POWER(1+'Inputs'!$E$19,4) -> 4510.4148 | I7: ='Inputs'!$E$18*POWER(1+'Inputs'!$E$19,5) -> 4555.519 | J7: ='Inputs'!$E$18*POWER(1+'Inputs'!$E$19,6) -> 4601.0742 | K7: ='Inputs'!$E$18*POWER(1+'Inputs'!$E$19,7) -> 4647.0849 | L7: ='Inputs'!$E$18*POWER(1+'Inputs'!$E$19,8) -> 4693.5558 | M7: ='Inputs'!$E$18*POWER(1+'Inputs'!$E$19,9) -> 4740.4913 | N7: ='Inputs'!$E$18*POWER(1+'Inputs'!$E$19,10) -> 4787.8962 | O7: ='Inputs'!$E$18*POWER(1+'Inputs'!$E$19,11) -> 4835.7752 | P7: ='Inputs'!$E$18*POWER(1+'Inputs'!$E$19,12) -> 4884.1329 | Q7: ='Inputs'!$E$18*POWER(1+'Inputs'!$E$19,13) -> 4932.9743 | R7: ='Inputs'!$E$18*POWER(1+'Inputs'!$E$19,14) -> 4982.304 | S7: ='Inputs'!$E$18*POWER(1+'Inputs'!$E$19,15) -> 5032.1271 | T7: ='Inputs'!$E$18*POWER(1+'Inputs'!$E$19,16) -> 5082.4483 | U7: ='Inputs'!$E$18*POWER(1+'Inputs'!$E$19,17) -> 5133.2728 | V7: ='Inputs'!$E$18*POWER(1+'Inputs'!$E$19,18) -> 5184.6055 | W7: ='Inputs'!$E$18*POWER(1+'Inputs'!$E$19,19) -> 5236.4516 | X7: ='Inputs'!$E$18*POWER(1+'Inputs'!$E$19,20) -> 5288.8161 | Y7: ='Inputs'!$E$18*POWER(1+'Inputs'!$E$19,21) -> 5341.7043 | Z7: ='Inputs'!$E$18*POWER(1+'Inputs'!$E$19,22) -> 5395.1213 | AA7: ='Inputs'!$E$18*POWER(1+'Inputs'!$E$19,23) -> 5449.0725 | AB7: ='Inputs'!$E$18*POWER(1+'Inputs'!$E$19,24) -> 5503.5633 | AC7: ='Inputs'!$E$18*POWER(1+'Inputs'!$E$19,25) -> 5558.5989 | AD7: ='Inputs'!$E$18*POWER(1+'Inputs'!$E$19,26) -> 5614.1849 | AE7: ='Inputs'!$E$18*POWER(1+'Inputs'!$E$19,27) -> 5670.3267 | AF7: ='Inputs'!$E$18*POWER(1+'Inputs'!$E$19,28) -> 5727.03 | AG7: ='Inputs'!$E$18*POWER(1+'Inputs'!$E$19,29) -> 5784.3003 | AH7: ='Inputs'!$E$18*POWER(1+'Inputs'!$E$19,30) -> 5842.1433 | AI7: ='Inputs'!$E$18*POWER(1+'Inputs'!$E$19,31) -> 5900.5647 | AJ7: ='Inputs'!$E$18*POWER(1+'Inputs'!$E$19,32) -> 5959.5704 | AK7: ='Inputs'!$E$18*POWER(1+'Inputs'!$E$19,33) -> 6019.1661 | AL7: ='Inputs'!$E$18*POWER(1+'Inputs'!$E$19,34) -> 6079.3577 | AM7: ='Inputs'!$E$18*POWER(1+'Inputs'!$E$19,35) -> 6140.1513 | AN7: ='Inputs'!$E$18*POWER(1+'Inputs'!$E$19,36) -> 6201.5528 | AO7: ='Inputs'!$E$18*POWER(1+'Inputs'!$E$19,37) -> 6263.5684 | AP7: ='Inputs'!$E$18*POWER(1+'Inputs'!$E$19,38) -> 6326.204 | AQ7: ='Inputs'!$E$18*POWER(1+'Inputs'!$E$19,39) -> 6389.4661 | AR7: ='Inputs'!$E$18*POWER(1+'Inputs'!$E$19,40) -> 6453.3607 | AS7: ='Inputs'!$E$18*POWER(1+'Inputs'!$E$19,41) -> 6517.8944 | AT7: ='Inputs'!$E$18*POWER(1+'Inputs'!$E$19,42) -> 6583.0733 | AU7: ='Inputs'!$E$18*POWER(1+'Inputs'!$E$19,43) -> 6648.904
A8: Frozen Pizza Revenue | B8: $/month | C8: Starting units × realized price × unit growth; produced at Hopkins | D8: ='Inputs'!$E$20*POWER(1+'Inputs'!$E$22,0)*'Inputs'!$E$21 -> 1800 | E8: ='Inputs'!$E$20*POWER(1+'Inputs'!$E$22,1)*'Inputs'!$E$21 -> 1827 | F8: ='Inputs'!$E$20*POWER(1+'Inputs'!$E$22,2)*'Inputs'!$E$21 -> 1854.405 | G8: ='Inputs'!$E$20*POWER(1+'Inputs'!$E$22,3)*'Inputs'!$E$21 -> 1882.2211 | H8: ='Inputs'!$E$20*POWER(1+'Inputs'!$E$22,4)*'Inputs'!$E$21 -> 1910.4544 | I8: ='Inputs'!$E$20*POWER(1+'Inputs'!$E$22,5)*'Inputs'!$E$21 -> 1939.1112 | J8: ='Inputs'!$E$20*POWER(1+'Inputs'!$E$22,6)*'Inputs'!$E$21 -> 1968.1979 | K8: ='Inputs'!$E$20*POWER(1+'Inputs'!$E$22,7)*'Inputs'!$E$21 -> 1997.7208 | L8: ='Inputs'!$E$20*POWER(1+'Inputs'!$E$22,8)*'Inputs'!$E$21 -> 2027.6867 | M8: ='Inputs'!$E$20*POWER(1+'Inputs'!$E$22,9)*'Inputs'!$E$21 -> 2058.102 | N8: ='Inputs'!$E$20*POWER(1+'Inputs'!$E$22,10)*'Inputs'!$E$21 -> 2088.9735 | O8: ='Inputs'!$E$20*POWER(1+'Inputs'!$E$22,11)*'Inputs'!$E$21 -> 2120.3081 | P8: ='Inputs'!$E$20*POWER(1+'Inputs'!$E$22,12)*'Inputs'!$E$21 -> 2152.1127 | Q8: ='Inputs'!$E$20*POWER(1+'Inputs'!$E$22,13)*'Inputs'!$E$21 -> 2184.3944 | R8: ='Inputs'!$E$20*POWER(1+'Inputs'!$E$22,14)*'Inputs'!$E$21 -> 2217.1603 | S8: ='Inputs'!$E$20*POWER(1+'Inputs'!$E$22,15)*'Inputs'!$E$21 -> 2250.4177 | T8: ='Inputs'!$E$20*POWER(1+'Inputs'!$E$22,16)*'Inputs'!$E$21 -> 2284.174 | U8: ='Inputs'!$E$20*POWER(1+'Inputs'!$E$22,17)*'Inputs'!$E$21 -> 2318.4366 | V8: ='Inputs'!$E$20*POWER(1+'Inputs'!$E$22,18)*'Inputs'!$E$21 -> 2353.2131 | W8: ='Inputs'!$E$20*POWER(1+'Inputs'!$E$22,19)*'Inputs'!$E$21 -> 2388.5113 | X8: ='Inputs'!$E$20*POWER(1+'Inputs'!$E$22,20)*'Inputs'!$E$21 -> 2424.339 | Y8: ='Inputs'!$E$20*POWER(1+'Inputs'!$E$22,21)*'Inputs'!$E$21 -> 2460.7041 | Z8: ='Inputs'!$E$20*POWER(1+'Inputs'!$E$22,22)*'Inputs'!$E$21 -> 2497.6147 | AA8: ='Inputs'!$E$20*POWER(1+'Inputs'!$E$22,23)*'Inputs'!$E$21 -> 2535.0789 | AB8: ='Inputs'!$E$20*POWER(1+'Inputs'!$E$22,24)*'Inputs'!$E$21 -> 2573.1051 | AC8: ='Inputs'!$E$20*POWER(1+'Inputs'!$E$22,25)*'Inputs'!$E$21 -> 2611.7016 | AD8: ='Inputs'!$E$20*POWER(1+'Inputs'!$E$22,26)*'Inputs'!$E$21 -> 2650.8772 | AE8: ='Inputs'!$E$20*POWER(1+'Inputs'!$E$22,27)*'Inputs'!$E$21 -> 2690.6403 | AF8: ='Inputs'!$E$20*POWER(1+'Inputs'!$E$22,28)*'Inputs'!$E$21 -> 2730.9999 | AG8: ='Inputs'!$E$20*POWER(1+'Inputs'!$E$22,29)*'Inputs'!$E$21 -> 2771.9649 | AH8: ='Inputs'!$E$20*POWER(1+'Inputs'!$E$22,30)*'Inputs'!$E$21 -> 2813.5444 | AI8: ='Inputs'!$E$20*POWER(1+'Inputs'!$E$22,31)*'Inputs'!$E$21 -> 2855.7476 | AJ8: ='Inputs'!$E$20*POWER(1+'Inputs'!$E$22,32)*'Inputs'!$E$21 -> 2898.5838 | AK8: ='Inputs'!$E$20*POWER(1+'Inputs'!$E$22,33)*'Inputs'!$E$21 -> 2942.0625 | AL8: ='Inputs'!$E$20*POWER(1+'Inputs'!$E$22,34)*'Inputs'!$E$21 -> 2986.1935 | AM8: ='Inputs'!$E$20*POWER(1+'Inputs'!$E$22,35)*'Inputs'!$E$21 -> 3030.9864 | AN8: ='Inputs'!$E$20*POWER(1+'Inputs'!$E$22,36)*'Inputs'!$E$21 -> 3076.4512 | AO8: ='Inputs'!$E$20*POWER(1+'Inputs'!$E$22,37)*'Inputs'!$E$21 -> 3122.5979 | AP8: ='Inputs'!$E$20*POWER(1+'Inputs'!$E$22,38)*'Inputs'!$E$21 -> 3169.4369 | AQ8: ='Inputs'!$E$20*POWER(1+'Inputs'!$E$22,39)*'Inputs'!$E$21 -> 3216.9785 | AR8: ='Inputs'!$E$20*POWER(1+'Inputs'!$E$22,40)*'Inputs'!$E$21 -> 3265.2331 | AS8: ='Inputs'!$E$20*POWER(1+'Inputs'!$E$22,41)*'Inputs'!$E$21 -> 3314.2116 | AT8: ='Inputs'!$E$20*POWER(1+'Inputs'!$E$22,42)*'Inputs'!$E$21 -> 3363.9248 | AU8: ='Inputs'!$E$20*POWER(1+'Inputs'!$E$22,43)*'Inputs'!$E$21 -> 3414.3837
A9: Storefront Revenue | B9: $/month | C9: Required Smith sales after meal prep and frozen pizza × six-month ramp | D9: =MAX(0,D36-D7-D8)*(IF(D$5<'Inputs'!$E$23,0,CHOOSE(MIN(7,MAX(1,(YEAR(D$5)-YEAR('Inputs'!$E$23))*12+MONTH(D$5)-MONTH('Inputs'!$E$23)+1)),'Inputs'!$E$50,'Inputs'!$E$51,'Inputs'!$E$52,'Inputs'!$E$53,'Inputs'!$E$54,'Inputs'!$E$55,'Inputs'!$E$55))) -> 0 | E9: =MAX(0,E36-E7-E8)*(IF(E$5<'Inputs'!$E$23,0,CHOOSE(MIN(7,MAX(1,(YEAR(E$5)-YEAR('Inputs'!$E$23))*12+MONTH(E$5)-MONTH('Inputs'!$E$23)+1)),'Inputs'!$E$50,'Inputs'!$E$51,'Inputs'!$E$52,'Inputs'!$E$53,'Inputs'!$E$54,'Inputs'!$E$55,'Inputs'!$E$55))) -> 0 | F9: =MAX(0,F36-F7-F8)*(IF(F$5<'Inputs'!$E$23,0,CHOOSE(MIN(7,MAX(1,(YEAR(F$5)-YEAR('Inputs'!$E$23))*12+MONTH(F$5)-MONTH('Inputs'!$E$23)+1)),'Inputs'!$E$50,'Inputs'!$E$51,'Inputs'!$E$52,'Inputs'!$E$53,'Inputs'!$E$54,'Inputs'!$E$55,'Inputs'!$E$55))) -> 0 | G9: =MAX(0,G36-G7-G8)*(IF(G$5<'Inputs'!$E$23,0,CHOOSE(MIN(7,MAX(1,(YEAR(G$5)-YEAR('Inputs'!$E$23))*12+MONTH(G$5)-MONTH('Inputs'!$E$23)+1)),'Inputs'!$E$50,'Inputs'!$E$51,'Inputs'!$E$52,'Inputs'!$E$53,'Inputs'!$E$54,'Inputs'!$E$55,'Inputs'!$E$55))) -> 0 | H9: =MAX(0,H36-H7-H8)*(IF(H$5<'Inputs'!$E$23,0,CHOOSE(MIN(7,MAX(1,(YEAR(H$5)-YEAR('Inputs'!$E$23))*12+MONTH(H$5)-MONTH('Inputs'!$E$23)+1)),'Inputs'!$E$50,'Inputs'!$E$51,'Inputs'!$E$52,'Inputs'!$E$53,'Inputs'!$E$54,'Inputs'!$E$55,'Inputs'!$E$55))) -> 0 | I9: =MAX(0,I36-I7-I8)*(IF(I$5<'Inputs'!$E$23,0,CHOOSE(MIN(7,MAX(1,(YEAR(I$5)-YEAR('Inputs'!$E$23))*12+MONTH(I$5)-MONTH('Inputs'!$E$23)+1)),'Inputs'!$E$50,'Inputs'!$E$51,'Inputs'!$E$52,'Inputs'!$E$53,'Inputs'!$E$54,'Inputs'!$E$55,'Inputs'!$E$55))) -> 10990.037 | J9: =MAX(0,J36-J7-J8)*(IF(J$5<'Inputs'!$E$23,0,CHOOSE(MIN(7,MAX(1,(YEAR(J$5)-YEAR('Inputs'!$E$23))*12+MONTH(J$5)-MONTH('Inputs'!$E$23)+1)),'Inputs'!$E$50,'Inputs'!$E$51,'Inputs'!$E$52,'Inputs'!$E$53,'Inputs'!$E$54,'Inputs'!$E$55,'Inputs'!$E$55))) -> 15662.732 | K9: =MAX(0,K36-K7-K8)*(IF(K$5<'Inputs'!$E$23,0,CHOOSE(MIN(7,MAX(1,(YEAR(K$5)-YEAR('Inputs'!$E$23))*12+MONTH(K$5)-MONTH('Inputs'!$E$23)+1)),'Inputs'!$E$50,'Inputs'!$E$51,'Inputs'!$E$52,'Inputs'!$E$53,'Inputs'!$E$54,'Inputs'!$E$55,'Inputs'!$E$55))) -> 20312.455 | ... AU9: =MAX(0,AU36-AU7-AU8)*(IF(AU$5<'Inputs'!$E$23,0,CHOOSE(MIN(7,MAX(1,(YEAR(AU$5)-YEAR('Inputs'!$E$23))*12+MONTH(AU$5)-MONTH('Inputs'!$E$23)+1)),'Inputs'!$E$50,'Inputs'!$E$51,'Inputs'!$E$52,'Inputs'!$E$53,'Inputs'!$E$54,'Inputs'!$E$55,'Inputs'!$E$55))) -> 42178.818
A10: Smith Revenue | B10: $/month | C10: Meal prep + frozen pizza + storefront | D10: =SUM(D7:D9) -> 6134.42 | E10: =SUM(E7:E9) -> 6204.7642 | F10: =SUM(F7:F9) -> 6275.9468 | G10: =SUM(G7:G9) -> 6347.9783 | H10: =SUM(H7:H9) -> 6420.8692 | I10: =SUM(I7:I9) -> 17484.668 | J10: =SUM(J7:J9) -> 22232.004 | K10: =SUM(K7:K9) -> 26957.261 | ... AU10: =SUM(AU7:AU9) -> 52242.105
A11: Airbnb Revenue | B11: $/month | C11: Nonfood revenue at the second venue | D11: ='Inputs'!$E$11*'Inputs'!$E$48*(IF(D$5<'Inputs'!$E$57,0,IF(D$5<='Inputs'!$E$58,'Inputs'!$E$10,IF(D$5>='Inputs'!$E$59,'Inputs'!$E$9,0)))) -> 5400 | E11: ='Inputs'!$E$11*'Inputs'!$E$48*(IF(E$5<'Inputs'!$E$57,0,IF(E$5<='Inputs'!$E$58,'Inputs'!$E$10,IF(E$5>='Inputs'!$E$59,'Inputs'!$E$9,0)))) -> 5400 | F11: ='Inputs'!$E$11*'Inputs'!$E$48*(IF(F$5<'Inputs'!$E$57,0,IF(F$5<='Inputs'!$E$58,'Inputs'!$E$10,IF(F$5>='Inputs'!$E$59,'Inputs'!$E$9,0)))) -> 5400 | G11: ='Inputs'!$E$11*'Inputs'!$E$48*(IF(G$5<'Inputs'!$E$57,0,IF(G$5<='Inputs'!$E$58,'Inputs'!$E$10,IF(G$5>='Inputs'!$E$59,'Inputs'!$E$9,0)))) -> 7200 | H11: ='Inputs'!$E$11*'Inputs'!$E$48*(IF(H$5<'Inputs'!$E$57,0,IF(H$5<='Inputs'!$E$58,'Inputs'!$E$10,IF(H$5>='Inputs'!$E$59,'Inputs'!$E$9,0)))) -> 7200 | I11: ='Inputs'!$E$11*'Inputs'!$E$48*(IF(I$5<'Inputs'!$E$57,0,IF(I$5<='Inputs'!$E$58,'Inputs'!$E$10,IF(I$5>='Inputs'!$E$59,'Inputs'!$E$9,0)))) -> 7200 | J11: ='Inputs'!$E$11*'Inputs'!$E$48*(IF(J$5<'Inputs'!$E$57,0,IF(J$5<='Inputs'!$E$58,'Inputs'!$E$10,IF(J$5>='Inputs'!$E$59,'Inputs'!$E$9,0)))) -> 7200 | K11: ='Inputs'!$E$11*'Inputs'!$E$48*(IF(K$5<'Inputs'!$E$57,0,IF(K$5<='Inputs'!$E$58,'Inputs'!$E$10,IF(K$5>='Inputs'!$E$59,'Inputs'!$E$9,0)))) -> 7200 | ... AU11: ='Inputs'!$E$11*'Inputs'!$E$48*(IF(AU$5<'Inputs'!$E$57,0,IF(AU$5<='Inputs'!$E$58,'Inputs'!$E$10,IF(AU$5>='Inputs'!$E$59,'Inputs'!$E$9,0)))) -> 7200
A12: Small Events Revenue | B12: $/month | C12: Gross small-event revenue | D12: ='Inputs'!$E$13*'Inputs'!$E$14*(IF(D$5<'Inputs'!$E$57,0,IF(D$5<='Inputs'!$E$58,'Inputs'!$E$10,IF(D$5>='Inputs'!$E$59,'Inputs'!$E$9,0)))) -> 3150 | E12: ='Inputs'!$E$13*'Inputs'!$E$14*(IF(E$5<'Inputs'!$E$57,0,IF(E$5<='Inputs'!$E$58,'Inputs'!$E$10,IF(E$5>='Inputs'!$E$59,'Inputs'!$E$9,0)))) -> 3150 | F12: ='Inputs'!$E$13*'Inputs'!$E$14*(IF(F$5<'Inputs'!$E$57,0,IF(F$5<='Inputs'!$E$58,'Inputs'!$E$10,IF(F$5>='Inputs'!$E$59,'Inputs'!$E$9,0)))) -> 3150 | G12: ='Inputs'!$E$13*'Inputs'!$E$14*(IF(G$5<'Inputs'!$E$57,0,IF(G$5<='Inputs'!$E$58,'Inputs'!$E$10,IF(G$5>='Inputs'!$E$59,'Inputs'!$E$9,0)))) -> 4200 | H12: ='Inputs'!$E$13*'Inputs'!$E$14*(IF(H$5<'Inputs'!$E$57,0,IF(H$5<='Inputs'!$E$58,'Inputs'!$E$10,IF(H$5>='Inputs'!$E$59,'Inputs'!$E$9,0)))) -> 4200 | I12: ='Inputs'!$E$13*'Inputs'!$E$14*(IF(I$5<'Inputs'!$E$57,0,IF(I$5<='Inputs'!$E$58,'Inputs'!$E$10,IF(I$5>='Inputs'!$E$59,'Inputs'!$E$9,0)))) -> 4200 | J12: ='Inputs'!$E$13*'Inputs'!$E$14*(IF(J$5<'Inputs'!$E$57,0,IF(J$5<='Inputs'!$E$58,'Inputs'!$E$10,IF(J$5>='Inputs'!$E$59,'Inputs'!$E$9,0)))) -> 4200 | K12: ='Inputs'!$E$13*'Inputs'!$E$14*(IF(K$5<'Inputs'!$E$57,0,IF(K$5<='Inputs'!$E$58,'Inputs'!$E$10,IF(K$5>='Inputs'!$E$59,'Inputs'!$E$9,0)))) -> 4200 | ... AU12: ='Inputs'!$E$13*'Inputs'!$E$14*(IF(AU$5<'Inputs'!$E$57,0,IF(AU$5<='Inputs'!$E$58,'Inputs'!$E$10,IF(AU$5>='Inputs'!$E$59,'Inputs'!$E$9,0)))) -> 4200
A13: Personal Chef Revenue | B13: $/month | C13: Food revenue from packages at the second venue | D13: ='Inputs'!$E$16*'Inputs'!$E$17*(IF(D$5<'Inputs'!$E$57,0,IF(D$5<='Inputs'!$E$58,'Inputs'!$E$10,IF(D$5>='Inputs'!$E$59,'Inputs'!$E$9,0)))) -> 1800 | E13: ='Inputs'!$E$16*'Inputs'!$E$17*(IF(E$5<'Inputs'!$E$57,0,IF(E$5<='Inputs'!$E$58,'Inputs'!$E$10,IF(E$5>='Inputs'!$E$59,'Inputs'!$E$9,0)))) -> 1800 | F13: ='Inputs'!$E$16*'Inputs'!$E$17*(IF(F$5<'Inputs'!$E$57,0,IF(F$5<='Inputs'!$E$58,'Inputs'!$E$10,IF(F$5>='Inputs'!$E$59,'Inputs'!$E$9,0)))) -> 1800 | G13: ='Inputs'!$E$16*'Inputs'!$E$17*(IF(G$5<'Inputs'!$E$57,0,IF(G$5<='Inputs'!$E$58,'Inputs'!$E$10,IF(G$5>='Inputs'!$E$59,'Inputs'!$E$9,0)))) -> 2400 | H13: ='Inputs'!$E$16*'Inputs'!$E$17*(IF(H$5<'Inputs'!$E$57,0,IF(H$5<='Inputs'!$E$58,'Inputs'!$E$10,IF(H$5>='Inputs'!$E$59,'Inputs'!$E$9,0)))) -> 2400 | I13: ='Inputs'!$E$16*'Inputs'!$E$17*(IF(I$5<'Inputs'!$E$57,0,IF(I$5<='Inputs'!$E$58,'Inputs'!$E$10,IF(I$5>='Inputs'!$E$59,'Inputs'!$E$9,0)))) -> 2400 | J13: ='Inputs'!$E$16*'Inputs'!$E$17*(IF(J$5<'Inputs'!$E$57,0,IF(J$5<='Inputs'!$E$58,'Inputs'!$E$10,IF(J$5>='Inputs'!$E$59,'Inputs'!$E$9,0)))) -> 2400 | K13: ='Inputs'!$E$16*'Inputs'!$E$17*(IF(K$5<'Inputs'!$E$57,0,IF(K$5<='Inputs'!$E$58,'Inputs'!$E$10,IF(K$5>='Inputs'!$E$59,'Inputs'!$E$9,0)))) -> 2400 | ... AU13: ='Inputs'!$E$16*'Inputs'!$E$17*(IF(AU$5<'Inputs'!$E$57,0,IF(AU$5<='Inputs'!$E$58,'Inputs'!$E$10,IF(AU$5>='Inputs'!$E$59,'Inputs'!$E$9,0)))) -> 2400
A14: Second Venue Revenue | B14: $/month | C14: Airbnb + small events + personal chef | D14: =SUM(D11:D13) -> 10350 | E14: =SUM(E11:E13) -> 10350 | F14: =SUM(F11:F13) -> 10350 | G14: =SUM(G11:G13) -> 13800 | H14: =SUM(H11:H13) -> 13800 | I14: =SUM(I11:I13) -> 13800 | J14: =SUM(J11:J13) -> 13800 | K14: =SUM(K11:K13) -> 13800 | ... AU14: =SUM(AU11:AU13) -> 13800
A15: Total Revenue | B15: $/month | C15: Smith + second venue | D15: =D10+D14 -> 16484.42 | E15: =E10+E14 -> 16554.764 | F15: =F10+F14 -> 16625.947 | G15: =G10+G14 -> 20147.978 | H15: =H10+H14 -> 20220.869 | I15: =I10+I14 -> 31284.668 | J15: =J10+J14 -> 36032.004 | K15: =K10+K14 -> 40757.261 | ... AU15: =AU10+AU14 -> 66042.105
A16: Food Revenue | B16: $/month | C16: Smith + event food component + personal chef | D16: =D10+'Inputs'!$E$13*'Inputs'!$E$15*(IF(D$5<'Inputs'!$E$57,0,IF(D$5<='Inputs'!$E$58,'Inputs'!$E$10,IF(D$5>='Inputs'!$E$59,'Inputs'!$E$9,0))))+D13 -> 9959.42 | E16: =E10+'Inputs'!$E$13*'Inputs'!$E$15*(IF(E$5<'Inputs'!$E$57,0,IF(E$5<='Inputs'!$E$58,'Inputs'!$E$10,IF(E$5>='Inputs'!$E$59,'Inputs'!$E$9,0))))+E13 -> 10029.764 | F16: =F10+'Inputs'!$E$13*'Inputs'!$E$15*(IF(F$5<'Inputs'!$E$57,0,IF(F$5<='Inputs'!$E$58,'Inputs'!$E$10,IF(F$5>='Inputs'!$E$59,'Inputs'!$E$9,0))))+F13 -> 10100.947 | G16: =G10+'Inputs'!$E$13*'Inputs'!$E$15*(IF(G$5<'Inputs'!$E$57,0,IF(G$5<='Inputs'!$E$58,'Inputs'!$E$10,IF(G$5>='Inputs'!$E$59,'Inputs'!$E$9,0))))+G13 -> 11447.978 | H16: =H10+'Inputs'!$E$13*'Inputs'!$E$15*(IF(H$5<'Inputs'!$E$57,0,IF(H$5<='Inputs'!$E$58,'Inputs'!$E$10,IF(H$5>='Inputs'!$E$59,'Inputs'!$E$9,0))))+H13 -> 11520.869 | I16: =I10+'Inputs'!$E$13*'Inputs'!$E$15*(IF(I$5<'Inputs'!$E$57,0,IF(I$5<='Inputs'!$E$58,'Inputs'!$E$10,IF(I$5>='Inputs'!$E$59,'Inputs'!$E$9,0))))+I13 -> 22584.668 | J16: =J10+'Inputs'!$E$13*'Inputs'!$E$15*(IF(J$5<'Inputs'!$E$57,0,IF(J$5<='Inputs'!$E$58,'Inputs'!$E$10,IF(J$5>='Inputs'!$E$59,'Inputs'!$E$9,0))))+J13 -> 27332.004 | K16: =K10+'Inputs'!$E$13*'Inputs'!$E$15*(IF(K$5<'Inputs'!$E$57,0,IF(K$5<='Inputs'!$E$58,'Inputs'!$E$10,IF(K$5>='Inputs'!$E$59,'Inputs'!$E$9,0))))+K13 -> 32057.261 | ... AU16: =AU10+'Inputs'!$E$13*'Inputs'!$E$15*(IF(AU$5<'Inputs'!$E$57,0,IF(AU$5<='Inputs'!$E$58,'Inputs'!$E$10,IF(AU$5>='Inputs'!$E$59,'Inputs'!$E$9,0))))+AU13 -> 57342.105
A17: COST OF SALES & LABOR
A18: Food COGS | B18: $/month | C18: Applied only to food revenue | D18: =D16*'Inputs'!$E$27 -> 2091.4782 | E18: =E16*'Inputs'!$E$27 -> 2106.2505 | F18: =F16*'Inputs'!$E$27 -> 2121.1988 | G18: =G16*'Inputs'!$E$27 -> 2404.0755 | H18: =H16*'Inputs'!$E$27 -> 2419.3825 | I18: =I16*'Inputs'!$E$27 -> 4742.7802 | J18: =J16*'Inputs'!$E$27 -> 5739.7209 | K18: =K16*'Inputs'!$E$27 -> 6732.0248 | ... AU18: =AU16*'Inputs'!$E$27 -> 12041.842
A19: Food Cost % | B19: % revenue | C19: Food COGS ÷ food revenue | D19: =IFERROR(D18/D16,0) -> 0.21 | E19: =IFERROR(E18/E16,0) -> 0.21 | F19: =IFERROR(F18/F16,0) -> 0.21 | G19: =IFERROR(G18/G16,0) -> 0.21 | H19: =IFERROR(H18/H16,0) -> 0.21 | I19: =IFERROR(I18/I16,0) -> 0.21 | J19: =IFERROR(J18/J16,0) -> 0.21 | K19: =IFERROR(K18/K16,0) -> 0.21 | ... AU19: =IFERROR(AU18/AU16,0) -> 0.21
A20: Venue Variable Cost | B20: $/month | C20: Applied only to Airbnb revenue | D20: =D11*'Inputs'!$E$12 -> 972 | E20: =E11*'Inputs'!$E$12 -> 972 | F20: =F11*'Inputs'!$E$12 -> 972 | G20: =G11*'Inputs'!$E$12 -> 1296 | H20: =H11*'Inputs'!$E$12 -> 1296 | I20: =I11*'Inputs'!$E$12 -> 1296 | J20: =J11*'Inputs'!$E$12 -> 1296 | K20: =K11*'Inputs'!$E$12 -> 1296 | ... AU20: =AU11*'Inputs'!$E$12 -> 1296
A21: Packaging & Delivery | B21: $/month | C21: Applied to food revenue | D21: =D16*'Inputs'!$E$37 -> 298.7826 | E21: =E16*'Inputs'!$E$37 -> 300.89293 | F21: =F16*'Inputs'!$E$37 -> 303.02841 | G21: =G16*'Inputs'!$E$37 -> 343.43935 | H21: =H16*'Inputs'!$E$37 -> 345.62608 | I21: =I16*'Inputs'!$E$37 -> 677.54003 | J21: =J16*'Inputs'!$E$37 -> 819.96013 | K21: =K16*'Inputs'!$E$37 -> 961.71783 | ... AU21: =AU16*'Inputs'!$E$37 -> 1720.2632
A22: Direct Paid Labor | B22: $/month | C22: Phase rate × total revenue | D22: =D15*(IF(D$5<'Inputs'!$E$23,'Inputs'!$E$28,IF(D$5<EDATE('Inputs'!$E$23,6),'Inputs'!$E$29,'Inputs'!$E$30))) -> 1978.1304 | E22: =E15*(IF(E$5<'Inputs'!$E$23,'Inputs'!$E$28,IF(E$5<EDATE('Inputs'!$E$23,6),'Inputs'!$E$29,'Inputs'!$E$30))) -> 1986.5717 | F22: =F15*(IF(F$5<'Inputs'!$E$23,'Inputs'!$E$28,IF(F$5<EDATE('Inputs'!$E$23,6),'Inputs'!$E$29,'Inputs'!$E$30))) -> 1995.1136 | G22: =G15*(IF(G$5<'Inputs'!$E$23,'Inputs'!$E$28,IF(G$5<EDATE('Inputs'!$E$23,6),'Inputs'!$E$29,'Inputs'!$E$30))) -> 2417.7574 | H22: =H15*(IF(H$5<'Inputs'!$E$23,'Inputs'!$E$28,IF(H$5<EDATE('Inputs'!$E$23,6),'Inputs'!$E$29,'Inputs'!$E$30))) -> 2426.5043 | I22: =I15*(IF(I$5<'Inputs'!$E$23,'Inputs'!$E$28,IF(I$5<EDATE('Inputs'!$E$23,6),'Inputs'!$E$29,'Inputs'!$E$30))) -> 5318.3935 | J22: =J15*(IF(J$5<'Inputs'!$E$23,'Inputs'!$E$28,IF(J$5<EDATE('Inputs'!$E$23,6),'Inputs'!$E$29,'Inputs'!$E$30))) -> 6125.4408 | K22: =K15*(IF(K$5<'Inputs'!$E$23,'Inputs'!$E$28,IF(K$5<EDATE('Inputs'!$E$23,6),'Inputs'!$E$29,'Inputs'!$E$30))) -> 6928.7344 | ... AU22: =AU15*(IF(AU$5<'Inputs'!$E$23,'Inputs'!$E$28,IF(AU$5<EDATE('Inputs'!$E$23,6),'Inputs'!$E$29,'Inputs'!$E$30))) -> 9245.8947
A23: Founder Economic Salary | B23: $/month | C23: Catherine + Weston combined economic compensation | D23: ='Inputs'!$E$32 -> 7500 | E23: ='Inputs'!$E$32 -> 7500 | F23: ='Inputs'!$E$32 -> 7500 | G23: ='Inputs'!$E$32 -> 7500 | H23: ='Inputs'!$E$32 -> 7500 | I23: ='Inputs'!$E$32 -> 7500 | J23: ='Inputs'!$E$32 -> 7500 | K23: ='Inputs'!$E$32 -> 7500 | ... AU23: ='Inputs'!$E$32 -> 7500
A24: Direct Payroll Burden | B24: $/month | C24: Burden on direct paid labor | D24: =D22*'Inputs'!$E$31 -> 197.81304 | E24: =E22*'Inputs'!$E$31 -> 198.65717 | F24: =F22*'Inputs'!$E$31 -> 199.51136 | G24: =G22*'Inputs'!$E$31 -> 241.77574 | H24: =H22*'Inputs'!$E$31 -> 242.65043 | I24: =I22*'Inputs'!$E$31 -> 531.83935 | J24: =J22*'Inputs'!$E$31 -> 612.54408 | K24: =K22*'Inputs'!$E$31 -> 692.87344 | ... AU24: =AU22*'Inputs'!$E$31 -> 924.58947
A25: Total Labor | B25: $/month | C25: Direct labor + founder economic compensation + burden | D25: =SUM(D22,D23,D24) -> 9675.9434 | E25: =SUM(E22,E23,E24) -> 9685.2289 | F25: =SUM(F22,F23,F24) -> 9694.625 | G25: =SUM(G22,G23,G24) -> 10159.533 | H25: =SUM(H22,H23,H24) -> 10169.155 | I25: =SUM(I22,I23,I24) -> 13350.233 | J25: =SUM(J22,J23,J24) -> 14237.985 | K25: =SUM(K22,K23,K24) -> 15121.608 | ... AU25: =SUM(AU22,AU23,AU24) -> 17670.484
A26: Total Labor % | B26: % revenue | C26: Total labor ÷ total revenue | D26: =IFERROR(D25/D15,0) -> 0.58697506 | E26: =IFERROR(E25/E15,0) -> 0.58504179 | F26: =IFERROR(F25/F15,0) -> 0.58310213 | G26: =IFERROR(G25/G15,0) -> 0.50424578 | H26: =IFERROR(H25/H15,0) -> 0.50290394 | I26: =IFERROR(I25/I15,0) -> 0.42673405 | J26: =IFERROR(J25/J15,0) -> 0.39514829 | K26: =IFERROR(K25/K15,0) -> 0.37101629 | ... AU26: =IFERROR(AU25/AU15,0) -> 0.26756391
A27: OCCUPANCY & REQUIRED SALES
A28: Smith Rent & NNN | B28: $/month | C28: Owner-provided stepped rent schedule | D28: =IF(D$5<DATE(2026,10,1),'Inputs'!$E$41,IF(D$5<DATE(2027,1,1),'Inputs'!$E$42,IF(D$5<DATE(2027,6,1),'Inputs'!$E$43,IF(D$5<DATE(2028,1,1),'Inputs'!$E$44,'Inputs'!$E$45)))) -> 1800 | E28: =IF(E$5<DATE(2026,10,1),'Inputs'!$E$41,IF(E$5<DATE(2027,1,1),'Inputs'!$E$42,IF(E$5<DATE(2027,6,1),'Inputs'!$E$43,IF(E$5<DATE(2028,1,1),'Inputs'!$E$44,'Inputs'!$E$45)))) -> 1800 | F28: =IF(F$5<DATE(2026,10,1),'Inputs'!$E$41,IF(F$5<DATE(2027,1,1),'Inputs'!$E$42,IF(F$5<DATE(2027,6,1),'Inputs'!$E$43,IF(F$5<DATE(2028,1,1),'Inputs'!$E$44,'Inputs'!$E$45)))) -> 1800 | G28: =IF(G$5<DATE(2026,10,1),'Inputs'!$E$41,IF(G$5<DATE(2027,1,1),'Inputs'!$E$42,IF(G$5<DATE(2027,6,1),'Inputs'!$E$43,IF(G$5<DATE(2028,1,1),'Inputs'!$E$44,'Inputs'!$E$45)))) -> 2600 | H28: =IF(H$5<DATE(2026,10,1),'Inputs'!$E$41,IF(H$5<DATE(2027,1,1),'Inputs'!$E$42,IF(H$5<DATE(2027,6,1),'Inputs'!$E$43,IF(H$5<DATE(2028,1,1),'Inputs'!$E$44,'Inputs'!$E$45)))) -> 2600 | I28: =IF(I$5<DATE(2026,10,1),'Inputs'!$E$41,IF(I$5<DATE(2027,1,1),'Inputs'!$E$42,IF(I$5<DATE(2027,6,1),'Inputs'!$E$43,IF(I$5<DATE(2028,1,1),'Inputs'!$E$44,'Inputs'!$E$45)))) -> 2600 | J28: =IF(J$5<DATE(2026,10,1),'Inputs'!$E$41,IF(J$5<DATE(2027,1,1),'Inputs'!$E$42,IF(J$5<DATE(2027,6,1),'Inputs'!$E$43,IF(J$5<DATE(2028,1,1),'Inputs'!$E$44,'Inputs'!$E$45)))) -> 2600 | K28: =IF(K$5<DATE(2026,10,1),'Inputs'!$E$41,IF(K$5<DATE(2027,1,1),'Inputs'!$E$42,IF(K$5<DATE(2027,6,1),'Inputs'!$E$43,IF(K$5<DATE(2028,1,1),'Inputs'!$E$44,'Inputs'!$E$45)))) -> 2600 | ... AU28: =IF(AU$5<DATE(2026,10,1),'Inputs'!$E$41,IF(AU$5<DATE(2027,1,1),'Inputs'!$E$42,IF(AU$5<DATE(2027,6,1),'Inputs'!$E$43,IF(AU$5<DATE(2028,1,1),'Inputs'!$E$44,'Inputs'!$E$45)))) -> 3963
A29: Smith Utilities | B29: $/month | C29: Begins on the editable transfer date | D29: =IF(D$5>='Inputs'!$E$46,'Inputs'!$E$8,0) -> 0 | E29: =IF(E$5>='Inputs'!$E$46,'Inputs'!$E$8,0) -> 0 | F29: =IF(F$5>='Inputs'!$E$46,'Inputs'!$E$8,0) -> 0 | G29: =IF(G$5>='Inputs'!$E$46,'Inputs'!$E$8,0) -> 0 | H29: =IF(H$5>='Inputs'!$E$46,'Inputs'!$E$8,0) -> 0 | I29: =IF(I$5>='Inputs'!$E$46,'Inputs'!$E$8,0) -> 1000 | J29: =IF(J$5>='Inputs'!$E$46,'Inputs'!$E$8,0) -> 1000 | K29: =IF(K$5>='Inputs'!$E$46,'Inputs'!$E$8,0) -> 1000 | ... AU29: =IF(AU$5>='Inputs'!$E$46,'Inputs'!$E$8,0) -> 1000
A30: Smith Occupancy Cost | B30: $/month | C30: Smith rent + utilities | D30: =SUM(D28:D29) -> 1800 | E30: =SUM(E28:E29) -> 1800 | F30: =SUM(F28:F29) -> 1800 | G30: =SUM(G28:G29) -> 2600 | H30: =SUM(H28:H29) -> 2600 | I30: =SUM(I28:I29) -> 3600 | J30: =SUM(J28:J29) -> 3600 | K30: =SUM(K28:K29) -> 3600 | ... AU30: =SUM(AU28:AU29) -> 4963
A31: Second Venue Rent | B31: $/month | C31: Conditional on post-trial activation | D31: =IF(D$5>='Inputs'!$E$59,'Inputs'!$E$9*'Inputs'!$E$47,0) -> 0 | E31: =IF(E$5>='Inputs'!$E$59,'Inputs'!$E$9*'Inputs'!$E$47,0) -> 0 | F31: =IF(F$5>='Inputs'!$E$59,'Inputs'!$E$9*'Inputs'!$E$47,0) -> 0 | G31: =IF(G$5>='Inputs'!$E$59,'Inputs'!$E$9*'Inputs'!$E$47,0) -> 5000 | H31: =IF(H$5>='Inputs'!$E$59,'Inputs'!$E$9*'Inputs'!$E$47,0) -> 5000 | I31: =IF(I$5>='Inputs'!$E$59,'Inputs'!$E$9*'Inputs'!$E$47,0) -> 5000 | J31: =IF(J$5>='Inputs'!$E$59,'Inputs'!$E$9*'Inputs'!$E$47,0) -> 5000 | K31: =IF(K$5>='Inputs'!$E$59,'Inputs'!$E$9*'Inputs'!$E$47,0) -> 5000 | ... AU31: =IF(AU$5>='Inputs'!$E$59,'Inputs'!$E$9*'Inputs'!$E$47,0) -> 5000
A32: Hopkins Admin | B32: $/month | C32: Ongoing Hopkins facility/admin charge | D32: ='Inputs'!$E$49 -> 150 | E32: ='Inputs'!$E$49 -> 150 | F32: ='Inputs'!$E$49 -> 150 | G32: ='Inputs'!$E$49 -> 150 | H32: ='Inputs'!$E$49 -> 150 | I32: ='Inputs'!$E$49 -> 150 | J32: ='Inputs'!$E$49 -> 150 | K32: ='Inputs'!$E$49 -> 150 | ... AU32: ='Inputs'!$E$49 -> 150
A33: Total Occupancy Cost | B33: $/month | C33: Smith + second venue + Hopkins | D33: =SUM(D30,D31,D32) -> 1950 | E33: =SUM(E30,E31,E32) -> 1950 | F33: =SUM(F30,F31,F32) -> 1950 | G33: =SUM(G30,G31,G32) -> 7750 | H33: =SUM(H30,H31,H32) -> 7750 | I33: =SUM(I30,I31,I32) -> 8750 | J33: =SUM(J30,J31,J32) -> 8750 | K33: =SUM(K30,K31,K32) -> 8750 | ... AU33: =SUM(AU30,AU31,AU32) -> 10113
A34: Consolidated Occupancy % | B34: % revenue | C34: Total occupancy ÷ total revenue | D34: =IFERROR(D33/D15,0) -> 0.11829352 | E34: =IFERROR(E33/E15,0) -> 0.11779087 | F34: =IFERROR(F33/F15,0) -> 0.11728655 | G34: =IFERROR(G33/G15,0) -> 0.38465398 | H34: =IFERROR(H33/H15,0) -> 0.3832674 | I34: =IFERROR(I33/I15,0) -> 0.27968972 | J34: =IFERROR(J33/J15,0) -> 0.24283967 | K34: =IFERROR(K33/K15,0) -> 0.21468567 | ... AU34: =IFERROR(AU33/AU15,0) -> 0.15312958
A35: Smith Occupancy % | B35: % revenue | C35: Smith occupancy ÷ Smith revenue | D35: =IFERROR(D30/D10,0) -> 0.29342627 | E35: =IFERROR(E30/E10,0) -> 0.29009966 | F35: =IFERROR(F30/F10,0) -> 0.28680931 | G35: =IFERROR(G30/G10,0) -> 0.40957922 | H35: =IFERROR(H30/H10,0) -> 0.4049296 | I35: =IFERROR(I30/I10,0) -> 0.20589468 | J35: =IFERROR(J30/J10,0) -> 0.16192872 | K35: =IFERROR(K30/K10,0) -> 0.13354472 | ... AU35: =IFERROR(AU30/AU10,0) -> 0.095
A36: Required Smith Revenue | B36: $/month | C36: Smith occupancy ÷ target ratio | D36: =D30/'Inputs'!$E$24 -> 18947.368 | E36: =E30/'Inputs'!$E$24 -> 18947.368 | F36: =F30/'Inputs'!$E$24 -> 18947.368 | G36: =G30/'Inputs'!$E$24 -> 27368.421 | H36: =H30/'Inputs'!$E$24 -> 27368.421 | I36: =I30/'Inputs'!$E$24 -> 37894.737 | J36: =J30/'Inputs'!$E$24 -> 37894.737 | K36: =K30/'Inputs'!$E$24 -> 37894.737 | ... AU36: =AU30/'Inputs'!$E$24 -> 52242.105
A37: Smith Revenue Gap / (Surplus) | B37: $/month | C37: Required less modeled Smith revenue | D37: =D36-D10 -> 12812.948 | E37: =E36-E10 -> 12742.604 | F37: =F36-F10 -> 12671.422 | G37: =G36-G10 -> 21020.443 | H37: =H36-H10 -> 20947.552 | I37: =I36-I10 -> 20410.069 | J37: =J36-J10 -> 15662.732 | K37: =K36-K10 -> 10937.476 | ... AU37: =AU36-AU10 -> 0
A38: Required Storefront Transactions / Day | B38: transactions | C38: Required storefront sales ÷ ticket ÷ open days | D38: =MAX(0,D36-D7-D8)/('Inputs'!$E$25*'Inputs'!$E$26) -> 29.120337 | E38: =MAX(0,E36-E7-E8)/('Inputs'!$E$25*'Inputs'!$E$26) -> 28.960464 | F38: =MAX(0,F36-F7-F8)/('Inputs'!$E$25*'Inputs'!$E$26) -> 28.798685 | G38: =MAX(0,G36-G7-G8)/('Inputs'!$E$25*'Inputs'!$E$26) -> 47.773733 | H38: =MAX(0,H36-H7-H8)/('Inputs'!$E$25*'Inputs'!$E$26) -> 47.608072 | I38: =MAX(0,I36-I7-I8)/('Inputs'!$E$25*'Inputs'!$E$26) -> 71.363879 | J38: =MAX(0,J36-J7-J8)/('Inputs'!$E$25*'Inputs'!$E$26) -> 71.194238 | K38: =MAX(0,K36-K7-K8)/('Inputs'!$E$25*'Inputs'!$E$26) -> 71.022571 | ... AU38: =MAX(0,AU36-AU7-AU8)/('Inputs'!$E$25*'Inputs'!$E$26) -> 95.860949
A39: OPERATING RESULT & CASH
A40: Payment Processing | B40: $/month | C40: 3% of revenue other than Airbnb | D40: ='Inputs'!$E$38*(D15-D11) -> 332.5326 | E40: ='Inputs'!$E$38*(E15-E11) -> 334.64293 | F40: ='Inputs'!$E$38*(F15-F11) -> 336.77841 | G40: ='Inputs'!$E$38*(G15-G11) -> 388.43935 | H40: ='Inputs'!$E$38*(H15-H11) -> 390.62608 | I40: ='Inputs'!$E$38*(I15-I11) -> 722.54003 | J40: ='Inputs'!$E$38*(J15-J11) -> 864.96013 | K40: ='Inputs'!$E$38*(K15-K11) -> 1006.7178 | ... AU40: ='Inputs'!$E$38*(AU15-AU11) -> 1765.2632
A41: Fixed Other OpEx | B41: $/month | C41: 3% inflation on each model-year anniversary | D41: ='Inputs'!$E$39*POWER(1+'Inputs'!$E$56,INT(((YEAR(D$5)-YEAR($D$5))*12+MONTH(D$5)-MONTH($D$5))/12)) -> 1686.95 | E41: ='Inputs'!$E$39*POWER(1+'Inputs'!$E$56,INT(((YEAR(E$5)-YEAR($D$5))*12+MONTH(E$5)-MONTH($D$5))/12)) -> 1686.95 | F41: ='Inputs'!$E$39*POWER(1+'Inputs'!$E$56,INT(((YEAR(F$5)-YEAR($D$5))*12+MONTH(F$5)-MONTH($D$5))/12)) -> 1686.95 | G41: ='Inputs'!$E$39*POWER(1+'Inputs'!$E$56,INT(((YEAR(G$5)-YEAR($D$5))*12+MONTH(G$5)-MONTH($D$5))/12)) -> 1686.95 | H41: ='Inputs'!$E$39*POWER(1+'Inputs'!$E$56,INT(((YEAR(H$5)-YEAR($D$5))*12+MONTH(H$5)-MONTH($D$5))/12)) -> 1686.95 | I41: ='Inputs'!$E$39*POWER(1+'Inputs'!$E$56,INT(((YEAR(I$5)-YEAR($D$5))*12+MONTH(I$5)-MONTH($D$5))/12)) -> 1686.95 | J41: ='Inputs'!$E$39*POWER(1+'Inputs'!$E$56,INT(((YEAR(J$5)-YEAR($D$5))*12+MONTH(J$5)-MONTH($D$5))/12)) -> 1686.95 | K41: ='Inputs'!$E$39*POWER(1+'Inputs'!$E$56,INT(((YEAR(K$5)-YEAR($D$5))*12+MONTH(K$5)-MONTH($D$5))/12)) -> 1686.95 | ... AU41: ='Inputs'!$E$39*POWER(1+'Inputs'!$E$56,INT(((YEAR(AU$5)-YEAR($D$5))*12+MONTH(AU$5)-MONTH($D$5))/12)) -> 1843.3758
A42: Operating Profit | B42: $/month | C42: Accrual operating profit after founder economic compensation | D42: =D15-D18-D20-D21-D25-D33-D40-D41 -> -523.26684 | E42: =E15-E18-E20-E21-E25-E33-E40-E41 -> -481.20101 | F42: =F15-F18-F20-F21-F25-F33-F40-F41 -> -438.63379 | G42: =G15-G18-G20-G21-G25-G33-G40-G41 -> -3880.459 | H42: =H15-H18-H20-H21-H25-H33-H40-H41 -> -3836.8702 | I42: =I15-I18-I20-I21-I25-I33-I40-I41 -> 58.624462 | J42: =J15-J18-J20-J21-J25-J33-J40-J41 -> 2636.4284 | K42: =K15-K18-K20-K21-K25-K33-K40-K41 -> 5202.2427 | ... AU42: =AU15-AU18-AU20-AU21-AU25-AU33-AU40-AU41 -> 19591.877
A43: Operating Margin | B43: % revenue | C43: Operating profit ÷ total revenue | D43: =IFERROR(D42/D15,0) -> -0.031743115 | E43: =IFERROR(E42/E15,0) -> -0.029067222 | F43: =IFERROR(F42/F15,0) -> -0.026382485 | G43: =IFERROR(G42/G15,0) -> -0.19259793 | H43: =IFERROR(H42/H15,0) -> -0.18974804 | I43: =IFERROR(I42/I15,0) -> 0.0018739039 | J43: =IFERROR(J42/J15,0) -> 0.073169074 | K43: =IFERROR(K42/K15,0) -> 0.12763965 | ... AU43: =IFERROR(AU42/AU15,0) -> 0.29665736
A44: Founder Cash Salary | B44: $/month | C44: Current salary follows the editable cash-pay start | D44: =IF(D$5>='Inputs'!$E$33,'Inputs'!$E$32,0) -> 7500 | E44: =IF(E$5>='Inputs'!$E$33,'Inputs'!$E$32,0) -> 7500 | F44: =IF(F$5>='Inputs'!$E$33,'Inputs'!$E$32,0) -> 7500 | G44: =IF(G$5>='Inputs'!$E$33,'Inputs'!$E$32,0) -> 7500 | H44: =IF(H$5>='Inputs'!$E$33,'Inputs'!$E$32,0) -> 7500 | I44: =IF(I$5>='Inputs'!$E$33,'Inputs'!$E$32,0) -> 7500 | J44: =IF(J$5>='Inputs'!$E$33,'Inputs'!$E$32,0) -> 7500 | K44: =IF(K$5>='Inputs'!$E$33,'Inputs'!$E$32,0) -> 7500 | ... AU44: =IF(AU$5>='Inputs'!$E$33,'Inputs'!$E$32,0) -> 7500
A45: Founder Deferred Repayment | B45: $/month | C45: Editable backpay request capped at available deferred balance | D45: =MIN(MAX(0,IF(D$5>='Inputs'!$E$35,'Inputs'!$E$36,0)),MAX(0,'Inputs'!$E$34+D23-D44)) -> 0 | E45: =MIN(MAX(0,IF(E$5>='Inputs'!$E$35,'Inputs'!$E$36,0)),MAX(0,D47+E23-E44)) -> 0 | F45: =MIN(MAX(0,IF(F$5>='Inputs'!$E$35,'Inputs'!$E$36,0)),MAX(0,E47+F23-F44)) -> 0 | G45: =MIN(MAX(0,IF(G$5>='Inputs'!$E$35,'Inputs'!$E$36,0)),MAX(0,F47+G23-G44)) -> 0 | H45: =MIN(MAX(0,IF(H$5>='Inputs'!$E$35,'Inputs'!$E$36,0)),MAX(0,G47+H23-H44)) -> 0 | I45: =MIN(MAX(0,IF(I$5>='Inputs'!$E$35,'Inputs'!$E$36,0)),MAX(0,H47+I23-I44)) -> 0 | J45: =MIN(MAX(0,IF(J$5>='Inputs'!$E$35,'Inputs'!$E$36,0)),MAX(0,I47+J23-J44)) -> 0 | K45: =MIN(MAX(0,IF(K$5>='Inputs'!$E$35,'Inputs'!$E$36,0)),MAX(0,J47+K23-K44)) -> 0 | L45: =MIN(MAX(0,IF(L$5>='Inputs'!$E$35,'Inputs'!$E$36,0)),MAX(0,K47+L23-L44)) -> 0 | ... AU45: =MIN(MAX(0,IF(AU$5>='Inputs'!$E$35,'Inputs'!$E$36,0)),MAX(0,AT47+AU23-AU44)) -> 0
A46: Deferred Salary Movement | B46: $/month | C46: Economic compensation less current cash salary and repayment | D46: =D23-D44-D45 -> 0 | E46: =E23-E44-E45 -> 0 | F46: =F23-F44-F45 -> 0 | G46: =G23-G44-G45 -> 0 | H46: =H23-H44-H45 -> 0 | I46: =I23-I44-I45 -> 0 | J46: =J23-J44-J45 -> 0 | K46: =K23-K44-K45 -> 0 | ... AU46: =AU23-AU44-AU45 -> 0
A47: Founder Deferred Balance | B47: $ balance | C47: Prior balance + current movement | D47: ='Inputs'!$E$34+D46 -> 0 | E47: =D47+E46 -> 0 | F47: =E47+F46 -> 0 | G47: =F47+G46 -> 0 | H47: =G47+H46 -> 0 | I47: =H47+I46 -> 0 | J47: =I47+J46 -> 0 | K47: =J47+K46 -> 0 | L47: =K47+L46 -> 0 | ... AU47: =AT47+AU46 -> 0
A48: Monthly Operating Cash | B48: $/month | C48: Operating profit + economic compensation − current cash − repayment | D48: =D42+D23-D44-D45 -> -523.26684 | E48: =E42+E23-E44-E45 -> -481.20101 | F48: =F42+F23-F44-F45 -> -438.63379 | G48: =G42+G23-G44-G45 -> -3880.459 | H48: =H42+H23-H44-H45 -> -3836.8702 | I48: =I42+I23-I44-I45 -> 58.624462 | J48: =J42+J23-J44-J45 -> 2636.4284 | K48: =K42+K23-K44-K45 -> 5202.2427 | ... AU48: =AU42+AU23-AU44-AU45 -> 19591.877
A49: Cumulative Operating Cash | B49: $ balance | C49: Opening cash + cumulative monthly operating cash | D49: ='Inputs'!$E$40+D48 -> -421.03684 | E49: =D49+E48 -> -902.23785 | F49: =E49+F48 -> -1340.8716 | G49: =F49+G48 -> -5221.3306 | H49: =G49+H48 -> -9058.2008 | I49: =H49+I48 -> -8999.5763 | J49: =I49+J48 -> -6363.1479 | K49: =J49+K48 -> -1160.9052 | L49: =K49+L48 -> 9453.0507 | ... AU49: =AT49+AU48 -> 674335.34

Sheet Model - Upside
A1: 608 Smith Avenue — Upside Scenario
A2: Formula-driven 44-month upside case. Yellow assumptions live on Inputs; outputs below include cached values for non-calculating readers.
A3: Storefront sales are target-driven illustrations, not observed demand. Founder current cash salary and deferred repayment are separate from economic labor cost.
A5: Metric | B5: Unit | C5: Driver / interpretation | D5: 46296 | E5: 46327 | F5: 46357 | G5: 46388 | H5: 46419 | I5: 46447 | J5: 46478 | K5: 46508 | L5: 46539 | M5: 46569 | N5: 46600 | O5: 46631 | P5: 46661 | Q5: 46692 | R5: 46722 | S5: 46753 | T5: 46784 | U5: 46813 | V5: 46844 | W5: 46874 | X5: 46905 | Y5: 46935 | Z5: 46966 | AA5: 46997 | AB5: 47027 | AC5: 47058 | AD5: 47088 | AE5: 47119 | AF5: 47150 | AG5: 47178 | AH5: 47209 | AI5: 47239 | AJ5: 47270 | AK5: 47300 | AL5: 47331 | AM5: 47362 | AN5: 47392 | AO5: 47423 | AP5: 47453 | AQ5: 47484 | AR5: 47515 | AS5: 47543 | AT5: 47574 | AU5: 47604
A6: REVENUE
A7: Meal Prep Revenue | B7: $/month | C7: Smith food revenue; monthly compound growth | D7: ='Inputs'!$F$18*POWER(1+'Inputs'!$F$19,0) -> 4334.42 | E7: ='Inputs'!$F$18*POWER(1+'Inputs'!$F$19,1) -> 4421.1084 | F7: ='Inputs'!$F$18*POWER(1+'Inputs'!$F$19,2) -> 4509.5306 | G7: ='Inputs'!$F$18*POWER(1+'Inputs'!$F$19,3) -> 4599.7212 | H7: ='Inputs'!$F$18*POWER(1+'Inputs'!$F$19,4) -> 4691.7156 | I7: ='Inputs'!$F$18*POWER(1+'Inputs'!$F$19,5) -> 4785.5499 | J7: ='Inputs'!$F$18*POWER(1+'Inputs'!$F$19,6) -> 4881.2609 | K7: ='Inputs'!$F$18*POWER(1+'Inputs'!$F$19,7) -> 4978.8861 | L7: ='Inputs'!$F$18*POWER(1+'Inputs'!$F$19,8) -> 5078.4639 | M7: ='Inputs'!$F$18*POWER(1+'Inputs'!$F$19,9) -> 5180.0331 | N7: ='Inputs'!$F$18*POWER(1+'Inputs'!$F$19,10) -> 5283.6338 | O7: ='Inputs'!$F$18*POWER(1+'Inputs'!$F$19,11) -> 5389.3065 | P7: ='Inputs'!$F$18*POWER(1+'Inputs'!$F$19,12) -> 5497.0926 | Q7: ='Inputs'!$F$18*POWER(1+'Inputs'!$F$19,13) -> 5607.0345 | R7: ='Inputs'!$F$18*POWER(1+'Inputs'!$F$19,14) -> 5719.1751 | S7: ='Inputs'!$F$18*POWER(1+'Inputs'!$F$19,15) -> 5833.5586 | T7: ='Inputs'!$F$18*POWER(1+'Inputs'!$F$19,16) -> 5950.2298 | U7: ='Inputs'!$F$18*POWER(1+'Inputs'!$F$19,17) -> 6069.2344 | V7: ='Inputs'!$F$18*POWER(1+'Inputs'!$F$19,18) -> 6190.6191 | W7: ='Inputs'!$F$18*POWER(1+'Inputs'!$F$19,19) -> 6314.4315 | X7: ='Inputs'!$F$18*POWER(1+'Inputs'!$F$19,20) -> 6440.7201 | Y7: ='Inputs'!$F$18*POWER(1+'Inputs'!$F$19,21) -> 6569.5345 | Z7: ='Inputs'!$F$18*POWER(1+'Inputs'!$F$19,22) -> 6700.9252 | AA7: ='Inputs'!$F$18*POWER(1+'Inputs'!$F$19,23) -> 6834.9437 | AB7: ='Inputs'!$F$18*POWER(1+'Inputs'!$F$19,24) -> 6971.6426 | AC7: ='Inputs'!$F$18*POWER(1+'Inputs'!$F$19,25) -> 7111.0754 | AD7: ='Inputs'!$F$18*POWER(1+'Inputs'!$F$19,26) -> 7253.2969 | AE7: ='Inputs'!$F$18*POWER(1+'Inputs'!$F$19,27) -> 7398.3629 | AF7: ='Inputs'!$F$18*POWER(1+'Inputs'!$F$19,28) -> 7546.3301 | AG7: ='Inputs'!$F$18*POWER(1+'Inputs'!$F$19,29) -> 7697.2567 | AH7: ='Inputs'!$F$18*POWER(1+'Inputs'!$F$19,30) -> 7851.2019 | AI7: ='Inputs'!$F$18*POWER(1+'Inputs'!$F$19,31) -> 8008.2259 | AJ7: ='Inputs'!$F$18*POWER(1+'Inputs'!$F$19,32) -> 8168.3904 | AK7: ='Inputs'!$F$18*POWER(1+'Inputs'!$F$19,33) -> 8331.7582 | AL7: ='Inputs'!$F$18*POWER(1+'Inputs'!$F$19,34) -> 8498.3934 | AM7: ='Inputs'!$F$18*POWER(1+'Inputs'!$F$19,35) -> 8668.3613 | AN7: ='Inputs'!$F$18*POWER(1+'Inputs'!$F$19,36) -> 8841.7285 | AO7: ='Inputs'!$F$18*POWER(1+'Inputs'!$F$19,37) -> 9018.5631 | AP7: ='Inputs'!$F$18*POWER(1+'Inputs'!$F$19,38) -> 9198.9343 | AQ7: ='Inputs'!$F$18*POWER(1+'Inputs'!$F$19,39) -> 9382.913 | AR7: ='Inputs'!$F$18*POWER(1+'Inputs'!$F$19,40) -> 9570.5713 | AS7: ='Inputs'!$F$18*POWER(1+'Inputs'!$F$19,41) -> 9761.9827 | AT7: ='Inputs'!$F$18*POWER(1+'Inputs'!$F$19,42) -> 9957.2224 | AU7: ='Inputs'!$F$18*POWER(1+'Inputs'!$F$19,43) -> 10156.367
A8: Frozen Pizza Revenue | B8: $/month | C8: Starting units × realized price × unit growth; produced at Hopkins | D8: ='Inputs'!$F$20*POWER(1+'Inputs'!$F$22,0)*'Inputs'!$F$21 -> 3850 | E8: ='Inputs'!$F$20*POWER(1+'Inputs'!$F$22,1)*'Inputs'!$F$21 -> 3965.5 | F8: ='Inputs'!$F$20*POWER(1+'Inputs'!$F$22,2)*'Inputs'!$F$21 -> 4084.465 | G8: ='Inputs'!$F$20*POWER(1+'Inputs'!$F$22,3)*'Inputs'!$F$21 -> 4206.999 | H8: ='Inputs'!$F$20*POWER(1+'Inputs'!$F$22,4)*'Inputs'!$F$21 -> 4333.2089 | I8: ='Inputs'!$F$20*POWER(1+'Inputs'!$F$22,5)*'Inputs'!$F$21 -> 4463.2052 | J8: ='Inputs'!$F$20*POWER(1+'Inputs'!$F$22,6)*'Inputs'!$F$21 -> 4597.1013 | K8: ='Inputs'!$F$20*POWER(1+'Inputs'!$F$22,7)*'Inputs'!$F$21 -> 4735.0144 | L8: ='Inputs'!$F$20*POWER(1+'Inputs'!$F$22,8)*'Inputs'!$F$21 -> 4877.0648 | M8: ='Inputs'!$F$20*POWER(1+'Inputs'!$F$22,9)*'Inputs'!$F$21 -> 5023.3768 | N8: ='Inputs'!$F$20*POWER(1+'Inputs'!$F$22,10)*'Inputs'!$F$21 -> 5174.0781 | O8: ='Inputs'!$F$20*POWER(1+'Inputs'!$F$22,11)*'Inputs'!$F$21 -> 5329.3004 | P8: ='Inputs'!$F$20*POWER(1+'Inputs'!$F$22,12)*'Inputs'!$F$21 -> 5489.1794 | Q8: ='Inputs'!$F$20*POWER(1+'Inputs'!$F$22,13)*'Inputs'!$F$21 -> 5653.8548 | R8: ='Inputs'!$F$20*POWER(1+'Inputs'!$F$22,14)*'Inputs'!$F$21 -> 5823.4704 | S8: ='Inputs'!$F$20*POWER(1+'Inputs'!$F$22,15)*'Inputs'!$F$21 -> 5998.1746 | T8: ='Inputs'!$F$20*POWER(1+'Inputs'!$F$22,16)*'Inputs'!$F$21 -> 6178.1198 | U8: ='Inputs'!$F$20*POWER(1+'Inputs'!$F$22,17)*'Inputs'!$F$21 -> 6363.4634 | V8: ='Inputs'!$F$20*POWER(1+'Inputs'!$F$22,18)*'Inputs'!$F$21 -> 6554.3673 | W8: ='Inputs'!$F$20*POWER(1+'Inputs'!$F$22,19)*'Inputs'!$F$21 -> 6750.9983 | X8: ='Inputs'!$F$20*POWER(1+'Inputs'!$F$22,20)*'Inputs'!$F$21 -> 6953.5283 | Y8: ='Inputs'!$F$20*POWER(1+'Inputs'!$F$22,21)*'Inputs'!$F$21 -> 7162.1341 | Z8: ='Inputs'!$F$20*POWER(1+'Inputs'!$F$22,22)*'Inputs'!$F$21 -> 7376.9981 | AA8: ='Inputs'!$F$20*POWER(1+'Inputs'!$F$22,23)*'Inputs'!$F$21 -> 7598.3081 | AB8: ='Inputs'!$F$20*POWER(1+'Inputs'!$F$22,24)*'Inputs'!$F$21 -> 7826.2573 | AC8: ='Inputs'!$F$20*POWER(1+'Inputs'!$F$22,25)*'Inputs'!$F$21 -> 8061.045 | AD8: ='Inputs'!$F$20*POWER(1+'Inputs'!$F$22,26)*'Inputs'!$F$21 -> 8302.8764 | AE8: ='Inputs'!$F$20*POWER(1+'Inputs'!$F$22,27)*'Inputs'!$F$21 -> 8551.9627 | AF8: ='Inputs'!$F$20*POWER(1+'Inputs'!$F$22,28)*'Inputs'!$F$21 -> 8808.5216 | AG8: ='Inputs'!$F$20*POWER(1+'Inputs'!$F$22,29)*'Inputs'!$F$21 -> 9072.7772 | AH8: ='Inputs'!$F$20*POWER(1+'Inputs'!$F$22,30)*'Inputs'!$F$21 -> 9344.9605 | AI8: ='Inputs'!$F$20*POWER(1+'Inputs'!$F$22,31)*'Inputs'!$F$21 -> 9625.3093 | AJ8: ='Inputs'!$F$20*POWER(1+'Inputs'!$F$22,32)*'Inputs'!$F$21 -> 9914.0686 | AK8: ='Inputs'!$F$20*POWER(1+'Inputs'!$F$22,33)*'Inputs'!$F$21 -> 10211.491 | AL8: ='Inputs'!$F$20*POWER(1+'Inputs'!$F$22,34)*'Inputs'!$F$21 -> 10517.835 | AM8: ='Inputs'!$F$20*POWER(1+'Inputs'!$F$22,35)*'Inputs'!$F$21 -> 10833.37 | AN8: ='Inputs'!$F$20*POWER(1+'Inputs'!$F$22,36)*'Inputs'!$F$21 -> 11158.372 | AO8: ='Inputs'!$F$20*POWER(1+'Inputs'!$F$22,37)*'Inputs'!$F$21 -> 11493.123 | AP8: ='Inputs'!$F$20*POWER(1+'Inputs'!$F$22,38)*'Inputs'!$F$21 -> 11837.916 | AQ8: ='Inputs'!$F$20*POWER(1+'Inputs'!$F$22,39)*'Inputs'!$F$21 -> 12193.054 | AR8: ='Inputs'!$F$20*POWER(1+'Inputs'!$F$22,40)*'Inputs'!$F$21 -> 12558.845 | AS8: ='Inputs'!$F$20*POWER(1+'Inputs'!$F$22,41)*'Inputs'!$F$21 -> 12935.611 | AT8: ='Inputs'!$F$20*POWER(1+'Inputs'!$F$22,42)*'Inputs'!$F$21 -> 13323.679 | AU8: ='Inputs'!$F$20*POWER(1+'Inputs'!$F$22,43)*'Inputs'!$F$21 -> 13723.39
A9: Storefront Revenue | B9: $/month | C9: Required Smith sales after meal prep and frozen pizza × six-month ramp | D9: =MAX(0,D36-D7-D8)*(IF(D$5<'Inputs'!$F$23,0,CHOOSE(MIN(7,MAX(1,(YEAR(D$5)-YEAR('Inputs'!$F$23))*12+MONTH(D$5)-MONTH('Inputs'!$F$23)+1)),'Inputs'!$F$50,'Inputs'!$F$51,'Inputs'!$F$52,'Inputs'!$F$53,'Inputs'!$F$54,'Inputs'!$F$55,'Inputs'!$F$55))) -> 0 | E9: =MAX(0,E36-E7-E8)*(IF(E$5<'Inputs'!$F$23,0,CHOOSE(MIN(7,MAX(1,(YEAR(E$5)-YEAR('Inputs'!$F$23))*12+MONTH(E$5)-MONTH('Inputs'!$F$23)+1)),'Inputs'!$F$50,'Inputs'!$F$51,'Inputs'!$F$52,'Inputs'!$F$53,'Inputs'!$F$54,'Inputs'!$F$55,'Inputs'!$F$55))) -> 0 | F9: =MAX(0,F36-F7-F8)*(IF(F$5<'Inputs'!$F$23,0,CHOOSE(MIN(7,MAX(1,(YEAR(F$5)-YEAR('Inputs'!$F$23))*12+MONTH(F$5)-MONTH('Inputs'!$F$23)+1)),'Inputs'!$F$50,'Inputs'!$F$51,'Inputs'!$F$52,'Inputs'!$F$53,'Inputs'!$F$54,'Inputs'!$F$55,'Inputs'!$F$55))) -> 0 | G9: =MAX(0,G36-G7-G8)*(IF(G$5<'Inputs'!$F$23,0,CHOOSE(MIN(7,MAX(1,(YEAR(G$5)-YEAR('Inputs'!$F$23))*12+MONTH(G$5)-MONTH('Inputs'!$F$23)+1)),'Inputs'!$F$50,'Inputs'!$F$51,'Inputs'!$F$52,'Inputs'!$F$53,'Inputs'!$F$54,'Inputs'!$F$55,'Inputs'!$F$55))) -> 0 | H9: =MAX(0,H36-H7-H8)*(IF(H$5<'Inputs'!$F$23,0,CHOOSE(MIN(7,MAX(1,(YEAR(H$5)-YEAR('Inputs'!$F$23))*12+MONTH(H$5)-MONTH('Inputs'!$F$23)+1)),'Inputs'!$F$50,'Inputs'!$F$51,'Inputs'!$F$52,'Inputs'!$F$53,'Inputs'!$F$54,'Inputs'!$F$55,'Inputs'!$F$55))) -> 0 | I9: =MAX(0,I36-I7-I8)*(IF(I$5<'Inputs'!$F$23,0,CHOOSE(MIN(7,MAX(1,(YEAR(I$5)-YEAR('Inputs'!$F$23))*12+MONTH(I$5)-MONTH('Inputs'!$F$23)+1)),'Inputs'!$F$50,'Inputs'!$F$51,'Inputs'!$F$52,'Inputs'!$F$53,'Inputs'!$F$54,'Inputs'!$F$55,'Inputs'!$F$55))) -> 9596.269 | J9: =MAX(0,J36-J7-J8)*(IF(J$5<'Inputs'!$F$23,0,CHOOSE(MIN(7,MAX(1,(YEAR(J$5)-YEAR('Inputs'!$F$23))*12+MONTH(J$5)-MONTH('Inputs'!$F$23)+1)),'Inputs'!$F$50,'Inputs'!$F$51,'Inputs'!$F$52,'Inputs'!$F$53,'Inputs'!$F$54,'Inputs'!$F$55,'Inputs'!$F$55))) -> 13594.152 | K9: =MAX(0,K36-K7-K8)*(IF(K$5<'Inputs'!$F$23,0,CHOOSE(MIN(7,MAX(1,(YEAR(K$5)-YEAR('Inputs'!$F$23))*12+MONTH(K$5)-MONTH('Inputs'!$F$23)+1)),'Inputs'!$F$50,'Inputs'!$F$51,'Inputs'!$F$52,'Inputs'!$F$53,'Inputs'!$F$54,'Inputs'!$F$55,'Inputs'!$F$55))) -> 17519.298 | ... AU9: =MAX(0,AU36-AU7-AU8)*(IF(AU$5<'Inputs'!$F$23,0,CHOOSE(MIN(7,MAX(1,(YEAR(AU$5)-YEAR('Inputs'!$F$23))*12+MONTH(AU$5)-MONTH('Inputs'!$F$23)+1)),'Inputs'!$F$50,'Inputs'!$F$51,'Inputs'!$F$52,'Inputs'!$F$53,'Inputs'!$F$54,'Inputs'!$F$55,'Inputs'!$F$55))) -> 27931.355
A10: Smith Revenue | B10: $/month | C10: Meal prep + frozen pizza + storefront | D10: =SUM(D7:D9) -> 8184.42 | E10: =SUM(E7:E9) -> 8386.6084 | F10: =SUM(F7:F9) -> 8593.9956 | G10: =SUM(G7:G9) -> 8806.7201 | H10: =SUM(H7:H9) -> 9024.9245 | I10: =SUM(I7:I9) -> 18845.024 | J10: =SUM(J7:J9) -> 23072.514 | K10: =SUM(K7:K9) -> 27233.199 | ... AU10: =SUM(AU7:AU9) -> 51811.111
A11: Airbnb Revenue | B11: $/month | C11: Nonfood revenue at the second venue | D11: ='Inputs'!$F$11*'Inputs'!$F$48*(IF(D$5<'Inputs'!$F$57,0,IF(D$5<='Inputs'!$F$58,'Inputs'!$F$10,IF(D$5>='Inputs'!$F$59,'Inputs'!$F$9,0)))) -> 9600 | E11: ='Inputs'!$F$11*'Inputs'!$F$48*(IF(E$5<'Inputs'!$F$57,0,IF(E$5<='Inputs'!$F$58,'Inputs'!$F$10,IF(E$5>='Inputs'!$F$59,'Inputs'!$F$9,0)))) -> 9600 | F11: ='Inputs'!$F$11*'Inputs'!$F$48*(IF(F$5<'Inputs'!$F$57,0,IF(F$5<='Inputs'!$F$58,'Inputs'!$F$10,IF(F$5>='Inputs'!$F$59,'Inputs'!$F$9,0)))) -> 9600 | G11: ='Inputs'!$F$11*'Inputs'!$F$48*(IF(G$5<'Inputs'!$F$57,0,IF(G$5<='Inputs'!$F$58,'Inputs'!$F$10,IF(G$5>='Inputs'!$F$59,'Inputs'!$F$9,0)))) -> 9600 | H11: ='Inputs'!$F$11*'Inputs'!$F$48*(IF(H$5<'Inputs'!$F$57,0,IF(H$5<='Inputs'!$F$58,'Inputs'!$F$10,IF(H$5>='Inputs'!$F$59,'Inputs'!$F$9,0)))) -> 9600 | I11: ='Inputs'!$F$11*'Inputs'!$F$48*(IF(I$5<'Inputs'!$F$57,0,IF(I$5<='Inputs'!$F$58,'Inputs'!$F$10,IF(I$5>='Inputs'!$F$59,'Inputs'!$F$9,0)))) -> 9600 | J11: ='Inputs'!$F$11*'Inputs'!$F$48*(IF(J$5<'Inputs'!$F$57,0,IF(J$5<='Inputs'!$F$58,'Inputs'!$F$10,IF(J$5>='Inputs'!$F$59,'Inputs'!$F$9,0)))) -> 9600 | K11: ='Inputs'!$F$11*'Inputs'!$F$48*(IF(K$5<'Inputs'!$F$57,0,IF(K$5<='Inputs'!$F$58,'Inputs'!$F$10,IF(K$5>='Inputs'!$F$59,'Inputs'!$F$9,0)))) -> 9600 | ... AU11: ='Inputs'!$F$11*'Inputs'!$F$48*(IF(AU$5<'Inputs'!$F$57,0,IF(AU$5<='Inputs'!$F$58,'Inputs'!$F$10,IF(AU$5>='Inputs'!$F$59,'Inputs'!$F$9,0)))) -> 9600
A12: Small Events Revenue | B12: $/month | C12: Gross small-event revenue | D12: ='Inputs'!$F$13*'Inputs'!$F$14*(IF(D$5<'Inputs'!$F$57,0,IF(D$5<='Inputs'!$F$58,'Inputs'!$F$10,IF(D$5>='Inputs'!$F$59,'Inputs'!$F$9,0)))) -> 6300 | E12: ='Inputs'!$F$13*'Inputs'!$F$14*(IF(E$5<'Inputs'!$F$57,0,IF(E$5<='Inputs'!$F$58,'Inputs'!$F$10,IF(E$5>='Inputs'!$F$59,'Inputs'!$F$9,0)))) -> 6300 | F12: ='Inputs'!$F$13*'Inputs'!$F$14*(IF(F$5<'Inputs'!$F$57,0,IF(F$5<='Inputs'!$F$58,'Inputs'!$F$10,IF(F$5>='Inputs'!$F$59,'Inputs'!$F$9,0)))) -> 6300 | G12: ='Inputs'!$F$13*'Inputs'!$F$14*(IF(G$5<'Inputs'!$F$57,0,IF(G$5<='Inputs'!$F$58,'Inputs'!$F$10,IF(G$5>='Inputs'!$F$59,'Inputs'!$F$9,0)))) -> 6300 | H12: ='Inputs'!$F$13*'Inputs'!$F$14*(IF(H$5<'Inputs'!$F$57,0,IF(H$5<='Inputs'!$F$58,'Inputs'!$F$10,IF(H$5>='Inputs'!$F$59,'Inputs'!$F$9,0)))) -> 6300 | I12: ='Inputs'!$F$13*'Inputs'!$F$14*(IF(I$5<'Inputs'!$F$57,0,IF(I$5<='Inputs'!$F$58,'Inputs'!$F$10,IF(I$5>='Inputs'!$F$59,'Inputs'!$F$9,0)))) -> 6300 | J12: ='Inputs'!$F$13*'Inputs'!$F$14*(IF(J$5<'Inputs'!$F$57,0,IF(J$5<='Inputs'!$F$58,'Inputs'!$F$10,IF(J$5>='Inputs'!$F$59,'Inputs'!$F$9,0)))) -> 6300 | K12: ='Inputs'!$F$13*'Inputs'!$F$14*(IF(K$5<'Inputs'!$F$57,0,IF(K$5<='Inputs'!$F$58,'Inputs'!$F$10,IF(K$5>='Inputs'!$F$59,'Inputs'!$F$9,0)))) -> 6300 | ... AU12: ='Inputs'!$F$13*'Inputs'!$F$14*(IF(AU$5<'Inputs'!$F$57,0,IF(AU$5<='Inputs'!$F$58,'Inputs'!$F$10,IF(AU$5>='Inputs'!$F$59,'Inputs'!$F$9,0)))) -> 6300
A13: Personal Chef Revenue | B13: $/month | C13: Food revenue from packages at the second venue | D13: ='Inputs'!$F$16*'Inputs'!$F$17*(IF(D$5<'Inputs'!$F$57,0,IF(D$5<='Inputs'!$F$58,'Inputs'!$F$10,IF(D$5>='Inputs'!$F$59,'Inputs'!$F$9,0)))) -> 7200 | E13: ='Inputs'!$F$16*'Inputs'!$F$17*(IF(E$5<'Inputs'!$F$57,0,IF(E$5<='Inputs'!$F$58,'Inputs'!$F$10,IF(E$5>='Inputs'!$F$59,'Inputs'!$F$9,0)))) -> 7200 | F13: ='Inputs'!$F$16*'Inputs'!$F$17*(IF(F$5<'Inputs'!$F$57,0,IF(F$5<='Inputs'!$F$58,'Inputs'!$F$10,IF(F$5>='Inputs'!$F$59,'Inputs'!$F$9,0)))) -> 7200 | G13: ='Inputs'!$F$16*'Inputs'!$F$17*(IF(G$5<'Inputs'!$F$57,0,IF(G$5<='Inputs'!$F$58,'Inputs'!$F$10,IF(G$5>='Inputs'!$F$59,'Inputs'!$F$9,0)))) -> 7200 | H13: ='Inputs'!$F$16*'Inputs'!$F$17*(IF(H$5<'Inputs'!$F$57,0,IF(H$5<='Inputs'!$F$58,'Inputs'!$F$10,IF(H$5>='Inputs'!$F$59,'Inputs'!$F$9,0)))) -> 7200 | I13: ='Inputs'!$F$16*'Inputs'!$F$17*(IF(I$5<'Inputs'!$F$57,0,IF(I$5<='Inputs'!$F$58,'Inputs'!$F$10,IF(I$5>='Inputs'!$F$59,'Inputs'!$F$9,0)))) -> 7200 | J13: ='Inputs'!$F$16*'Inputs'!$F$17*(IF(J$5<'Inputs'!$F$57,0,IF(J$5<='Inputs'!$F$58,'Inputs'!$F$10,IF(J$5>='Inputs'!$F$59,'Inputs'!$F$9,0)))) -> 7200 | K13: ='Inputs'!$F$16*'Inputs'!$F$17*(IF(K$5<'Inputs'!$F$57,0,IF(K$5<='Inputs'!$F$58,'Inputs'!$F$10,IF(K$5>='Inputs'!$F$59,'Inputs'!$F$9,0)))) -> 7200 | ... AU13: ='Inputs'!$F$16*'Inputs'!$F$17*(IF(AU$5<'Inputs'!$F$57,0,IF(AU$5<='Inputs'!$F$58,'Inputs'!$F$10,IF(AU$5>='Inputs'!$F$59,'Inputs'!$F$9,0)))) -> 7200
A14: Second Venue Revenue | B14: $/month | C14: Airbnb + small events + personal chef | D14: =SUM(D11:D13) -> 23100 | E14: =SUM(E11:E13) -> 23100 | F14: =SUM(F11:F13) -> 23100 | G14: =SUM(G11:G13) -> 23100 | H14: =SUM(H11:H13) -> 23100 | I14: =SUM(I11:I13) -> 23100 | J14: =SUM(J11:J13) -> 23100 | K14: =SUM(K11:K13) -> 23100 | ... AU14: =SUM(AU11:AU13) -> 23100
A15: Total Revenue | B15: $/month | C15: Smith + second venue | D15: =D10+D14 -> 31284.42 | E15: =E10+E14 -> 31486.608 | F15: =F10+F14 -> 31693.996 | G15: =G10+G14 -> 31906.72 | H15: =H10+H14 -> 32124.925 | I15: =I10+I14 -> 41945.024 | J15: =J10+J14 -> 46172.514 | K15: =K10+K14 -> 50333.199 | ... AU15: =AU10+AU14 -> 74911.111
A16: Food Revenue | B16: $/month | C16: Smith + event food component + personal chef | D16: =D10+'Inputs'!$F$13*'Inputs'!$F$15*(IF(D$5<'Inputs'!$F$57,0,IF(D$5<='Inputs'!$F$58,'Inputs'!$F$10,IF(D$5>='Inputs'!$F$59,'Inputs'!$F$9,0))))+D13 -> 19434.42 | E16: =E10+'Inputs'!$F$13*'Inputs'!$F$15*(IF(E$5<'Inputs'!$F$57,0,IF(E$5<='Inputs'!$F$58,'Inputs'!$F$10,IF(E$5>='Inputs'!$F$59,'Inputs'!$F$9,0))))+E13 -> 19636.608 | F16: =F10+'Inputs'!$F$13*'Inputs'!$F$15*(IF(F$5<'Inputs'!$F$57,0,IF(F$5<='Inputs'!$F$58,'Inputs'!$F$10,IF(F$5>='Inputs'!$F$59,'Inputs'!$F$9,0))))+F13 -> 19843.996 | G16: =G10+'Inputs'!$F$13*'Inputs'!$F$15*(IF(G$5<'Inputs'!$F$57,0,IF(G$5<='Inputs'!$F$58,'Inputs'!$F$10,IF(G$5>='Inputs'!$F$59,'Inputs'!$F$9,0))))+G13 -> 20056.72 | H16: =H10+'Inputs'!$F$13*'Inputs'!$F$15*(IF(H$5<'Inputs'!$F$57,0,IF(H$5<='Inputs'!$F$58,'Inputs'!$F$10,IF(H$5>='Inputs'!$F$59,'Inputs'!$F$9,0))))+H13 -> 20274.925 | I16: =I10+'Inputs'!$F$13*'Inputs'!$F$15*(IF(I$5<'Inputs'!$F$57,0,IF(I$5<='Inputs'!$F$58,'Inputs'!$F$10,IF(I$5>='Inputs'!$F$59,'Inputs'!$F$9,0))))+I13 -> 30095.024 | J16: =J10+'Inputs'!$F$13*'Inputs'!$F$15*(IF(J$5<'Inputs'!$F$57,0,IF(J$5<='Inputs'!$F$58,'Inputs'!$F$10,IF(J$5>='Inputs'!$F$59,'Inputs'!$F$9,0))))+J13 -> 34322.514 | K16: =K10+'Inputs'!$F$13*'Inputs'!$F$15*(IF(K$5<'Inputs'!$F$57,0,IF(K$5<='Inputs'!$F$58,'Inputs'!$F$10,IF(K$5>='Inputs'!$F$59,'Inputs'!$F$9,0))))+K13 -> 38483.199 | ... AU16: =AU10+'Inputs'!$F$13*'Inputs'!$F$15*(IF(AU$5<'Inputs'!$F$57,0,IF(AU$5<='Inputs'!$F$58,'Inputs'!$F$10,IF(AU$5>='Inputs'!$F$59,'Inputs'!$F$9,0))))+AU13 -> 63061.111
A17: COST OF SALES & LABOR
A18: Food COGS | B18: $/month | C18: Applied only to food revenue | D18: =D16*'Inputs'!$F$27 -> 3886.884 | E18: =E16*'Inputs'!$F$27 -> 3927.3217 | F18: =F16*'Inputs'!$F$27 -> 3968.7991 | G18: =G16*'Inputs'!$F$27 -> 4011.344 | H18: =H16*'Inputs'!$F$27 -> 4054.9849 | I18: =I16*'Inputs'!$F$27 -> 6019.0048 | J18: =J16*'Inputs'!$F$27 -> 6864.5029 | K18: =K16*'Inputs'!$F$27 -> 7696.6397 | ... AU18: =AU16*'Inputs'!$F$27 -> 12612.222
A19: Food Cost % | B19: % revenue | C19: Food COGS ÷ food revenue | D19: =IFERROR(D18/D16,0) -> 0.2 | E19: =IFERROR(E18/E16,0) -> 0.2 | F19: =IFERROR(F18/F16,0) -> 0.2 | G19: =IFERROR(G18/G16,0) -> 0.2 | H19: =IFERROR(H18/H16,0) -> 0.2 | I19: =IFERROR(I18/I16,0) -> 0.2 | J19: =IFERROR(J18/J16,0) -> 0.2 | K19: =IFERROR(K18/K16,0) -> 0.2 | ... AU19: =IFERROR(AU18/AU16,0) -> 0.2
A20: Venue Variable Cost | B20: $/month | C20: Applied only to Airbnb revenue | D20: =D11*'Inputs'!$F$12 -> 1152 | E20: =E11*'Inputs'!$F$12 -> 1152 | F20: =F11*'Inputs'!$F$12 -> 1152 | G20: =G11*'Inputs'!$F$12 -> 1152 | H20: =H11*'Inputs'!$F$12 -> 1152 | I20: =I11*'Inputs'!$F$12 -> 1152 | J20: =J11*'Inputs'!$F$12 -> 1152 | K20: =K11*'Inputs'!$F$12 -> 1152 | ... AU20: =AU11*'Inputs'!$F$12 -> 1152
A21: Packaging & Delivery | B21: $/month | C21: Applied to food revenue | D21: =D16*'Inputs'!$F$37 -> 388.6884 | E21: =E16*'Inputs'!$F$37 -> 392.73217 | F21: =F16*'Inputs'!$F$37 -> 396.87991 | G21: =G16*'Inputs'!$F$37 -> 401.1344 | H21: =H16*'Inputs'!$F$37 -> 405.49849 | I21: =I16*'Inputs'!$F$37 -> 601.90048 | J21: =J16*'Inputs'!$F$37 -> 686.45029 | K21: =K16*'Inputs'!$F$37 -> 769.66397 | ... AU21: =AU16*'Inputs'!$F$37 -> 1261.2222
A22: Direct Paid Labor | B22: $/month | C22: Phase rate × total revenue | D22: =D15*(IF(D$5<'Inputs'!$F$23,'Inputs'!$F$28,IF(D$5<EDATE('Inputs'!$F$23,6),'Inputs'!$F$29,'Inputs'!$F$30))) -> 3128.442 | E22: =E15*(IF(E$5<'Inputs'!$F$23,'Inputs'!$F$28,IF(E$5<EDATE('Inputs'!$F$23,6),'Inputs'!$F$29,'Inputs'!$F$30))) -> 3148.6608 | F22: =F15*(IF(F$5<'Inputs'!$F$23,'Inputs'!$F$28,IF(F$5<EDATE('Inputs'!$F$23,6),'Inputs'!$F$29,'Inputs'!$F$30))) -> 3169.3996 | G22: =G15*(IF(G$5<'Inputs'!$F$23,'Inputs'!$F$28,IF(G$5<EDATE('Inputs'!$F$23,6),'Inputs'!$F$29,'Inputs'!$F$30))) -> 3190.672 | H22: =H15*(IF(H$5<'Inputs'!$F$23,'Inputs'!$F$28,IF(H$5<EDATE('Inputs'!$F$23,6),'Inputs'!$F$29,'Inputs'!$F$30))) -> 3212.4925 | I22: =I15*(IF(I$5<'Inputs'!$F$23,'Inputs'!$F$28,IF(I$5<EDATE('Inputs'!$F$23,6),'Inputs'!$F$29,'Inputs'!$F$30))) -> 5872.3034 | J22: =J15*(IF(J$5<'Inputs'!$F$23,'Inputs'!$F$28,IF(J$5<EDATE('Inputs'!$F$23,6),'Inputs'!$F$29,'Inputs'!$F$30))) -> 6464.152 | K22: =K15*(IF(K$5<'Inputs'!$F$23,'Inputs'!$F$28,IF(K$5<EDATE('Inputs'!$F$23,6),'Inputs'!$F$29,'Inputs'!$F$30))) -> 7046.6478 | ... AU22: =AU15*(IF(AU$5<'Inputs'!$F$23,'Inputs'!$F$28,IF(AU$5<EDATE('Inputs'!$F$23,6),'Inputs'!$F$29,'Inputs'!$F$30))) -> 8240.2222
A23: Founder Economic Salary | B23: $/month | C23: Catherine + Weston combined economic compensation | D23: ='Inputs'!$F$32 -> 7500 | E23: ='Inputs'!$F$32 -> 7500 | F23: ='Inputs'!$F$32 -> 7500 | G23: ='Inputs'!$F$32 -> 7500 | H23: ='Inputs'!$F$32 -> 7500 | I23: ='Inputs'!$F$32 -> 7500 | J23: ='Inputs'!$F$32 -> 7500 | K23: ='Inputs'!$F$32 -> 7500 | ... AU23: ='Inputs'!$F$32 -> 7500
A24: Direct Payroll Burden | B24: $/month | C24: Burden on direct paid labor | D24: =D22*'Inputs'!$F$31 -> 250.27536 | E24: =E22*'Inputs'!$F$31 -> 251.89287 | F24: =F22*'Inputs'!$F$31 -> 253.55196 | G24: =G22*'Inputs'!$F$31 -> 255.25376 | H24: =H22*'Inputs'!$F$31 -> 256.9994 | I24: =I22*'Inputs'!$F$31 -> 469.78427 | J24: =J22*'Inputs'!$F$31 -> 517.13216 | K24: =K22*'Inputs'!$F$31 -> 563.73182 | ... AU24: =AU22*'Inputs'!$F$31 -> 659.21778
A25: Total Labor | B25: $/month | C25: Direct labor + founder economic compensation + burden | D25: =SUM(D22,D23,D24) -> 10878.717 | E25: =SUM(E22,E23,E24) -> 10900.554 | F25: =SUM(F22,F23,F24) -> 10922.952 | G25: =SUM(G22,G23,G24) -> 10945.926 | H25: =SUM(H22,H23,H24) -> 10969.492 | I25: =SUM(I22,I23,I24) -> 13842.088 | J25: =SUM(J22,J23,J24) -> 14481.284 | K25: =SUM(K22,K23,K24) -> 15110.38 | ... AU25: =SUM(AU22,AU23,AU24) -> 16399.44
A26: Total Labor % | B26: % revenue | C26: Total labor ÷ total revenue | D26: =IFERROR(D25/D15,0) -> 0.34773595 | E26: =IFERROR(E25/E15,0) -> 0.3461965 | F26: =IFERROR(F25/F15,0) -> 0.34463788 | G26: =IFERROR(G25/G15,0) -> 0.3430602 | H26: =IFERROR(H25/H15,0) -> 0.34146358 | I26: =IFERROR(I25/I15,0) -> 0.33000548 | J26: =IFERROR(J25/J15,0) -> 0.3136343 | K26: =IFERROR(K25/K15,0) -> 0.30020702 | ... AU26: =IFERROR(AU25/AU15,0) -> 0.21891866
A27: OCCUPANCY & REQUIRED SALES
A28: Smith Rent & NNN | B28: $/month | C28: Owner-provided stepped rent schedule | D28: =IF(D$5<DATE(2026,10,1),'Inputs'!$F$41,IF(D$5<DATE(2027,1,1),'Inputs'!$F$42,IF(D$5<DATE(2027,6,1),'Inputs'!$F$43,IF(D$5<DATE(2028,1,1),'Inputs'!$F$44,'Inputs'!$F$45)))) -> 1800 | E28: =IF(E$5<DATE(2026,10,1),'Inputs'!$F$41,IF(E$5<DATE(2027,1,1),'Inputs'!$F$42,IF(E$5<DATE(2027,6,1),'Inputs'!$F$43,IF(E$5<DATE(2028,1,1),'Inputs'!$F$44,'Inputs'!$F$45)))) -> 1800 | F28: =IF(F$5<DATE(2026,10,1),'Inputs'!$F$41,IF(F$5<DATE(2027,1,1),'Inputs'!$F$42,IF(F$5<DATE(2027,6,1),'Inputs'!$F$43,IF(F$5<DATE(2028,1,1),'Inputs'!$F$44,'Inputs'!$F$45)))) -> 1800 | G28: =IF(G$5<DATE(2026,10,1),'Inputs'!$F$41,IF(G$5<DATE(2027,1,1),'Inputs'!$F$42,IF(G$5<DATE(2027,6,1),'Inputs'!$F$43,IF(G$5<DATE(2028,1,1),'Inputs'!$F$44,'Inputs'!$F$45)))) -> 2600 | H28: =IF(H$5<DATE(2026,10,1),'Inputs'!$F$41,IF(H$5<DATE(2027,1,1),'Inputs'!$F$42,IF(H$5<DATE(2027,6,1),'Inputs'!$F$43,IF(H$5<DATE(2028,1,1),'Inputs'!$F$44,'Inputs'!$F$45)))) -> 2600 | I28: =IF(I$5<DATE(2026,10,1),'Inputs'!$F$41,IF(I$5<DATE(2027,1,1),'Inputs'!$F$42,IF(I$5<DATE(2027,6,1),'Inputs'!$F$43,IF(I$5<DATE(2028,1,1),'Inputs'!$F$44,'Inputs'!$F$45)))) -> 2600 | J28: =IF(J$5<DATE(2026,10,1),'Inputs'!$F$41,IF(J$5<DATE(2027,1,1),'Inputs'!$F$42,IF(J$5<DATE(2027,6,1),'Inputs'!$F$43,IF(J$5<DATE(2028,1,1),'Inputs'!$F$44,'Inputs'!$F$45)))) -> 2600 | K28: =IF(K$5<DATE(2026,10,1),'Inputs'!$F$41,IF(K$5<DATE(2027,1,1),'Inputs'!$F$42,IF(K$5<DATE(2027,6,1),'Inputs'!$F$43,IF(K$5<DATE(2028,1,1),'Inputs'!$F$44,'Inputs'!$F$45)))) -> 2600 | ... AU28: =IF(AU$5<DATE(2026,10,1),'Inputs'!$F$41,IF(AU$5<DATE(2027,1,1),'Inputs'!$F$42,IF(AU$5<DATE(2027,6,1),'Inputs'!$F$43,IF(AU$5<DATE(2028,1,1),'Inputs'!$F$44,'Inputs'!$F$45)))) -> 3963
A29: Smith Utilities | B29: $/month | C29: Begins on the editable transfer date | D29: =IF(D$5>='Inputs'!$F$46,'Inputs'!$F$8,0) -> 0 | E29: =IF(E$5>='Inputs'!$F$46,'Inputs'!$F$8,0) -> 0 | F29: =IF(F$5>='Inputs'!$F$46,'Inputs'!$F$8,0) -> 0 | G29: =IF(G$5>='Inputs'!$F$46,'Inputs'!$F$8,0) -> 0 | H29: =IF(H$5>='Inputs'!$F$46,'Inputs'!$F$8,0) -> 0 | I29: =IF(I$5>='Inputs'!$F$46,'Inputs'!$F$8,0) -> 700 | J29: =IF(J$5>='Inputs'!$F$46,'Inputs'!$F$8,0) -> 700 | K29: =IF(K$5>='Inputs'!$F$46,'Inputs'!$F$8,0) -> 700 | ... AU29: =IF(AU$5>='Inputs'!$F$46,'Inputs'!$F$8,0) -> 700
A30: Smith Occupancy Cost | B30: $/month | C30: Smith rent + utilities | D30: =SUM(D28:D29) -> 1800 | E30: =SUM(E28:E29) -> 1800 | F30: =SUM(F28:F29) -> 1800 | G30: =SUM(G28:G29) -> 2600 | H30: =SUM(H28:H29) -> 2600 | I30: =SUM(I28:I29) -> 3300 | J30: =SUM(J28:J29) -> 3300 | K30: =SUM(K28:K29) -> 3300 | ... AU30: =SUM(AU28:AU29) -> 4663
A31: Second Venue Rent | B31: $/month | C31: Conditional on post-trial activation | D31: =IF(D$5>='Inputs'!$F$59,'Inputs'!$F$9*'Inputs'!$F$47,0) -> 0 | E31: =IF(E$5>='Inputs'!$F$59,'Inputs'!$F$9*'Inputs'!$F$47,0) -> 0 | F31: =IF(F$5>='Inputs'!$F$59,'Inputs'!$F$9*'Inputs'!$F$47,0) -> 0 | G31: =IF(G$5>='Inputs'!$F$59,'Inputs'!$F$9*'Inputs'!$F$47,0) -> 5000 | H31: =IF(H$5>='Inputs'!$F$59,'Inputs'!$F$9*'Inputs'!$F$47,0) -> 5000 | I31: =IF(I$5>='Inputs'!$F$59,'Inputs'!$F$9*'Inputs'!$F$47,0) -> 5000 | J31: =IF(J$5>='Inputs'!$F$59,'Inputs'!$F$9*'Inputs'!$F$47,0) -> 5000 | K31: =IF(K$5>='Inputs'!$F$59,'Inputs'!$F$9*'Inputs'!$F$47,0) -> 5000 | ... AU31: =IF(AU$5>='Inputs'!$F$59,'Inputs'!$F$9*'Inputs'!$F$47,0) -> 5000
A32: Hopkins Admin | B32: $/month | C32: Ongoing Hopkins facility/admin charge | D32: ='Inputs'!$F$49 -> 150 | E32: ='Inputs'!$F$49 -> 150 | F32: ='Inputs'!$F$49 -> 150 | G32: ='Inputs'!$F$49 -> 150 | H32: ='Inputs'!$F$49 -> 150 | I32: ='Inputs'!$F$49 -> 150 | J32: ='Inputs'!$F$49 -> 150 | K32: ='Inputs'!$F$49 -> 150 | ... AU32: ='Inputs'!$F$49 -> 150
A33: Total Occupancy Cost | B33: $/month | C33: Smith + second venue + Hopkins | D33: =SUM(D30,D31,D32) -> 1950 | E33: =SUM(E30,E31,E32) -> 1950 | F33: =SUM(F30,F31,F32) -> 1950 | G33: =SUM(G30,G31,G32) -> 7750 | H33: =SUM(H30,H31,H32) -> 7750 | I33: =SUM(I30,I31,I32) -> 8450 | J33: =SUM(J30,J31,J32) -> 8450 | K33: =SUM(K30,K31,K32) -> 8450 | ... AU33: =SUM(AU30,AU31,AU32) -> 9813
A34: Consolidated Occupancy % | B34: % revenue | C34: Total occupancy ÷ total revenue | D34: =IFERROR(D33/D15,0) -> 0.062331346 | E34: =IFERROR(E33/E15,0) -> 0.061931091 | F34: =IFERROR(F33/F15,0) -> 0.061525849 | G34: =IFERROR(G33/G15,0) -> 0.24289554 | H34: =IFERROR(H33/H15,0) -> 0.2412457 | I34: =IFERROR(I33/I15,0) -> 0.20145417 | J34: =IFERROR(J33/J15,0) -> 0.18300931 | K34: =IFERROR(K33/K15,0) -> 0.16788124 | ... AU34: =IFERROR(AU33/AU15,0) -> 0.13099525
A35: Smith Occupancy % | B35: % revenue | C35: Smith occupancy ÷ Smith revenue | D35: =IFERROR(D30/D10,0) -> 0.21993006 | E35: =IFERROR(E30/E10,0) -> 0.21462788 | F35: =IFERROR(F30/F10,0) -> 0.20944856 | G35: =IFERROR(G30/G10,0) -> 0.29522909 | H35: =IFERROR(H30/H10,0) -> 0.28809105 | I35: =IFERROR(I30/I10,0) -> 0.17511254 | J35: =IFERROR(J30/J10,0) -> 0.14302732 | K35: =IFERROR(K30/K10,0) -> 0.12117563 | ... AU35: =IFERROR(AU30/AU10,0) -> 0.09
A36: Required Smith Revenue | B36: $/month | C36: Smith occupancy ÷ target ratio | D36: =D30/'Inputs'!$F$24 -> 20000 | E36: =E30/'Inputs'!$F$24 -> 20000 | F36: =F30/'Inputs'!$F$24 -> 20000 | G36: =G30/'Inputs'!$F$24 -> 28888.889 | H36: =H30/'Inputs'!$F$24 -> 28888.889 | I36: =I30/'Inputs'!$F$24 -> 36666.667 | J36: =J30/'Inputs'!$F$24 -> 36666.667 | K36: =K30/'Inputs'!$F$24 -> 36666.667 | ... AU36: =AU30/'Inputs'!$F$24 -> 51811.111
A37: Smith Revenue Gap / (Surplus) | B37: $/month | C37: Required less modeled Smith revenue | D37: =D36-D10 -> 11815.58 | E37: =E36-E10 -> 11613.392 | F37: =F36-F10 -> 11406.004 | G37: =G36-G10 -> 20082.169 | H37: =H36-H10 -> 19863.964 | I37: =I36-I10 -> 17821.643 | J37: =J36-J10 -> 13594.152 | K37: =K36-K10 -> 9433.4682 | ... AU37: =AU36-AU10 -> 0
A38: Required Storefront Transactions / Day | B38: transactions | C38: Required storefront sales ÷ ticket ÷ open days | D38: =MAX(0,D36-D7-D8)/('Inputs'!$F$25*'Inputs'!$F$26) -> 22.377992 | E38: =MAX(0,E36-E7-E8)/('Inputs'!$F$25*'Inputs'!$F$26) -> 21.99506 | F38: =MAX(0,F36-F7-F8)/('Inputs'!$F$25*'Inputs'!$F$26) -> 21.602281 | G38: =MAX(0,G36-G7-G8)/('Inputs'!$F$25*'Inputs'!$F$26) -> 38.034411 | H38: =MAX(0,H36-H7-H8)/('Inputs'!$F$25*'Inputs'!$F$26) -> 37.621145 | I38: =MAX(0,I36-I7-I8)/('Inputs'!$F$25*'Inputs'!$F$26) -> 51.927863 | J38: =MAX(0,J36-J7-J8)/('Inputs'!$F$25*'Inputs'!$F$26) -> 51.493001 | K38: =MAX(0,K36-K7-K8)/('Inputs'!$F$25*'Inputs'!$F$26) -> 51.046906 | ... AU38: =MAX(0,AU36-AU7-AU8)/('Inputs'!$F$25*'Inputs'!$F$26) -> 52.900293
A39: OPERATING RESULT & CASH
A40: Payment Processing | B40: $/month | C40: 3% of revenue other than Airbnb | D40: ='Inputs'!$F$38*(D15-D11) -> 650.5326 | E40: ='Inputs'!$F$38*(E15-E11) -> 656.59825 | F40: ='Inputs'!$F$38*(F15-F11) -> 662.81987 | G40: ='Inputs'!$F$38*(G15-G11) -> 669.2016 | H40: ='Inputs'!$F$38*(H15-H11) -> 675.74774 | I40: ='Inputs'!$F$38*(I15-I11) -> 970.35072 | J40: ='Inputs'!$F$38*(J15-J11) -> 1097.1754 | K40: ='Inputs'!$F$38*(K15-K11) -> 1221.996 | ... AU40: ='Inputs'!$F$38*(AU15-AU11) -> 1959.3333
A41: Fixed Other OpEx | B41: $/month | C41: 3% inflation on each model-year anniversary | D41: ='Inputs'!$F$39*POWER(1+'Inputs'!$F$56,INT(((YEAR(D$5)-YEAR($D$5))*12+MONTH(D$5)-MONTH($D$5))/12)) -> 1518.26 | E41: ='Inputs'!$F$39*POWER(1+'Inputs'!$F$56,INT(((YEAR(E$5)-YEAR($D$5))*12+MONTH(E$5)-MONTH($D$5))/12)) -> 1518.26 | F41: ='Inputs'!$F$39*POWER(1+'Inputs'!$F$56,INT(((YEAR(F$5)-YEAR($D$5))*12+MONTH(F$5)-MONTH($D$5))/12)) -> 1518.26 | G41: ='Inputs'!$F$39*POWER(1+'Inputs'!$F$56,INT(((YEAR(G$5)-YEAR($D$5))*12+MONTH(G$5)-MONTH($D$5))/12)) -> 1518.26 | H41: ='Inputs'!$F$39*POWER(1+'Inputs'!$F$56,INT(((YEAR(H$5)-YEAR($D$5))*12+MONTH(H$5)-MONTH($D$5))/12)) -> 1518.26 | I41: ='Inputs'!$F$39*POWER(1+'Inputs'!$F$56,INT(((YEAR(I$5)-YEAR($D$5))*12+MONTH(I$5)-MONTH($D$5))/12)) -> 1518.26 | J41: ='Inputs'!$F$39*POWER(1+'Inputs'!$F$56,INT(((YEAR(J$5)-YEAR($D$5))*12+MONTH(J$5)-MONTH($D$5))/12)) -> 1518.26 | K41: ='Inputs'!$F$39*POWER(1+'Inputs'!$F$56,INT(((YEAR(K$5)-YEAR($D$5))*12+MONTH(K$5)-MONTH($D$5))/12)) -> 1518.26 | ... AU41: ='Inputs'!$F$39*POWER(1+'Inputs'!$F$56,INT(((YEAR(AU$5)-YEAR($D$5))*12+MONTH(AU$5)-MONTH($D$5))/12)) -> 1659.0437
A42: Operating Profit | B42: $/month | C42: Accrual operating profit after founder economic compensation | D42: =D15-D18-D20-D21-D25-D33-D40-D41 -> 10859.338 | E42: =E15-E18-E20-E21-E25-E33-E40-E41 -> 10989.143 | F42: =F15-F18-F20-F21-F25-F33-F40-F41 -> 11122.285 | G42: =G15-G18-G20-G21-G25-G33-G40-G41 -> 5458.8543 | H42: =H15-H18-H20-H21-H25-H33-H40-H41 -> 5598.9415 | I42: =I15-I18-I20-I21-I25-I33-I40-I41 -> 9391.4205 | J42: =J15-J18-J20-J21-J25-J33-J40-J41 -> 11922.842 | K42: =K15-K18-K20-K21-K25-K33-K40-K41 -> 14414.259 | ... AU42: =AU15-AU18-AU20-AU21-AU25-AU33-AU40-AU41 -> 30054.85
A43: Operating Margin | B43: % revenue | C43: Operating profit ÷ total revenue | D43: =IFERROR(D42/D15,0) -> 0.34711648 | E43: =IFERROR(E42/E15,0) -> 0.34901004 | F43: =IFERROR(F42/F15,0) -> 0.3509272 | G43: =IFERROR(G42/G15,0) -> 0.17108792 | H43: =IFERROR(H42/H15,0) -> 0.17428653 | I43: =IFERROR(I42/I15,0) -> 0.22389832 | J43: =IFERROR(J42/J15,0) -> 0.25822379 | K43: =IFERROR(K42/K15,0) -> 0.28637678 | ... AU43: =IFERROR(AU42/AU15,0) -> 0.40120683
A44: Founder Cash Salary | B44: $/month | C44: Current salary follows the editable cash-pay start | D44: =IF(D$5>='Inputs'!$F$33,'Inputs'!$F$32,0) -> 7500 | E44: =IF(E$5>='Inputs'!$F$33,'Inputs'!$F$32,0) -> 7500 | F44: =IF(F$5>='Inputs'!$F$33,'Inputs'!$F$32,0) -> 7500 | G44: =IF(G$5>='Inputs'!$F$33,'Inputs'!$F$32,0) -> 7500 | H44: =IF(H$5>='Inputs'!$F$33,'Inputs'!$F$32,0) -> 7500 | I44: =IF(I$5>='Inputs'!$F$33,'Inputs'!$F$32,0) -> 7500 | J44: =IF(J$5>='Inputs'!$F$33,'Inputs'!$F$32,0) -> 7500 | K44: =IF(K$5>='Inputs'!$F$33,'Inputs'!$F$32,0) -> 7500 | ... AU44: =IF(AU$5>='Inputs'!$F$33,'Inputs'!$F$32,0) -> 7500
A45: Founder Deferred Repayment | B45: $/month | C45: Editable backpay request capped at available deferred balance | D45: =MIN(MAX(0,IF(D$5>='Inputs'!$F$35,'Inputs'!$F$36,0)),MAX(0,'Inputs'!$F$34+D23-D44)) -> 0 | E45: =MIN(MAX(0,IF(E$5>='Inputs'!$F$35,'Inputs'!$F$36,0)),MAX(0,D47+E23-E44)) -> 0 | F45: =MIN(MAX(0,IF(F$5>='Inputs'!$F$35,'Inputs'!$F$36,0)),MAX(0,E47+F23-F44)) -> 0 | G45: =MIN(MAX(0,IF(G$5>='Inputs'!$F$35,'Inputs'!$F$36,0)),MAX(0,F47+G23-G44)) -> 0 | H45: =MIN(MAX(0,IF(H$5>='Inputs'!$F$35,'Inputs'!$F$36,0)),MAX(0,G47+H23-H44)) -> 0 | I45: =MIN(MAX(0,IF(I$5>='Inputs'!$F$35,'Inputs'!$F$36,0)),MAX(0,H47+I23-I44)) -> 0 | J45: =MIN(MAX(0,IF(J$5>='Inputs'!$F$35,'Inputs'!$F$36,0)),MAX(0,I47+J23-J44)) -> 0 | K45: =MIN(MAX(0,IF(K$5>='Inputs'!$F$35,'Inputs'!$F$36,0)),MAX(0,J47+K23-K44)) -> 0 | L45: =MIN(MAX(0,IF(L$5>='Inputs'!$F$35,'Inputs'!$F$36,0)),MAX(0,K47+L23-L44)) -> 0 | ... AU45: =MIN(MAX(0,IF(AU$5>='Inputs'!$F$35,'Inputs'!$F$36,0)),MAX(0,AT47+AU23-AU44)) -> 0
A46: Deferred Salary Movement | B46: $/month | C46: Economic compensation less current cash salary and repayment | D46: =D23-D44-D45 -> 0 | E46: =E23-E44-E45 -> 0 | F46: =F23-F44-F45 -> 0 | G46: =G23-G44-G45 -> 0 | H46: =H23-H44-H45 -> 0 | I46: =I23-I44-I45 -> 0 | J46: =J23-J44-J45 -> 0 | K46: =K23-K44-K45 -> 0 | ... AU46: =AU23-AU44-AU45 -> 0
A47: Founder Deferred Balance | B47: $ balance | C47: Prior balance + current movement | D47: ='Inputs'!$F$34+D46 -> 0 | E47: =D47+E46 -> 0 | F47: =E47+F46 -> 0 | G47: =F47+G46 -> 0 | H47: =G47+H46 -> 0 | I47: =H47+I46 -> 0 | J47: =I47+J46 -> 0 | K47: =J47+K46 -> 0 | L47: =K47+L46 -> 0 | ... AU47: =AT47+AU46 -> 0
A48: Monthly Operating Cash | B48: $/month | C48: Operating profit + economic compensation − current cash − repayment | D48: =D42+D23-D44-D45 -> 10859.338 | E48: =E42+E23-E44-E45 -> 10989.143 | F48: =F42+F23-F44-F45 -> 11122.285 | G48: =G42+G23-G44-G45 -> 5458.8543 | H48: =H42+H23-H44-H45 -> 5598.9415 | I48: =I42+I23-I44-I45 -> 9391.4205 | J48: =J42+J23-J44-J45 -> 11922.842 | K48: =K42+K23-K44-K45 -> 14414.259 | ... AU48: =AU42+AU23-AU44-AU45 -> 30054.85
A49: Cumulative Operating Cash | B49: $ balance | C49: Opening cash + cumulative monthly operating cash | D49: ='Inputs'!$F$40+D48 -> 10961.568 | E49: =D49+E48 -> 21950.71 | F49: =E49+F48 -> 33072.995 | G49: =F49+G48 -> 38531.85 | H49: =G49+H48 -> 44130.791 | I49: =H49+I48 -> 53522.212 | J49: =I49+J48 -> 65445.053 | K49: =J49+K48 -> 79859.313 | L49: =K49+L48 -> 100181.54 | ... AU49: =AT49+AU48 -> 1127367.5

Sheet Dashboard
A1: Dashboard — 608 Smith Avenue
A2: Selected scenario: Base default. Change Inputs!B4 to recalculate all dashboard and annual-summary formulas.
A3: Decision focus: revenue sufficiency, Smith occupancy, labor load, founder cash compensation, and cumulative operating cash.
A4: Pre-lease Total Revenue | D4: Lease Year 1 Total Revenue
A5: ='Annual Summary'!B8 -> 198107.91 | D5: ='Annual Summary'!C8 -> 739150.42
A6: May 2030 Monthly Revenue | D6: May 2030 Operating Margin
A7: =CHOOSE(MATCH('Inputs'!$B$4,{"Downside","Base","Upside"},0),'Model - Downside'!$AU$15,'Model - Base'!$AU$15,'Model - Upside'!$AU$15) -> 66042.105 | D7: =CHOOSE(MATCH('Inputs'!$B$4,{"Downside","Base","Upside"},0),'Model - Downside'!$AU$43,'Model - Base'!$AU$43,'Model - Upside'!$AU$43) -> 0.29665736
A8: May 2030 Cumulative Cash | D8: May 2030 Founder Deferred Balance
A9: =CHOOSE(MATCH('Inputs'!$B$4,{"Downside","Base","Upside"},0),'Model - Downside'!$AU$49,'Model - Base'!$AU$49,'Model - Upside'!$AU$49) -> 674335.34 | D9: =CHOOSE(MATCH('Inputs'!$B$4,{"Downside","Base","Upside"},0),'Model - Downside'!$AU$47,'Model - Base'!$AU$47,'Model - Upside'!$AU$47) -> 0
A10: Lease Year 1 Avg Total Labor % | D10: Lease Year 1 Avg Smith Occupancy %
A11: ='Annual Summary'!C21 -> 0.28465332 | D11: ='Annual Summary'!C22 -> 0.097371187
A18: Month | B18: Total Revenue | C18: Operating Profit | D18: Total Labor % | E18: Smith Occupancy %
A19: 46296 | B19: =CHOOSE(MATCH('Inputs'!$B$4,{"Downside","Base","Upside"},0),'Model - Downside'!$D$15,'Model - Base'!$D$15,'Model - Upside'!$D$15) -> 16484.42 | C19: =CHOOSE(MATCH('Inputs'!$B$4,{"Downside","Base","Upside"},0),'Model - Downside'!$D$42,'Model - Base'!$D$42,'Model - Upside'!$D$42) -> -523.26684 | D19: =CHOOSE(MATCH('Inputs'!$B$4,{"Downside","Base","Upside"},0),'Model - Downside'!$D$26,'Model - Base'!$D$26,'Model - Upside'!$D$26) -> 0.58697506 | E19: =CHOOSE(MATCH('Inputs'!$B$4,{"Downside","Base","Upside"},0),'Model - Downside'!$D$35,'Model - Base'!$D$35,'Model - Upside'!$D$35) -> 0.29342627
A20: 46327 | B20: =CHOOSE(MATCH('Inputs'!$B$4,{"Downside","Base","Upside"},0),'Model - Downside'!$E$15,'Model - Base'!$E$15,'Model - Upside'!$E$15) -> 16554.764 | C20: =CHOOSE(MATCH('Inputs'!$B$4,{"Downside","Base","Upside"},0),'Model - Downside'!$E$42,'Model - Base'!$E$42,'Model - Upside'!$E$42) -> -481.20101 | D20: =CHOOSE(MATCH('Inputs'!$B$4,{"Downside","Base","Upside"},0),'Model - Downside'!$E$26,'Model - Base'!$E$26,'Model - Upside'!$E$26) -> 0.58504179 | E20: =CHOOSE(MATCH('Inputs'!$B$4,{"Downside","Base","Upside"},0),'Model - Downside'!$E$35,'Model - Base'!$E$35,'Model - Upside'!$E$35) -> 0.29009966
A21: 46357 | B21: =CHOOSE(MATCH('Inputs'!$B$4,{"Downside","Base","Upside"},0),'Model - Downside'!$F$15,'Model - Base'!$F$15,'Model - Upside'!$F$15) -> 16625.947 | C21: =CHOOSE(MATCH('Inputs'!$B$4,{"Downside","Base","Upside"},0),'Model - Downside'!$F$42,'Model - Base'!$F$42,'Model - Upside'!$F$42) -> -438.63379 | D21: =CHOOSE(MATCH('Inputs'!$B$4,{"Downside","Base","Upside"},0),'Model - Downside'!$F$26,'Model - Base'!$F$26,'Model - Upside'!$F$26) -> 0.58310213 | E21: =CHOOSE(MATCH('Inputs'!$B$4,{"Downside","Base","Upside"},0),'Model - Downside'!$F$35,'Model - Base'!$F$35,'Model - Upside'!$F$35) -> 0.28680931
A22: 46388 | B22: =CHOOSE(MATCH('Inputs'!$B$4,{"Downside","Base","Upside"},0),'Model - Downside'!$G$15,'Model - Base'!$G$15,'Model - Upside'!$G$15) -> 20147.978 | C22: =CHOOSE(MATCH('Inputs'!$B$4,{"Downside","Base","Upside"},0),'Model - Downside'!$G$42,'Model - Base'!$G$42,'Model - Upside'!$G$42) -> -3880.459 | D22: =CHOOSE(MATCH('Inputs'!$B$4,{"Downside","Base","Upside"},0),'Model - Downside'!$G$26,'Model - Base'!$G$26,'Model - Upside'!$G$26) -> 0.50424578 | E22: =CHOOSE(MATCH('Inputs'!$B$4,{"Downside","Base","Upside"},0),'Model - Downside'!$G$35,'Model - Base'!$G$35,'Model - Upside'!$G$35) -> 0.40957922
A23: 46419 | B23: =CHOOSE(MATCH('Inputs'!$B$4,{"Downside","Base","Upside"},0),'Model - Downside'!$H$15,'Model - Base'!$H$15,'Model - Upside'!$H$15) -> 20220.869 | C23: =CHOOSE(MATCH('Inputs'!$B$4,{"Downside","Base","Upside"},0),'Model - Downside'!$H$42,'Model - Base'!$H$42,'Model - Upside'!$H$42) -> -3836.8702 | D23: =CHOOSE(MATCH('Inputs'!$B$4,{"Downside","Base","Upside"},0),'Model - Downside'!$H$26,'Model - Base'!$H$26,'Model - Upside'!$H$26) -> 0.50290394 | E23: =CHOOSE(MATCH('Inputs'!$B$4,{"Downside","Base","Upside"},0),'Model - Downside'!$H$35,'Model - Base'!$H$35,'Model - Upside'!$H$35) -> 0.4049296
A24: 46447 | B24: =CHOOSE(MATCH('Inputs'!$B$4,{"Downside","Base","Upside"},0),'Model - Downside'!$I$15,'Model - Base'!$I$15,'Model - Upside'!$I$15) -> 31284.668 | C24: =CHOOSE(MATCH('Inputs'!$B$4,{"Downside","Base","Upside"},0),'Model - Downside'!$I$42,'Model - Base'!$I$42,'Model - Upside'!$I$42) -> 58.624462 | D24: =CHOOSE(MATCH('Inputs'!$B$4,{"Downside","Base","Upside"},0),'Model - Downside'!$I$26,'Model - Base'!$I$26,'Model - Upside'!$I$26) -> 0.42673405 | E24: =CHOOSE(MATCH('Inputs'!$B$4,{"Downside","Base","Upside"},0),'Model - Downside'!$I$35,'Model - Base'!$I$35,'Model - Upside'!$I$35) -> 0.20589468
A25: 46478 | B25: =CHOOSE(MATCH('Inputs'!$B$4,{"Downside","Base","Upside"},0),'Model - Downside'!$J$15,'Model - Base'!$J$15,'Model - Upside'!$J$15) -> 36032.004 | C25: =CHOOSE(MATCH('Inputs'!$B$4,{"Downside","Base","Upside"},0),'Model - Downside'!$J$42,'Model - Base'!$J$42,'Model - Upside'!$J$42) -> 2636.4284 | D25: =CHOOSE(MATCH('Inputs'!$B$4,{"Downside","Base","Upside"},0),'Model - Downside'!$J$26,'Model - Base'!$J$26,'Model - Upside'!$J$26) -> 0.39514829 | E25: =CHOOSE(MATCH('Inputs'!$B$4,{"Downside","Base","Upside"},0),'Model - Downside'!$J$35,'Model - Base'!$J$35,'Model - Upside'!$J$35) -> 0.16192872
A26: 46508 | B26: =CHOOSE(MATCH('Inputs'!$B$4,{"Downside","Base","Upside"},0),'Model - Downside'!$K$15,'Model - Base'!$K$15,'Model - Upside'!$K$15) -> 40757.261 | C26: =CHOOSE(MATCH('Inputs'!$B$4,{"Downside","Base","Upside"},0),'Model - Downside'!$K$42,'Model - Base'!$K$42,'Model - Upside'!$K$42) -> 5202.2427 | D26: =CHOOSE(MATCH('Inputs'!$B$4,{"Downside","Base","Upside"},0),'Model - Downside'!$K$26,'Model - Base'!$K$26,'Model - Upside'!$K$26) -> 0.37101629 | E26: =CHOOSE(MATCH('Inputs'!$B$4,{"Downside","Base","Upside"},0),'Model - Downside'!$K$35,'Model - Base'!$K$35,'Model - Upside'!$K$35) -> 0.13354472
A27: 46539 | B27: =CHOOSE(MATCH('Inputs'!$B$4,{"Downside","Base","Upside"},0),'Model - Downside'!$L$15,'Model - Base'!$L$15,'Model - Upside'!$L$15) -> 52196.88 | C27: =CHOOSE(MATCH('Inputs'!$B$4,{"Downside","Base","Upside"},0),'Model - Downside'!$L$42,'Model - Base'!$L$42,'Model - Upside'!$L$42) -> 10613.956 | D27: =CHOOSE(MATCH('Inputs'!$B$4,{"Downside","Base","Upside"},0),'Model - Downside'!$L$26,'Model - Base'!$L$26,'Model - Upside'!$L$26) -> 0.33068675 | E27: =CHOOSE(MATCH('Inputs'!$B$4,{"Downside","Base","Upside"},0),'Model - Downside'!$L$35,'Model - Base'!$L$35,'Model - Upside'!$L$35) -> 0.11459264
A28: 46569 | B28: =CHOOSE(MATCH('Inputs'!$B$4,{"Downside","Base","Upside"},0),'Model - Downside'!$M$15,'Model - Base'!$M$15,'Model - Upside'!$M$15) -> 56164.07 | C28: =CHOOSE(MATCH('Inputs'!$B$4,{"Downside","Base","Upside"},0),'Model - Downside'!$M$42,'Model - Base'!$M$42,'Model - Upside'!$M$42) -> 12768.14 | D28: =CHOOSE(MATCH('Inputs'!$B$4,{"Downside","Base","Upside"},0),'Model - Downside'!$M$26,'Model - Base'!$M$26,'Model - Upside'!$M$26) -> 0.32053733 | E28: =CHOOSE(MATCH('Inputs'!$B$4,{"Downside","Base","Upside"},0),'Model - Downside'!$M$35,'Model - Base'!$M$35,'Model - Upside'!$M$35) -> 0.1038616
A29: 46600 | B29: =CHOOSE(MATCH('Inputs'!$B$4,{"Downside","Base","Upside"},0),'Model - Downside'!$N$15,'Model - Base'!$N$15,'Model - Upside'!$N$15) -> 60115.789 | C29: =CHOOSE(MATCH('Inputs'!$B$4,{"Downside","Base","Upside"},0),'Model - Downside'!$N$42,'Model - Base'!$N$42,'Model - Upside'!$N$42) -> 14913.924 | D29: =CHOOSE(MATCH('Inputs'!$B$4,{"Downside","Base","Upside"},0),'Model - Downside'!$N$26,'Model - Base'!$N$26,'Model - Upside'!$N$26) -> 0.31175924 | E29: =CHOOSE(MATCH('Inputs'!$B$4,{"Downside","Base","Upside"},0),'Model - Downside'!$N$35,'Model - Base'!$N$35,'Model - Upside'!$N$35) -> 0.095
A30: 46631 | B30: =CHOOSE(MATCH('Inputs'!$B$4,{"Downside","Base","Upside"},0),'Model - Downside'!$O$15,'Model - Base'!$O$15,'Model - Upside'!$O$15) -> 60115.789 | C30: =CHOOSE(MATCH('Inputs'!$B$4,{"Downside","Base","Upside"},0),'Model - Downside'!$O$42,'Model - Base'!$O$42,'Model - Upside'!$O$42) -> 16897.745 | D30: =CHOOSE(MATCH('Inputs'!$B$4,{"Downside","Base","Upside"},0),'Model - Downside'!$O$26,'Model - Base'!$O$26,'Model - Upside'!$O$26) -> 0.27875924 | E30: =CHOOSE(MATCH('Inputs'!$B$4,{"Downside","Base","Upside"},0),'Model - Downside'!$O$35,'Model - Base'!$O$35,'Model - Upside'!$O$35) -> 0.095
A31: 46661 | B31: =CHOOSE(MATCH('Inputs'!$B$4,{"Downside","Base","Upside"},0),'Model - Downside'!$P$15,'Model - Base'!$P$15,'Model - Upside'!$P$15) -> 60115.789 | C31: =CHOOSE(MATCH('Inputs'!$B$4,{"Downside","Base","Upside"},0),'Model - Downside'!$P$42,'Model - Base'!$P$42,'Model - Upside'!$P$42) -> 16847.136 | D31: =CHOOSE(MATCH('Inputs'!$B$4,{"Downside","Base","Upside"},0),'Model - Downside'!$P$26,'Model - Base'!$P$26,'Model - Upside'!$P$26) -> 0.27875924 | E31: =CHOOSE(MATCH('Inputs'!$B$4,{"Downside","Base","Upside"},0),'Model - Downside'!$P$35,'Model - Base'!$P$35,'Model - Upside'!$P$35) -> 0.095
A32: 46692 | B32: =CHOOSE(MATCH('Inputs'!$B$4,{"Downside","Base","Upside"},0),'Model - Downside'!$Q$15,'Model - Base'!$Q$15,'Model - Upside'!$Q$15) -> 60115.789 | C32: =CHOOSE(MATCH('Inputs'!$B$4,{"Downside","Base","Upside"},0),'Model - Downside'!$Q$42,'Model - Base'!$Q$42,'Model - Upside'!$Q$42) -> 16847.136 | D32: =CHOOSE(MATCH('Inputs'!$B$4,{"Downside","Base","Upside"},0),'Model - Downside'!$Q$26,'Model - Base'!$Q$26,'Model - Upside'!$Q$26) -> 0.27875924 | E32: =CHOOSE(MATCH('Inputs'!$B$4,{"Downside","Base","Upside"},0),'Model - Downside'!$Q$35,'Model - Base'!$Q$35,'Model - Upside'!$Q$35) -> 0.095
A33: 46722 | B33: =CHOOSE(MATCH('Inputs'!$B$4,{"Downside","Base","Upside"},0),'Model - Downside'!$R$15,'Model - Base'!$R$15,'Model - Upside'!$R$15) -> 60115.789 | C33: =CHOOSE(MATCH('Inputs'!$B$4,{"Downside","Base","Upside"},0),'Model - Downside'!$R$42,'Model - Base'!$R$42,'Model - Upside'!$R$42) -> 16847.136 | D33: =CHOOSE(MATCH('Inputs'!$B$4,{"Downside","Base","Upside"},0),'Model - Downside'!$R$26,'Model - Base'!$R$26,'Model - Upside'!$R$26) -> 0.27875924 | E33: =CHOOSE(MATCH('Inputs'!$B$4,{"Downside","Base","Upside"},0),'Model - Downside'!$R$35,'Model - Base'!$R$35,'Model - Upside'!$R$35) -> 0.095
A34: 46753 | B34: =CHOOSE(MATCH('Inputs'!$B$4,{"Downside","Base","Upside"},0),'Model - Downside'!$S$15,'Model - Base'!$S$15,'Model - Upside'!$S$15) -> 66042.105 | C34: =CHOOSE(MATCH('Inputs'!$B$4,{"Downside","Base","Upside"},0),'Model - Downside'!$S$42,'Model - Base'!$S$42,'Model - Upside'!$S$42) -> 19697.694 | D34: =CHOOSE(MATCH('Inputs'!$B$4,{"Downside","Base","Upside"},0),'Model - Downside'!$S$26,'Model - Base'!$S$26,'Model - Upside'!$S$26) -> 0.26756391 | E34: =CHOOSE(MATCH('Inputs'!$B$4,{"Downside","Base","Upside"},0),'Model - Downside'!$S$35,'Model - Base'!$S$35,'Model - Upside'!$S$35) -> 0.095
A35: 46784 | B35: =CHOOSE(MATCH('Inputs'!$B$4,{"Downside","Base","Upside"},0),'Model - Downside'!$T$15,'Model - Base'!$T$15,'Model - Upside'!$T$15) -> 66042.105 | C35: =CHOOSE(MATCH('Inputs'!$B$4,{"Downside","Base","Upside"},0),'Model - Downside'!$T$42,'Model - Base'!$T$42,'Model - Upside'!$T$42) -> 19697.694 | D35: =CHOOSE(MATCH('Inputs'!$B$4,{"Downside","Base","Upside"},0),'Model - Downside'!$T$26,'Model - Base'!$T$26,'Model - Upside'!$T$26) -> 0.26756391 | E35: =CHOOSE(MATCH('Inputs'!$B$4,{"Downside","Base","Upside"},0),'Model - Downside'!$T$35,'Model - Base'!$T$35,'Model - Upside'!$T$35) -> 0.095
A36: 46813 | B36: =CHOOSE(MATCH('Inputs'!$B$4,{"Downside","Base","Upside"},0),'Model - Downside'!$U$15,'Model - Base'!$U$15,'Model - Upside'!$U$15) -> 66042.105 | C36: =CHOOSE(MATCH('Inputs'!$B$4,{"Downside","Base","Upside"},0),'Model - Downside'!$U$42,'Model - Base'!$U$42,'Model - Upside'!$U$42) -> 19697.694 | D36: =CHOOSE(MATCH('Inputs'!$B$4,{"Downside","Base","Upside"},0),'Model - Downside'!$U$26,'Model - Base'!$U$26,'Model - Upside'!$U$26) -> 0.26756391 | E36: =CHOOSE(MATCH('Inputs'!$B$4,{"Downside","Base","Upside"},0),'Model - Downside'!$U$35,'Model - Base'!$U$35,'Model - Upside'!$U$35) -> 0.095
A37: 46844 | B37: =CHOOSE(MATCH('Inputs'!$B$4,{"Downside","Base","Upside"},0),'Model - Downside'!$V$15,'Model - Base'!$V$15,'Model - Upside'!$V$15) -> 66042.105 | C37: =CHOOSE(MATCH('Inputs'!$B$4,{"Downside","Base","Upside"},0),'Model - Downside'!$V$42,'Model - Base'!$V$42,'Model - Upside'!$V$42) -> 19697.694 | D37: =CHOOSE(MATCH('Inputs'!$B$4,{"Downside","Base","Upside"},0),'Model - Downside'!$V$26,'Model - Base'!$V$26,'Model - Upside'!$V$26) -> 0.26756391 | E37: =CHOOSE(MATCH('Inputs'!$B$4,{"Downside","Base","Upside"},0),'Model - Downside'!$V$35,'Model - Base'!$V$35,'Model - Upside'!$V$35) -> 0.095
A38: 46874 | B38: =CHOOSE(MATCH('Inputs'!$B$4,{"Downside","Base","Upside"},0),'Model - Downside'!$W$15,'Model - Base'!$W$15,'Model - Upside'!$W$15) -> 66042.105 | C38: =CHOOSE(MATCH('Inputs'!$B$4,{"Downside","Base","Upside"},0),'Model - Downside'!$W$42,'Model - Base'!$W$42,'Model - Upside'!$W$42) -> 19697.694 | D38: =CHOOSE(MATCH('Inputs'!$B$4,{"Downside","Base","Upside"},0),'Model - Downside'!$W$26,'Model - Base'!$W$26,'Model - Upside'!$W$26) -> 0.26756391 | E38: =CHOOSE(MATCH('Inputs'!$B$4,{"Downside","Base","Upside"},0),'Model - Downside'!$W$35,'Model - Base'!$W$35,'Model - Upside'!$W$35) -> 0.095
A39: 46905 | B39: =CHOOSE(MATCH('Inputs'!$B$4,{"Downside","Base","Upside"},0),'Model - Downside'!$X$15,'Model - Base'!$X$15,'Model - Upside'!$X$15) -> 66042.105 | C39: =CHOOSE(MATCH('Inputs'!$B$4,{"Downside","Base","Upside"},0),'Model - Downside'!$X$42,'Model - Base'!$X$42,'Model - Upside'!$X$42) -> 19697.694 | D39: =CHOOSE(MATCH('Inputs'!$B$4,{"Downside","Base","Upside"},0),'Model - Downside'!$X$26,'Model - Base'!$X$26,'Model - Upside'!$X$26) -> 0.26756391 | E39: =CHOOSE(MATCH('Inputs'!$B$4,{"Downside","Base","Upside"},0),'Model - Downside'!$X$35,'Model - Base'!$X$35,'Model - Upside'!$X$35) -> 0.095
A40: 46935 | B40: =CHOOSE(MATCH('Inputs'!$B$4,{"Downside","Base","Upside"},0),'Model - Downside'!$Y$15,'Model - Base'!$Y$15,'Model - Upside'!$Y$15) -> 66042.105 | C40: =CHOOSE(MATCH('Inputs'!$B$4,{"Downside","Base","Upside"},0),'Model - Downside'!$Y$42,'Model - Base'!$Y$42,'Model - Upside'!$Y$42) -> 19697.694 | D40: =CHOOSE(MATCH('Inputs'!$B$4,{"Downside","Base","Upside"},0),'Model - Downside'!$Y$26,'Model - Base'!$Y$26,'Model - Upside'!$Y$26) -> 0.26756391 | E40: =CHOOSE(MATCH('Inputs'!$B$4,{"Downside","Base","Upside"},0),'Model - Downside'!$Y$35,'Model - Base'!$Y$35,'Model - Upside'!$Y$35) -> 0.095
A41: 46966 | B41: =CHOOSE(MATCH('Inputs'!$B$4,{"Downside","Base","Upside"},0),'Model - Downside'!$Z$15,'Model - Base'!$Z$15,'Model - Upside'!$Z$15) -> 66042.105 | C41: =CHOOSE(MATCH('Inputs'!$B$4,{"Downside","Base","Upside"},0),'Model - Downside'!$Z$42,'Model - Base'!$Z$42,'Model - Upside'!$Z$42) -> 19697.694 | D41: =CHOOSE(MATCH('Inputs'!$B$4,{"Downside","Base","Upside"},0),'Model - Downside'!$Z$26,'Model - Base'!$Z$26,'Model - Upside'!$Z$26) -> 0.26756391 | E41: =CHOOSE(MATCH('Inputs'!$B$4,{"Downside","Base","Upside"},0),'Model - Downside'!$Z$35,'Model - Base'!$Z$35,'Model - Upside'!$Z$35) -> 0.095
A42: 46997 | B42: =CHOOSE(MATCH('Inputs'!$B$4,{"Downside","Base","Upside"},0),'Model - Downside'!$AA$15,'Model - Base'!$AA$15,'Model - Upside'!$AA$15) -> 66042.105 | C42: =CHOOSE(MATCH('Inputs'!$B$4,{"Downside","Base","Upside"},0),'Model - Downside'!$AA$42,'Model - Base'!$AA$42,'Model - Upside'!$AA$42) -> 19697.694 | D42: =CHOOSE(MATCH('Inputs'!$B$4,{"Downside","Base","Upside"},0),'Model - Downside'!$AA$26,'Model - Base'!$AA$26,'Model - Upside'!$AA$26) -> 0.26756391 | E42: =CHOOSE(MATCH('Inputs'!$B$4,{"Downside","Base","Upside"},0),'Model - Downside'!$AA$35,'Model - Base'!$AA$35,'Model - Upside'!$AA$35) -> 0.095
A43: 47027 | B43: =CHOOSE(MATCH('Inputs'!$B$4,{"Downside","Base","Upside"},0),'Model - Downside'!$AB$15,'Model - Base'!$AB$15,'Model - Upside'!$AB$15) -> 66042.105 | C43: =CHOOSE(MATCH('Inputs'!$B$4,{"Downside","Base","Upside"},0),'Model - Downside'!$AB$42,'Model - Base'!$AB$42,'Model - Upside'!$AB$42) -> 19645.567 | D43: =CHOOSE(MATCH('Inputs'!$B$4,{"Downside","Base","Upside"},0),'Model - Downside'!$AB$26,'Model - Base'!$AB$26,'Model - Upside'!$AB$26) -> 0.26756391 | E43: =CHOOSE(MATCH('Inputs'!$B$4,{"Downside","Base","Upside"},0),'Model - Downside'!$AB$35,'Model - Base'!$AB$35,'Model - Upside'!$AB$35) -> 0.095
A44: 47058 | B44: =CHOOSE(MATCH('Inputs'!$B$4,{"Downside","Base","Upside"},0),'Model - Downside'!$AC$15,'Model - Base'!$AC$15,'Model - Upside'!$AC$15) -> 66042.105 | C44: =CHOOSE(MATCH('Inputs'!$B$4,{"Downside","Base","Upside"},0),'Model - Downside'!$AC$42,'Model - Base'!$AC$42,'Model - Upside'!$AC$42) -> 19645.567 | D44: =CHOOSE(MATCH('Inputs'!$B$4,{"Downside","Base","Upside"},0),'Model - Downside'!$AC$26,'Model - Base'!$AC$26,'Model - Upside'!$AC$26) -> 0.26756391 | E44: =CHOOSE(MATCH('Inputs'!$B$4,{"Downside","Base","Upside"},0),'Model - Downside'!$AC$35,'Model - Base'!$AC$35,'Model - Upside'!$AC$35) -> 0.095
A45: 47088 | B45: =CHOOSE(MATCH('Inputs'!$B$4,{"Downside","Base","Upside"},0),'Model - Downside'!$AD$15,'Model - Base'!$AD$15,'Model - Upside'!$AD$15) -> 66042.105 | C45: =CHOOSE(MATCH('Inputs'!$B$4,{"Downside","Base","Upside"},0),'Model - Downside'!$AD$42,'Model - Base'!$AD$42,'Model - Upside'!$AD$42) -> 19645.567 | D45: =CHOOSE(MATCH('Inputs'!$B$4,{"Downside","Base","Upside"},0),'Model - Downside'!$AD$26,'Model - Base'!$AD$26,'Model - Upside'!$AD$26) -> 0.26756391 | E45: =CHOOSE(MATCH('Inputs'!$B$4,{"Downside","Base","Upside"},0),'Model - Downside'!$AD$35,'Model - Base'!$AD$35,'Model - Upside'!$AD$35) -> 0.095
A46: 47119 | B46: =CHOOSE(MATCH('Inputs'!$B$4,{"Downside","Base","Upside"},0),'Model - Downside'!$AE$15,'Model - Base'!$AE$15,'Model - Upside'!$AE$15) -> 66042.105 | C46: =CHOOSE(MATCH('Inputs'!$B$4,{"Downside","Base","Upside"},0),'Model - Downside'!$AE$42,'Model - Base'!$AE$42,'Model - Upside'!$AE$42) -> 19645.567 | D46: =CHOOSE(MATCH('Inputs'!$B$4,{"Downside","Base","Upside"},0),'Model - Downside'!$AE$26,'Model - Base'!$AE$26,'Model - Upside'!$AE$26) -> 0.26756391 | E46: =CHOOSE(MATCH('Inputs'!$B$4,{"Downside","Base","Upside"},0),'Model - Downside'!$AE$35,'Model - Base'!$AE$35,'Model - Upside'!$AE$35) -> 0.095
A47: 47150 | B47: =CHOOSE(MATCH('Inputs'!$B$4,{"Downside","Base","Upside"},0),'Model - Downside'!$AF$15,'Model - Base'!$AF$15,'Model - Upside'!$AF$15) -> 66042.105 | C47: =CHOOSE(MATCH('Inputs'!$B$4,{"Downside","Base","Upside"},0),'Model - Downside'!$AF$42,'Model - Base'!$AF$42,'Model - Upside'!$AF$42) -> 19645.567 | D47: =CHOOSE(MATCH('Inputs'!$B$4,{"Downside","Base","Upside"},0),'Model - Downside'!$AF$26,'Model - Base'!$AF$26,'Model - Upside'!$AF$26) -> 0.26756391 | E47: =CHOOSE(MATCH('Inputs'!$B$4,{"Downside","Base","Upside"},0),'Model - Downside'!$AF$35,'Model - Base'!$AF$35,'Model - Upside'!$AF$35) -> 0.095
A48: 47178 | B48: =CHOOSE(MATCH('Inputs'!$B$4,{"Downside","Base","Upside"},0),'Model - Downside'!$AG$15,'Model - Base'!$AG$15,'Model - Upside'!$AG$15) -> 66042.105 | C48: =CHOOSE(MATCH('Inputs'!$B$4,{"Downside","Base","Upside"},0),'Model - Downside'!$AG$42,'Model - Base'!$AG$42,'Model - Upside'!$AG$42) -> 19645.567 | D48: =CHOOSE(MATCH('Inputs'!$B$4,{"Downside","Base","Upside"},0),'Model - Downside'!$AG$26,'Model - Base'!$AG$26,'Model - Upside'!$AG$26) -> 0.26756391 | E48: =CHOOSE(MATCH('Inputs'!$B$4,{"Downside","Base","Upside"},0),'Model - Downside'!$AG$35,'Model - Base'!$AG$35,'Model - Upside'!$AG$35) -> 0.095
A49: 47209 | B49: =CHOOSE(MATCH('Inputs'!$B$4,{"Downside","Base","Upside"},0),'Model - Downside'!$AH$15,'Model - Base'!$AH$15,'Model - Upside'!$AH$15) -> 66042.105 | C49: =CHOOSE(MATCH('Inputs'!$B$4,{"Downside","Base","Upside"},0),'Model - Downside'!$AH$42,'Model - Base'!$AH$42,'Model - Upside'!$AH$42) -> 19645.567 | D49: =CHOOSE(MATCH('Inputs'!$B$4,{"Downside","Base","Upside"},0),'Model - Downside'!$AH$26,'Model - Base'!$AH$26,'Model - Upside'!$AH$26) -> 0.26756391 | E49: =CHOOSE(MATCH('Inputs'!$B$4,{"Downside","Base","Upside"},0),'Model - Downside'!$AH$35,'Model - Base'!$AH$35,'Model - Upside'!$AH$35) -> 0.095
A50: 47239 | B50: =CHOOSE(MATCH('Inputs'!$B$4,{"Downside","Base","Upside"},0),'Model - Downside'!$AI$15,'Model - Base'!$AI$15,'Model - Upside'!$AI$15) -> 66042.105 | C50: =CHOOSE(MATCH('Inputs'!$B$4,{"Downside","Base","Upside"},0),'Model - Downside'!$AI$42,'Model - Base'!$AI$42,'Model - Upside'!$AI$42) -> 19645.567 | D50: =CHOOSE(MATCH('Inputs'!$B$4,{"Downside","Base","Upside"},0),'Model - Downside'!$AI$26,'Model - Base'!$AI$26,'Model - Upside'!$AI$26) -> 0.26756391 | E50: =CHOOSE(MATCH('Inputs'!$B$4,{"Downside","Base","Upside"},0),'Model - Downside'!$AI$35,'Model - Base'!$AI$35,'Model - Upside'!$AI$35) -> 0.095
A51: 47270 | B51: =CHOOSE(MATCH('Inputs'!$B$4,{"Downside","Base","Upside"},0),'Model - Downside'!$AJ$15,'Model - Base'!$AJ$15,'Model - Upside'!$AJ$15) -> 66042.105 | C51: =CHOOSE(MATCH('Inputs'!$B$4,{"Downside","Base","Upside"},0),'Model - Downside'!$AJ$42,'Model - Base'!$AJ$42,'Model - Upside'!$AJ$42) -> 19645.567 | D51: =CHOOSE(MATCH('Inputs'!$B$4,{"Downside","Base","Upside"},0),'Model - Downside'!$AJ$26,'Model - Base'!$AJ$26,'Model - Upside'!$AJ$26) -> 0.26756391 | E51: =CHOOSE(MATCH('Inputs'!$B$4,{"Downside","Base","Upside"},0),'Model - Downside'!$AJ$35,'Model - Base'!$AJ$35,'Model - Upside'!$AJ$35) -> 0.095
A52: 47300 | B52: =CHOOSE(MATCH('Inputs'!$B$4,{"Downside","Base","Upside"},0),'Model - Downside'!$AK$15,'Model - Base'!$AK$15,'Model - Upside'!$AK$15) -> 66042.105 | C52: =CHOOSE(MATCH('Inputs'!$B$4,{"Downside","Base","Upside"},0),'Model - Downside'!$AK$42,'Model - Base'!$AK$42,'Model - Upside'!$AK$42) -> 19645.567 | D52: =CHOOSE(MATCH('Inputs'!$B$4,{"Downside","Base","Upside"},0),'Model - Downside'!$AK$26,'Model - Base'!$AK$26,'Model - Upside'!$AK$26) -> 0.26756391 | E52: =CHOOSE(MATCH('Inputs'!$B$4,{"Downside","Base","Upside"},0),'Model - Downside'!$AK$35,'Model - Base'!$AK$35,'Model - Upside'!$AK$35) -> 0.095
A53: 47331 | B53: =CHOOSE(MATCH('Inputs'!$B$4,{"Downside","Base","Upside"},0),'Model - Downside'!$AL$15,'Model - Base'!$AL$15,'Model - Upside'!$AL$15) -> 66042.105 | C53: =CHOOSE(MATCH('Inputs'!$B$4,{"Downside","Base","Upside"},0),'Model - Downside'!$AL$42,'Model - Base'!$AL$42,'Model - Upside'!$AL$42) -> 19645.567 | D53: =CHOOSE(MATCH('Inputs'!$B$4,{"Downside","Base","Upside"},0),'Model - Downside'!$AL$26,'Model - Base'!$AL$26,'Model - Upside'!$AL$26) -> 0.26756391 | E53: =CHOOSE(MATCH('Inputs'!$B$4,{"Downside","Base","Upside"},0),'Model - Downside'!$AL$35,'Model - Base'!$AL$35,'Model - Upside'!$AL$35) -> 0.095
A54: 47362 | B54: =CHOOSE(MATCH('Inputs'!$B$4,{"Downside","Base","Upside"},0),'Model - Downside'!$AM$15,'Model - Base'!$AM$15,'Model - Upside'!$AM$15) -> 66042.105 | C54: =CHOOSE(MATCH('Inputs'!$B$4,{"Downside","Base","Upside"},0),'Model - Downside'!$AM$42,'Model - Base'!$AM$42,'Model - Upside'!$AM$42) -> 19645.567 | D54: =CHOOSE(MATCH('Inputs'!$B$4,{"Downside","Base","Upside"},0),'Model - Downside'!$AM$26,'Model - Base'!$AM$26,'Model - Upside'!$AM$26) -> 0.26756391 | E54: =CHOOSE(MATCH('Inputs'!$B$4,{"Downside","Base","Upside"},0),'Model - Downside'!$AM$35,'Model - Base'!$AM$35,'Model - Upside'!$AM$35) -> 0.095
A55: 47392 | B55: =CHOOSE(MATCH('Inputs'!$B$4,{"Downside","Base","Upside"},0),'Model - Downside'!$AN$15,'Model - Base'!$AN$15,'Model - Upside'!$AN$15) -> 66042.105 | C55: =CHOOSE(MATCH('Inputs'!$B$4,{"Downside","Base","Upside"},0),'Model - Downside'!$AN$42,'Model - Base'!$AN$42,'Model - Upside'!$AN$42) -> 19591.877 | D55: =CHOOSE(MATCH('Inputs'!$B$4,{"Downside","Base","Upside"},0),'Model - Downside'!$AN$26,'Model - Base'!$AN$26,'Model - Upside'!$AN$26) -> 0.26756391 | E55: =CHOOSE(MATCH('Inputs'!$B$4,{"Downside","Base","Upside"},0),'Model - Downside'!$AN$35,'Model - Base'!$AN$35,'Model - Upside'!$AN$35) -> 0.095
A56: 47423 | B56: =CHOOSE(MATCH('Inputs'!$B$4,{"Downside","Base","Upside"},0),'Model - Downside'!$AO$15,'Model - Base'!$AO$15,'Model - Upside'!$AO$15) -> 66042.105 | C56: =CHOOSE(MATCH('Inputs'!$B$4,{"Downside","Base","Upside"},0),'Model - Downside'!$AO$42,'Model - Base'!$AO$42,'Model - Upside'!$AO$42) -> 19591.877 | D56: =CHOOSE(MATCH('Inputs'!$B$4,{"Downside","Base","Upside"},0),'Model - Downside'!$AO$26,'Model - Base'!$AO$26,'Model - Upside'!$AO$26) -> 0.26756391 | E56: =CHOOSE(MATCH('Inputs'!$B$4,{"Downside","Base","Upside"},0),'Model - Downside'!$AO$35,'Model - Base'!$AO$35,'Model - Upside'!$AO$35) -> 0.095
A57: 47453 | B57: =CHOOSE(MATCH('Inputs'!$B$4,{"Downside","Base","Upside"},0),'Model - Downside'!$AP$15,'Model - Base'!$AP$15,'Model - Upside'!$AP$15) -> 66042.105 | C57: =CHOOSE(MATCH('Inputs'!$B$4,{"Downside","Base","Upside"},0),'Model - Downside'!$AP$42,'Model - Base'!$AP$42,'Model - Upside'!$AP$42) -> 19591.877 | D57: =CHOOSE(MATCH('Inputs'!$B$4,{"Downside","Base","Upside"},0),'Model - Downside'!$AP$26,'Model - Base'!$AP$26,'Model - Upside'!$AP$26) -> 0.26756391 | E57: =CHOOSE(MATCH('Inputs'!$B$4,{"Downside","Base","Upside"},0),'Model - Downside'!$AP$35,'Model - Base'!$AP$35,'Model - Upside'!$AP$35) -> 0.095
A58: 47484 | B58: =CHOOSE(MATCH('Inputs'!$B$4,{"Downside","Base","Upside"},0),'Model - Downside'!$AQ$15,'Model - Base'!$AQ$15,'Model - Upside'!$AQ$15) -> 66042.105 | C58: =CHOOSE(MATCH('Inputs'!$B$4,{"Downside","Base","Upside"},0),'Model - Downside'!$AQ$42,'Model - Base'!$AQ$42,'Model - Upside'!$AQ$42) -> 19591.877 | D58: =CHOOSE(MATCH('Inputs'!$B$4,{"Downside","Base","Upside"},0),'Model - Downside'!$AQ$26,'Model - Base'!$AQ$26,'Model - Upside'!$AQ$26) -> 0.26756391 | E58: =CHOOSE(MATCH('Inputs'!$B$4,{"Downside","Base","Upside"},0),'Model - Downside'!$AQ$35,'Model - Base'!$AQ$35,'Model - Upside'!$AQ$35) -> 0.095
A59: 47515 | B59: =CHOOSE(MATCH('Inputs'!$B$4,{"Downside","Base","Upside"},0),'Model - Downside'!$AR$15,'Model - Base'!$AR$15,'Model - Upside'!$AR$15) -> 66042.105 | C59: =CHOOSE(MATCH('Inputs'!$B$4,{"Downside","Base","Upside"},0),'Model - Downside'!$AR$42,'Model - Base'!$AR$42,'Model - Upside'!$AR$42) -> 19591.877 | D59: =CHOOSE(MATCH('Inputs'!$B$4,{"Downside","Base","Upside"},0),'Model - Downside'!$AR$26,'Model - Base'!$AR$26,'Model - Upside'!$AR$26) -> 0.26756391 | E59: =CHOOSE(MATCH('Inputs'!$B$4,{"Downside","Base","Upside"},0),'Model - Downside'!$AR$35,'Model - Base'!$AR$35,'Model - Upside'!$AR$35) -> 0.095
A60: 47543 | B60: =CHOOSE(MATCH('Inputs'!$B$4,{"Downside","Base","Upside"},0),'Model - Downside'!$AS$15,'Model - Base'!$AS$15,'Model - Upside'!$AS$15) -> 66042.105 | C60: =CHOOSE(MATCH('Inputs'!$B$4,{"Downside","Base","Upside"},0),'Model - Downside'!$AS$42,'Model - Base'!$AS$42,'Model - Upside'!$AS$42) -> 19591.877 | D60: =CHOOSE(MATCH('Inputs'!$B$4,{"Downside","Base","Upside"},0),'Model - Downside'!$AS$26,'Model - Base'!$AS$26,'Model - Upside'!$AS$26) -> 0.26756391 | E60: =CHOOSE(MATCH('Inputs'!$B$4,{"Downside","Base","Upside"},0),'Model - Downside'!$AS$35,'Model - Base'!$AS$35,'Model - Upside'!$AS$35) -> 0.095
A61: 47574 | B61: =CHOOSE(MATCH('Inputs'!$B$4,{"Downside","Base","Upside"},0),'Model - Downside'!$AT$15,'Model - Base'!$AT$15,'Model - Upside'!$AT$15) -> 66042.105 | C61: =CHOOSE(MATCH('Inputs'!$B$4,{"Downside","Base","Upside"},0),'Model - Downside'!$AT$42,'Model - Base'!$AT$42,'Model - Upside'!$AT$42) -> 19591.877 | D61: =CHOOSE(MATCH('Inputs'!$B$4,{"Downside","Base","Upside"},0),'Model - Downside'!$AT$26,'Model - Base'!$AT$26,'Model - Upside'!$AT$26) -> 0.26756391 | E61: =CHOOSE(MATCH('Inputs'!$B$4,{"Downside","Base","Upside"},0),'Model - Downside'!$AT$35,'Model - Base'!$AT$35,'Model - Upside'!$AT$35) -> 0.095
A62: 47604 | B62: =CHOOSE(MATCH('Inputs'!$B$4,{"Downside","Base","Upside"},0),'Model - Downside'!$AU$15,'Model - Base'!$AU$15,'Model - Upside'!$AU$15) -> 66042.105 | C62: =CHOOSE(MATCH('Inputs'!$B$4,{"Downside","Base","Upside"},0),'Model - Downside'!$AU$42,'Model - Base'!$AU$42,'Model - Upside'!$AU$42) -> 19591.877 | D62: =CHOOSE(MATCH('Inputs'!$B$4,{"Downside","Base","Upside"},0),'Model - Downside'!$AU$26,'Model - Base'!$AU$26,'Model - Upside'!$AU$26) -> 0.26756391 | E62: =CHOOSE(MATCH('Inputs'!$B$4,{"Downside","Base","Upside"},0),'Model - Downside'!$AU$35,'Model - Base'!$AU$35,'Model - Upside'!$AU$35) -> 0.095

Sheet Annual Summary
A1: Annual Summary — Selected Scenario
A2: Scenario formulas follow Inputs!B4 (Base default). Periods align to the Smith lease decision rather than calendar years.
A4: Selected Scenario | B4: Base default — controlled on Inputs
A5: Period | B5: Pre-lease | C5: Lease Year 1 | D5: Lease Year 2 | E5: Lease Year 3
A6: Visible boundaries | B6: Oct 2026 – May 2027 | C6: Jun 2027 – May 2028 | D6: Jun 2028 – May 2029 | E6: Jun 2029 – May 2030
A7: Metric | B7: Pre-lease | C7: Lease Year 1 | D7: Lease Year 2 | E7: Lease Year 3
A8: Total Revenue | B8: =CHOOSE(MATCH('Inputs'!$B$4,{"Downside","Base","Upside"},0),SUM('Model - Downside'!$D$15:$K$15),SUM('Model - Base'!$D$15:$K$15),SUM('Model - Upside'!$D$15:$K$15)) -> 198107.91 | C8: =CHOOSE(MATCH('Inputs'!$B$4,{"Downside","Base","Upside"},0),SUM('Model - Downside'!$L$15:$W$15),SUM('Model - Base'!$L$15:$W$15),SUM('Model - Upside'!$L$15:$W$15)) -> 739150.42 | D8: =CHOOSE(MATCH('Inputs'!$B$4,{"Downside","Base","Upside"},0),SUM('Model - Downside'!$X$15:$AI$15),SUM('Model - Base'!$X$15:$AI$15),SUM('Model - Upside'!$X$15:$AI$15)) -> 792505.26 | E8: =CHOOSE(MATCH('Inputs'!$B$4,{"Downside","Base","Upside"},0),SUM('Model - Downside'!$AJ$15:$AU$15),SUM('Model - Base'!$AJ$15:$AU$15),SUM('Model - Upside'!$AJ$15:$AU$15)) -> 792505.26
A9: Smith Revenue | B9: =CHOOSE(MATCH('Inputs'!$B$4,{"Downside","Base","Upside"},0),SUM('Model - Downside'!$D$10:$K$10),SUM('Model - Base'!$D$10:$K$10),SUM('Model - Upside'!$D$10:$K$10)) -> 98057.912 | C9: =CHOOSE(MATCH('Inputs'!$B$4,{"Downside","Base","Upside"},0),SUM('Model - Downside'!$L$10:$W$10),SUM('Model - Base'!$L$10:$W$10),SUM('Model - Upside'!$L$10:$W$10)) -> 573550.42 | D9: =CHOOSE(MATCH('Inputs'!$B$4,{"Downside","Base","Upside"},0),SUM('Model - Downside'!$X$10:$AI$10),SUM('Model - Base'!$X$10:$AI$10),SUM('Model - Upside'!$X$10:$AI$10)) -> 626905.26 | E9: =CHOOSE(MATCH('Inputs'!$B$4,{"Downside","Base","Upside"},0),SUM('Model - Downside'!$AJ$10:$AU$10),SUM('Model - Base'!$AJ$10:$AU$10),SUM('Model - Upside'!$AJ$10:$AU$10)) -> 626905.26
A10: Second Venue Revenue | B10: =CHOOSE(MATCH('Inputs'!$B$4,{"Downside","Base","Upside"},0),SUM('Model - Downside'!$D$14:$K$14),SUM('Model - Base'!$D$14:$K$14),SUM('Model - Upside'!$D$14:$K$14)) -> 100050 | C10: =CHOOSE(MATCH('Inputs'!$B$4,{"Downside","Base","Upside"},0),SUM('Model - Downside'!$L$14:$W$14),SUM('Model - Base'!$L$14:$W$14),SUM('Model - Upside'!$L$14:$W$14)) -> 165600 | D10: =CHOOSE(MATCH('Inputs'!$B$4,{"Downside","Base","Upside"},0),SUM('Model - Downside'!$X$14:$AI$14),SUM('Model - Base'!$X$14:$AI$14),SUM('Model - Upside'!$X$14:$AI$14)) -> 165600 | E10: =CHOOSE(MATCH('Inputs'!$B$4,{"Downside","Base","Upside"},0),SUM('Model - Downside'!$AJ$14:$AU$14),SUM('Model - Base'!$AJ$14:$AU$14),SUM('Model - Upside'!$AJ$14:$AU$14)) -> 165600
A11: Food Revenue | B11: =CHOOSE(MATCH('Inputs'!$B$4,{"Downside","Base","Upside"},0),SUM('Model - Downside'!$D$16:$K$16),SUM('Model - Base'!$D$16:$K$16),SUM('Model - Upside'!$D$16:$K$16)) -> 135032.91 | C11: =CHOOSE(MATCH('Inputs'!$B$4,{"Downside","Base","Upside"},0),SUM('Model - Downside'!$L$16:$W$16),SUM('Model - Base'!$L$16:$W$16),SUM('Model - Upside'!$L$16:$W$16)) -> 634750.42 | D11: =CHOOSE(MATCH('Inputs'!$B$4,{"Downside","Base","Upside"},0),SUM('Model - Downside'!$X$16:$AI$16),SUM('Model - Base'!$X$16:$AI$16),SUM('Model - Upside'!$X$16:$AI$16)) -> 688105.26 | E11: =CHOOSE(MATCH('Inputs'!$B$4,{"Downside","Base","Upside"},0),SUM('Model - Downside'!$AJ$16:$AU$16),SUM('Model - Base'!$AJ$16:$AU$16),SUM('Model - Upside'!$AJ$16:$AU$16)) -> 688105.26
A12: Food COGS | B12: =CHOOSE(MATCH('Inputs'!$B$4,{"Downside","Base","Upside"},0),SUM('Model - Downside'!$D$18:$K$18),SUM('Model - Base'!$D$18:$K$18),SUM('Model - Upside'!$D$18:$K$18)) -> 28356.911 | C12: =CHOOSE(MATCH('Inputs'!$B$4,{"Downside","Base","Upside"},0),SUM('Model - Downside'!$L$18:$W$18),SUM('Model - Base'!$L$18:$W$18),SUM('Model - Upside'!$L$18:$W$18)) -> 133297.59 | D12: =CHOOSE(MATCH('Inputs'!$B$4,{"Downside","Base","Upside"},0),SUM('Model - Downside'!$X$18:$AI$18),SUM('Model - Base'!$X$18:$AI$18),SUM('Model - Upside'!$X$18:$AI$18)) -> 144502.11 | E12: =CHOOSE(MATCH('Inputs'!$B$4,{"Downside","Base","Upside"},0),SUM('Model - Downside'!$AJ$18:$AU$18),SUM('Model - Base'!$AJ$18:$AU$18),SUM('Model - Upside'!$AJ$18:$AU$18)) -> 144502.11
A13: Total Labor | B13: =CHOOSE(MATCH('Inputs'!$B$4,{"Downside","Base","Upside"},0),SUM('Model - Downside'!$D$25:$K$25),SUM('Model - Base'!$D$25:$K$25),SUM('Model - Upside'!$D$25:$K$25)) -> 92094.311 | C13: =CHOOSE(MATCH('Inputs'!$B$4,{"Downside","Base","Upside"},0),SUM('Model - Downside'!$L$25:$W$25),SUM('Model - Base'!$L$25:$W$25),SUM('Model - Upside'!$L$25:$W$25)) -> 209388.9 | D13: =CHOOSE(MATCH('Inputs'!$B$4,{"Downside","Base","Upside"},0),SUM('Model - Downside'!$X$25:$AI$25),SUM('Model - Base'!$X$25:$AI$25),SUM('Model - Upside'!$X$25:$AI$25)) -> 212045.81 | E13: =CHOOSE(MATCH('Inputs'!$B$4,{"Downside","Base","Upside"},0),SUM('Model - Downside'!$AJ$25:$AU$25),SUM('Model - Base'!$AJ$25:$AU$25),SUM('Model - Upside'!$AJ$25:$AU$25)) -> 212045.81
A14: Total Occupancy Cost | B14: =CHOOSE(MATCH('Inputs'!$B$4,{"Downside","Base","Upside"},0),SUM('Model - Downside'!$D$33:$K$33),SUM('Model - Base'!$D$33:$K$33),SUM('Model - Upside'!$D$33:$K$33)) -> 47600 | C14: =CHOOSE(MATCH('Inputs'!$B$4,{"Downside","Base","Upside"},0),SUM('Model - Downside'!$L$33:$W$33),SUM('Model - Base'!$L$33:$W$33),SUM('Model - Upside'!$L$33:$W$33)) -> 117415 | D14: =CHOOSE(MATCH('Inputs'!$B$4,{"Downside","Base","Upside"},0),SUM('Model - Downside'!$X$33:$AI$33),SUM('Model - Base'!$X$33:$AI$33),SUM('Model - Upside'!$X$33:$AI$33)) -> 121356 | E14: =CHOOSE(MATCH('Inputs'!$B$4,{"Downside","Base","Upside"},0),SUM('Model - Downside'!$AJ$33:$AU$33),SUM('Model - Base'!$AJ$33:$AU$33),SUM('Model - Upside'!$AJ$33:$AU$33)) -> 121356
A15: Payment Processing | B15: =CHOOSE(MATCH('Inputs'!$B$4,{"Downside","Base","Upside"},0),SUM('Model - Downside'!$D$40:$K$40),SUM('Model - Base'!$D$40:$K$40),SUM('Model - Upside'!$D$40:$K$40)) -> 4377.2373 | C15: =CHOOSE(MATCH('Inputs'!$B$4,{"Downside","Base","Upside"},0),SUM('Model - Downside'!$L$40:$W$40),SUM('Model - Base'!$L$40:$W$40),SUM('Model - Upside'!$L$40:$W$40)) -> 19582.513 | D15: =CHOOSE(MATCH('Inputs'!$B$4,{"Downside","Base","Upside"},0),SUM('Model - Downside'!$X$40:$AI$40),SUM('Model - Base'!$X$40:$AI$40),SUM('Model - Upside'!$X$40:$AI$40)) -> 21183.158 | E15: =CHOOSE(MATCH('Inputs'!$B$4,{"Downside","Base","Upside"},0),SUM('Model - Downside'!$AJ$40:$AU$40),SUM('Model - Base'!$AJ$40:$AU$40),SUM('Model - Upside'!$AJ$40:$AU$40)) -> 21183.158
A16: Fixed Other OpEx | B16: =CHOOSE(MATCH('Inputs'!$B$4,{"Downside","Base","Upside"},0),SUM('Model - Downside'!$D$41:$K$41),SUM('Model - Base'!$D$41:$K$41),SUM('Model - Upside'!$D$41:$K$41)) -> 13495.6 | C16: =CHOOSE(MATCH('Inputs'!$B$4,{"Downside","Base","Upside"},0),SUM('Model - Downside'!$L$41:$W$41),SUM('Model - Base'!$L$41:$W$41),SUM('Model - Upside'!$L$41:$W$41)) -> 20648.268 | D16: =CHOOSE(MATCH('Inputs'!$B$4,{"Downside","Base","Upside"},0),SUM('Model - Downside'!$X$41:$AI$41),SUM('Model - Base'!$X$41:$AI$41),SUM('Model - Upside'!$X$41:$AI$41)) -> 21267.716 | E16: =CHOOSE(MATCH('Inputs'!$B$4,{"Downside","Base","Upside"},0),SUM('Model - Downside'!$AJ$41:$AU$41),SUM('Model - Base'!$AJ$41:$AU$41),SUM('Model - Upside'!$AJ$41:$AU$41)) -> 21905.748
A17: Operating Profit | B17: =CHOOSE(MATCH('Inputs'!$B$4,{"Downside","Base","Upside"},0),SUM('Model - Downside'!$D$42:$K$42),SUM('Model - Base'!$D$42:$K$42),SUM('Model - Upside'!$D$42:$K$42)) -> -1263.1352 | C17: =CHOOSE(MATCH('Inputs'!$B$4,{"Downside","Base","Upside"},0),SUM('Model - Downside'!$L$42:$W$42),SUM('Model - Base'!$L$42:$W$42),SUM('Model - Upside'!$L$42:$W$42)) -> 204223.64 | D17: =CHOOSE(MATCH('Inputs'!$B$4,{"Downside","Base","Upside"},0),SUM('Model - Downside'!$X$42:$AI$42),SUM('Model - Base'!$X$42:$AI$42),SUM('Model - Upside'!$X$42:$AI$42)) -> 235955.32 | E17: =CHOOSE(MATCH('Inputs'!$B$4,{"Downside","Base","Upside"},0),SUM('Model - Downside'!$AJ$42:$AU$42),SUM('Model - Base'!$AJ$42:$AU$42),SUM('Model - Upside'!$AJ$42:$AU$42)) -> 235317.28
A18: Operating Margin | B18: =IFERROR(B17/B8,0) -> -0.0063759958 | C18: =IFERROR(C17/C8,0) -> 0.2762951 | D18: =IFERROR(D17/D8,0) -> 0.29773344 | E18: =IFERROR(E17/E8,0) -> 0.29692835
A19: Operating Cash Generated | B19: =CHOOSE(MATCH('Inputs'!$B$4,{"Downside","Base","Upside"},0),SUM('Model - Downside'!$D$48:$K$48),SUM('Model - Base'!$D$48:$K$48),SUM('Model - Upside'!$D$48:$K$48)) -> -1263.1352 | C19: =CHOOSE(MATCH('Inputs'!$B$4,{"Downside","Base","Upside"},0),SUM('Model - Downside'!$L$48:$W$48),SUM('Model - Base'!$L$48:$W$48),SUM('Model - Upside'!$L$48:$W$48)) -> 204223.64 | D19: =CHOOSE(MATCH('Inputs'!$B$4,{"Downside","Base","Upside"},0),SUM('Model - Downside'!$X$48:$AI$48),SUM('Model - Base'!$X$48:$AI$48),SUM('Model - Upside'!$X$48:$AI$48)) -> 235955.32 | E19: =CHOOSE(MATCH('Inputs'!$B$4,{"Downside","Base","Upside"},0),SUM('Model - Downside'!$AJ$48:$AU$48),SUM('Model - Base'!$AJ$48:$AU$48),SUM('Model - Upside'!$AJ$48:$AU$48)) -> 235317.28
A20: Ending Cumulative Operating Cash | B20: =CHOOSE(MATCH('Inputs'!$B$4,{"Downside","Base","Upside"},0),'Model - Downside'!$K$49,'Model - Base'!$K$49,'Model - Upside'!$K$49) -> -1160.9052 | C20: =CHOOSE(MATCH('Inputs'!$B$4,{"Downside","Base","Upside"},0),'Model - Downside'!$W$49,'Model - Base'!$W$49,'Model - Upside'!$W$49) -> 203062.74 | D20: =CHOOSE(MATCH('Inputs'!$B$4,{"Downside","Base","Upside"},0),'Model - Downside'!$AI$49,'Model - Base'!$AI$49,'Model - Upside'!$AI$49) -> 439018.05 | E20: =CHOOSE(MATCH('Inputs'!$B$4,{"Downside","Base","Upside"},0),'Model - Downside'!$AU$49,'Model - Base'!$AU$49,'Model - Upside'!$AU$49) -> 674335.34
A21: Average Total Labor % | B21: =CHOOSE(MATCH('Inputs'!$B$4,{"Downside","Base","Upside"},0),AVERAGE('Model - Downside'!$D$26:$K$26),AVERAGE('Model - Base'!$D$26:$K$26),AVERAGE('Model - Upside'!$D$26:$K$26)) -> 0.49439592 | C21: =CHOOSE(MATCH('Inputs'!$B$4,{"Downside","Base","Upside"},0),AVERAGE('Model - Downside'!$L$26:$W$26),AVERAGE('Model - Base'!$L$26:$W$26),AVERAGE('Model - Upside'!$L$26:$W$26)) -> 0.28465332 | D21: =CHOOSE(MATCH('Inputs'!$B$4,{"Downside","Base","Upside"},0),AVERAGE('Model - Downside'!$X$26:$AI$26),AVERAGE('Model - Base'!$X$26:$AI$26),AVERAGE('Model - Upside'!$X$26:$AI$26)) -> 0.26756391 | E21: =CHOOSE(MATCH('Inputs'!$B$4,{"Downside","Base","Upside"},0),AVERAGE('Model - Downside'!$AJ$26:$AU$26),AVERAGE('Model - Base'!$AJ$26:$AU$26),AVERAGE('Model - Upside'!$AJ$26:$AU$26)) -> 0.26756391
A22: Average Smith Occupancy % | B22: =CHOOSE(MATCH('Inputs'!$B$4,{"Downside","Base","Upside"},0),AVERAGE('Model - Downside'!$D$35:$K$35),AVERAGE('Model - Base'!$D$35:$K$35),AVERAGE('Model - Upside'!$D$35:$K$35)) -> 0.27327652 | C22: =CHOOSE(MATCH('Inputs'!$B$4,{"Downside","Base","Upside"},0),AVERAGE('Model - Downside'!$L$35:$W$35),AVERAGE('Model - Base'!$L$35:$W$35),AVERAGE('Model - Upside'!$L$35:$W$35)) -> 0.097371187 | D22: =CHOOSE(MATCH('Inputs'!$B$4,{"Downside","Base","Upside"},0),AVERAGE('Model - Downside'!$X$35:$AI$35),AVERAGE('Model - Base'!$X$35:$AI$35),AVERAGE('Model - Upside'!$X$35:$AI$35)) -> 0.095 | E22: =CHOOSE(MATCH('Inputs'!$B$4,{"Downside","Base","Upside"},0),AVERAGE('Model - Downside'!$AJ$35:$AU$35),AVERAGE('Model - Base'!$AJ$35:$AU$35),AVERAGE('Model - Upside'!$AJ$35:$AU$35)) -> 0.095
A23: Average Consolidated Occupancy % | B23: =CHOOSE(MATCH('Inputs'!$B$4,{"Downside","Base","Upside"},0),AVERAGE('Model - Downside'!$D$34:$K$34),AVERAGE('Model - Base'!$D$34:$K$34),AVERAGE('Model - Upside'!$D$34:$K$34)) -> 0.23231342 | C23: =CHOOSE(MATCH('Inputs'!$B$4,{"Downside","Base","Upside"},0),AVERAGE('Model - Downside'!$L$34:$W$34),AVERAGE('Model - Base'!$L$34:$W$34),AVERAGE('Model - Upside'!$L$34:$W$34)) -> 0.15941225 | D23: =CHOOSE(MATCH('Inputs'!$B$4,{"Downside","Base","Upside"},0),AVERAGE('Model - Downside'!$X$34:$AI$34),AVERAGE('Model - Base'!$X$34:$AI$34),AVERAGE('Model - Upside'!$X$34:$AI$34)) -> 0.15312958 | E23: =CHOOSE(MATCH('Inputs'!$B$4,{"Downside","Base","Upside"},0),AVERAGE('Model - Downside'!$AJ$34:$AU$34),AVERAGE('Model - Base'!$AJ$34:$AU$34),AVERAGE('Model - Upside'!$AJ$34:$AU$34)) -> 0.15312958
A24: Founder Current Cash Salary | B24: =CHOOSE(MATCH('Inputs'!$B$4,{"Downside","Base","Upside"},0),SUM('Model - Downside'!$D$44:$K$44),SUM('Model - Base'!$D$44:$K$44),SUM('Model - Upside'!$D$44:$K$44)) -> 60000 | C24: =CHOOSE(MATCH('Inputs'!$B$4,{"Downside","Base","Upside"},0),SUM('Model - Downside'!$L$44:$W$44),SUM('Model - Base'!$L$44:$W$44),SUM('Model - Upside'!$L$44:$W$44)) -> 90000 | D24: =CHOOSE(MATCH('Inputs'!$B$4,{"Downside","Base","Upside"},0),SUM('Model - Downside'!$X$44:$AI$44),SUM('Model - Base'!$X$44:$AI$44),SUM('Model - Upside'!$X$44:$AI$44)) -> 90000 | E24: =CHOOSE(MATCH('Inputs'!$B$4,{"Downside","Base","Upside"},0),SUM('Model - Downside'!$AJ$44:$AU$44),SUM('Model - Base'!$AJ$44:$AU$44),SUM('Model - Upside'!$AJ$44:$AU$44)) -> 90000
A25: Founder Deferred Repayment | B25: =CHOOSE(MATCH('Inputs'!$B$4,{"Downside","Base","Upside"},0),SUM('Model - Downside'!$D$45:$K$45),SUM('Model - Base'!$D$45:$K$45),SUM('Model - Upside'!$D$45:$K$45)) -> 0 | C25: =CHOOSE(MATCH('Inputs'!$B$4,{"Downside","Base","Upside"},0),SUM('Model - Downside'!$L$45:$W$45),SUM('Model - Base'!$L$45:$W$45),SUM('Model - Upside'!$L$45:$W$45)) -> 0 | D25: =CHOOSE(MATCH('Inputs'!$B$4,{"Downside","Base","Upside"},0),SUM('Model - Downside'!$X$45:$AI$45),SUM('Model - Base'!$X$45:$AI$45),SUM('Model - Upside'!$X$45:$AI$45)) -> 0 | E25: =CHOOSE(MATCH('Inputs'!$B$4,{"Downside","Base","Upside"},0),SUM('Model - Downside'!$AJ$45:$AU$45),SUM('Model - Base'!$AJ$45:$AU$45),SUM('Model - Upside'!$AJ$45:$AU$45)) -> 0
A26: Ending Founder Deferred Balance | B26: =CHOOSE(MATCH('Inputs'!$B$4,{"Downside","Base","Upside"},0),'Model - Downside'!$K$47,'Model - Base'!$K$47,'Model - Upside'!$K$47) -> 0 | C26: =CHOOSE(MATCH('Inputs'!$B$4,{"Downside","Base","Upside"},0),'Model - Downside'!$W$47,'Model - Base'!$W$47,'Model - Upside'!$W$47) -> 0 | D26: =CHOOSE(MATCH('Inputs'!$B$4,{"Downside","Base","Upside"},0),'Model - Downside'!$AI$47,'Model - Base'!$AI$47,'Model - Upside'!$AI$47) -> 0 | E26: =CHOOSE(MATCH('Inputs'!$B$4,{"Downside","Base","Upside"},0),'Model - Downside'!$AU$47,'Model - Base'!$AU$47,'Model - Upside'!$AU$47) -> 0

Sheet Sensitivity
A1: Sensitivity — Decision Thresholds
A2: Formula-driven Base-case decision tables. Change Base assumptions on Inputs to refresh linked calculations.
A4: Airbnb weekends versus 5000 rent ($5,000 monthly)
A5: Airbnb Weekends | B5: Gross Revenue | C5: Variable Cost | D5: Net Contribution | E5: Rent Coverage Gap
A6: 1 | B6: =A6*'Inputs'!$E$48 -> 2400 | C6: =B6*'Inputs'!$E$12 -> 432 | D6: =B6-C6 -> 1968 | E6: =D6-'Inputs'!$E$47 -> -3032
A7: 2 | B7: =A7*'Inputs'!$E$48 -> 4800 | C7: =B7*'Inputs'!$E$12 -> 864 | D7: =B7-C7 -> 3936 | E7: =D7-'Inputs'!$E$47 -> -1064
A8: 3 | B8: =A8*'Inputs'!$E$48 -> 7200 | C8: =B8*'Inputs'!$E$12 -> 1296 | D8: =B8-C8 -> 5904 | E8: =D8-'Inputs'!$E$47 -> 904
A9: 4 | B9: =A9*'Inputs'!$E$48 -> 9600 | C9: =B9*'Inputs'!$E$12 -> 1728 | D9: =B9-C9 -> 7872 | E9: =D9-'Inputs'!$E$47 -> 2872
A10: 5 | B10: =A10*'Inputs'!$E$48 -> 12000 | C10: =B10*'Inputs'!$E$12 -> 2160 | D10: =B10-C10 -> 9840 | E10: =D10-'Inputs'!$E$47 -> 4840
A13: Smith required revenue by rent phase
A14: Rent Phase | B14: Smith Rent | C14: Utilities | D14: Occupancy Target | E14: Required Smith Revenue
A15: Sep 2026 | B15: ='Inputs'!$E$41 -> 400 | C15: ='Inputs'!$E$8*0 -> 0 | D15: ='Inputs'!$E$24 -> 0.095 | E15: =(B15+C15)/D15 -> 4210.5263
A16: Oct–Dec 2026 | B16: ='Inputs'!$E$42 -> 1800 | C16: ='Inputs'!$E$8*0 -> 0 | D16: ='Inputs'!$E$24 -> 0.095 | E16: =(B16+C16)/D16 -> 18947.368
A17: Jan–Feb 2027 | B17: ='Inputs'!$E$43 -> 2600 | C17: ='Inputs'!$E$8*0 -> 0 | D17: ='Inputs'!$E$24 -> 0.095 | E17: =(B17+C17)/D17 -> 27368.421
A18: Mar–May 2027 | B18: ='Inputs'!$E$43 -> 2600 | C18: ='Inputs'!$E$8 -> 1000 | D18: ='Inputs'!$E$24 -> 0.095 | E18: =(B18+C18)/D18 -> 37894.737
A19: Jun–Dec 2027 | B19: ='Inputs'!$E$44 -> 3400 | C19: ='Inputs'!$E$8 -> 1000 | D19: ='Inputs'!$E$24 -> 0.095 | E19: =(B19+C19)/D19 -> 46315.789
A20: Jan 2028 onward | B20: ='Inputs'!$E$45 -> 3963 | C20: ='Inputs'!$E$8 -> 1000 | D20: ='Inputs'!$E$24 -> 0.095 | E20: =(B20+C20)/D20 -> 52242.105
A23: Transactions/day by average ticket — Base Jan 2028 required storefront sales
A24: Required Storefront Revenue | B24: =MAX(0,'Model - Base'!S36-'Model - Base'!S7-'Model - Base'!S8) -> 44959.56
A26: Open Days / Month | B26: 16 | C26: 18 | D26: 20 | E26: 22 | F26: 24
A27: 20 | B27: =$B$24/(B$26*$A27) -> 140.49863 | C27: =$B$24/(C$26*$A27) -> 124.88767 | D27: =$B$24/(D$26*$A27) -> 112.3989 | E27: =$B$24/(E$26*$A27) -> 102.18082 | F27: =$B$24/(F$26*$A27) -> 93.665751
A28: 22 | B28: =$B$24/(B$26*$A28) -> 127.72602 | C28: =$B$24/(C$26*$A28) -> 113.53424 | D28: =$B$24/(D$26*$A28) -> 102.18082 | E28: =$B$24/(E$26*$A28) -> 92.891654 | F28: =$B$24/(F$26*$A28) -> 85.150683
A29: 24 | B29: =$B$24/(B$26*$A29) -> 117.08219 | C29: =$B$24/(C$26*$A29) -> 104.07306 | D29: =$B$24/(D$26*$A29) -> 93.665751 | E29: =$B$24/(E$26*$A29) -> 85.150683 | F29: =$B$24/(F$26*$A29) -> 78.054793
A33: Labor/revenue thresholds with 7500 founder compensation ($7,500/month)
A34: Monthly Revenue | B34: Direct Labor Rate | C34: Direct Labor | D34: Payroll Burden | E34: Founder Economic | F34: Total Labor | G34: Labor / Revenue
A35: 30000 | B35: ='Inputs'!$E$30 -> 0.14 | C35: =A35*B35 -> 4200 | D35: =C35*'Inputs'!$E$31 -> 420 | E35: ='Inputs'!$E$32 -> 7500 | F35: =SUM(C35:E35) -> 12120 | G35: =F35/A35 -> 0.404
A36: 40000 | B36: ='Inputs'!$E$30 -> 0.14 | C36: =A36*B36 -> 5600 | D36: =C36*'Inputs'!$E$31 -> 560 | E36: ='Inputs'!$E$32 -> 7500 | F36: =SUM(C36:E36) -> 13660 | G36: =F36/A36 -> 0.3415
A37: 50000 | B37: ='Inputs'!$E$30 -> 0.14 | C37: =A37*B37 -> 7000 | D37: =C37*'Inputs'!$E$31 -> 700 | E37: ='Inputs'!$E$32 -> 7500 | F37: =SUM(C37:E37) -> 15200 | G37: =F37/A37 -> 0.304
A38: 60000 | B38: ='Inputs'!$E$30 -> 0.14 | C38: =A38*B38 -> 8400 | D38: =C38*'Inputs'!$E$31 -> 840 | E38: ='Inputs'!$E$32 -> 7500 | F38: =SUM(C38:E38) -> 16740 | G38: =F38/A38 -> 0.279
A39: 70000 | B39: ='Inputs'!$E$30 -> 0.14 | C39: =A39*B39 -> 9800 | D39: =C39*'Inputs'!$E$31 -> 980 | E39: ='Inputs'!$E$32 -> 7500 | F39: =SUM(C39:E39) -> 18280 | G39: =F39/A39 -> 0.26114286

Sheet Sources
A1: Sources, Provenance & Disclosures
A2: Model facts are classified as Observed, Owner-defined, Modeled, or Unresolved. Owner-provided facts are dated 2026-09-24.
A4: As of | B4: Classification | C4: Source / fact | D4: Model treatment | E4: Decision caveat
A5: 2026-09-24 | B5: Owner-defined | C5: Owner-provided Smith rent schedule and Mar 2027 gas/electric/water transfer. | D5: Stepped rent: $400; $1,800; $2,600; $3,400; then $3,963 including $563 NNN. | E5: Lease begins Jun 2027.
A6: 2026-09-24 | B6: Owner-defined | C6: Owner-provided second-venue economics: $2,400 Airbnb weekend, events, and personal-chef packages. | D6: $5,000 rent begins Jan 2027 only if activated; Oct–Dec trial revenue is scaled. | E6: No supplied Oct–Dec trial rent; modeled at zero and unresolved.
A7: 2026-09-24 | B7: Owner-defined | C7: Owner-provided meal prep anchor: 4001 dollars per 28-day cycle ($4,001). | D7: Modeled monthly start is $4,334.42 using thirteen 28-day cycles divided by twelve months. | E7: Growth after the anchor is modeled.
A8: 2026-09-24 | B8: Observed | C8: Four-account snapshot supplied for broader business context. | D8: Retained as dated context; the model opening cash now uses the newer Local Pizza available balance. | E8: Not a complete balance sheet.
A9: 2026-10-01 | B9: Observed | C9: Local Budget posted, split-aware cash actuals through 2026-09-30 and Local Pizza balance synced 2026-10-01. | D9: Nine monthly series reproduced on Historical; Square advances are financing, not revenue; settlement remittances replace Debt placeholders in adjusted cash flow. | E9: May–Sep fixed/core other OpEx anchors the scenario range; purchases remain inventory purchasing, not consumed COGS.
A10: 2026-09-24 | B10: Owner-defined | C10: Smith houses meal prep; all frozen pizza is produced at Hopkins; Happy Monday sandwiches excluded. | D10: Only frozen-pizza revenue is modeled. | E10: No sandwich revenue is forecast.
A11: 2026-09-24 | B11: Modeled | C11: Downside, Base, and Upside operating assumptions. | D11: Editable yellow scenario cells drive meal growth, units, price, venue use, storefront, COGS, labor, and fixed OpEx. | E11: Scenarios are planning ranges, not observed demand.
A12: 2026-10-01 | B12: Unresolved | C12: Founder cash timing, opening founder deferred balance, and any backpay obligation. | D12: Oct 2026 cash-pay/backpay start, zero opening deferred balance, and zero monthly backpay are editable modeled defaults. | E12: No-backpay is not an owner fact; confirm pre-model balances.
A13: 2026-10-01 | B13: Observed | C13: Local Pizza available balance at model start. | D13: $102.23 available and $104.23 current, synced 2026-10-01; Local Pizza is the owner-confirmed primary business account. | E13: This is not a complete balance sheet or liquidity reserve.
A14: 2026-09-24 | B14: Modeled | C14: Storefront target-sales and cost-rate mechanics. | D14: Required sales solve from Smith occupancy target, then ramp 35/50/65/80/90/100%; fixed OpEx inflates 3% annually. | E14: Target-driven sales are illustrative, not a demand forecast.
A16: Financial model disclosure | B16: Internal planning financial model; not tax, legal, or accounting advice.
A17: Explicit exclusions: debt service and financing; income and sales taxes; inventory working capital; security deposits; and capital raises. The model also excludes any unconfirmed pre-model founder deferred compensation or back-pay balance until entered on Inputs.
